Workbook

Sheet Все позиции
A1: КП | B1: Дата КП | C1: Клиент | D1: Менеджер | E1: Статус КП | F1: Срок подачи КП | G1: № строки | H1: Номенклатура | I1: Аналог | J1: Адрес доставки | K1: Количество | L1: Ед. изм. | M1: Цена, ₽ | N1: Цена с НДС, ₽ | O1: Сумма, ₽ | P1: Сумма с НДС, ₽
A2: 00ЦБ-000001 | B2: 46033 | C2: Филиал ООО "АРГОС-Строй"-КЕДР | D2: Шарлаимова Валентина Афанасьевна | E2: Отменено | G2: 1 | H2: Труба фильтр-перфорированная для гидрогеологической скважины ГГС из трубы 57х4 | K2: 190 | L2: м | M2: 8346.5 | N2: 0 | O2: 1585835 | P2: 1934718.7
A3: 00ЦБ-000001 | B3: 46033 | C3: Филиал ООО "АРГОС-Строй"-КЕДР | D3: Шарлаимова Валентина Афанасьевна | E3: Отменено | G3: 2 | H3: Труба 76х4 ГОСТ 8732-78 09Г2С ГОСТ 8731-74 | K3: 0.028 | L3: т | M3: 227008.2 | N3: 0 | O3: 6356.23 | P3: 7754.6
A4: 00ЦБ-000001 | B4: 46033 | C4: Филиал ООО "АРГОС-Строй"-КЕДР | D4: Шарлаимова Валентина Афанасьевна | E4: Отменено | G4: 3 | H4: Труба 168х6 ГОСТ 8732-78 09Г2С ГОСТ 8731-74 | K4: 4.42 | L4: т | M4: 239725.41 | N4: 0 | O4: 1059586.3 | P4: 1292695.3
A5: 00ЦБ-000001 | B5: 46033 | C5: Филиал ООО "АРГОС-Строй"-КЕДР | D5: Шарлаимова Валентина Афанасьевна | E5: Отменено | G5: 4 | H5: Труба 57х4 ГОСТ 8732-78 09Г2С ГОСТ 8731-74 | K5: 3.171 | L5: т | M5: 227008.2 | N5: 0 | O5: 719843 | P5: 878208.46
A6: 00ЦБ-000001 | B6: 46033 | C6: Филиал ООО "АРГОС-Строй"-КЕДР | D6: Шарлаимова Валентина Афанасьевна | E6: Отменено | G6: 5 | H6: Уголок 50х50х5 ГОСТ 8509-93 С345 ГОСТ 27772-2021 KCV(-40)≥34Дж/см2 | K6: 0.009 | L6: т | M6: 99836.07 | N6: 0 | O6: 898.52 | P6: 1096.2
A7: 00ЦБ-000001 | B7: 46033 | C7: Филиал ООО "АРГОС-Строй"-КЕДР | D7: Шарлаимова Валентина Афанасьевна | E7: Отменено | G7: 6 | H7: Труба 108х4 ГОСТ 8732-78 09Г2С ГОСТ 8731-74 | K7: 0.032 | L7: т | M7: 227008.2 | N7: 0 | O7: 7264.26 | P7: 8862.4
A8: 00ЦБ-000001 | B8: 46033 | C8: Филиал ООО "АРГОС-Строй"-КЕДР | D8: Шарлаимова Валентина Афанасьевна | E8: Отменено | G8: 7 | H8: Труба 180х4 ГОСТ 8732-78 09Г2С ГОСТ 8731-74 | I8: Труба г/к 180х6 ГОСТ 8732-78 09Г2С ГОСТ 8731-74 | K8: 0.099 | L8: т | M8: 273122.96 | N8: 0 | O8: 27039.17 | P8: 32987.79
A9: 00ЦБ-000001 | B9: 46033 | C9: Филиал ООО "АРГОС-Строй"-КЕДР | D9: Шарлаимова Валентина Афанасьевна | E9: Отменено | G9: 8 | H9: Труба 180х5,5 ГОСТ 8732-78 09Г2С ГОСТ 8731-74 | I9: Труба г/к 180х6 ГОСТ 8732-78 09Г2С ГОСТ 8731-74 | K9: 0.063 | L9: т | M9: 273122.96 | N9: 0 | O9: 17206.75 | P9: 20992.23
A10: 00ЦБ-000001 | B10: 46033 | C10: Филиал ООО "АРГОС-Строй"-КЕДР | D10: Шарлаимова Валентина Афанасьевна | E10: Отменено | G10: 9 | H10: Лист Б-ПН-НО-5 ГОСТ 19903-2015 С345 ГОСТ 27772-2021 | K10: 0.033 | L10: т | M10: 102569.67 | N10: 0 | O10: 3384.8 | P10: 4129.46
A11: 00ЦБ-000001 | B11: 46033 | C11: Филиал ООО "АРГОС-Строй"-КЕДР | D11: Шарлаимова Валентина Афанасьевна | E11: Отменено | G11: 10 | H11: Арматура 6 А240 ГОСТ 34028-2016 | K11: 0.017 | L11: т | M11: 79631.14 | N11: 0 | O11: 1353.73 | P11: 1651.55
A12: 00ЦБ-000001 | B12: 46033 | C12: Филиал ООО "АРГОС-Строй"-КЕДР | D12: Шарлаимова Валентина Афанасьевна | E12: Отменено | G12: 11 | H12: Уголок 50х50х5 ГОСТ 8509-93 С345 ГОСТ 27772-2021 | K12: 0.015 | L12: т | M12: 99836.07 | N12: 0 | O12: 1497.54 | P12: 1827
A13: 00ЦБ-000001 | B13: 46033 | C13: Филиал ООО "АРГОС-Строй"-КЕДР | D13: Шарлаимова Валентина Афанасьевна | E13: Отменено | G13: 12 | H13: Труба 180х8 ГОСТ 8732-78 09Г2С ГОСТ 8731-74 | K13: 0.079 | L13: т | M13: 273122.96 | N13: 0 | O13: 21576.71 | P13: 26323.59
A14: 00ЦБ-000001 | B14: 46033 | C14: Филиал ООО "АРГОС-Строй"-КЕДР | D14: Шарлаимова Валентина Афанасьевна | E14: Отменено | G14: 13 | H14: Круг 58 ГОСТ 2590-2006 С345 ГОСТ 27772-2021 | K14: 0.042 | L14: т | M14: 110532.79 | N14: 0 | O14: 4642.38 | P14: 5663.7
A15: 00ЦБ-000001 | B15: 46033 | C15: Филиал ООО "АРГОС-Строй"-КЕДР | D15: Шарлаимова Валентина Афанасьевна | E15: Отменено | G15: 14 | H15: Лист Б-ПН-НО-3 ГОСТ 19903-2015 С345 ГОСТ 27772-2021 | K15: 0.011 | L15: т | M15: 99836.07 | N15: 0 | O15: 1098.2 | P15: 1339.8
A16: 00ЦБ-000001 | B16: 46033 | C16: Филиал ООО "АРГОС-Строй"-КЕДР | D16: Шарлаимова Валентина Афанасьевна | E16: Отменено | G16: 15 | H16: Пластина резиновая 1Ф-1-ТМКЩ-С-5 ГОСТ 7338-90 | K16: 56 | L16: шт | M16: 5968.77 | N16: 0 | O16: 334251.12 | P16: 407786.37
A17: 00ЦБ-000029 | B17: 46034 | C17: Филиал ООО "Аргос-Строй" Прометей | D17: Шарлаимова Валентина Афанасьевна | E17: Отменено | G17: 1 | H17: Задвижка стальная клиновая с выдвижным шпинделем, фланцевая (исп. F-E) из стали 20ГЛ, ХЛ1 DN80 PN250 с ручным управлением в комплекте с ответными флан | I17: Задвижка клиноваяс 31лс45нж Ду80 Ру250 ЗКЛ 080.250.01.Ф исп.RTG 16,5 по ASME, ст.20ГЛ, класс герм. А по ГОСТ 9544-2015 | K17: 1 | L17: шт | M17: 300401.33 | N17: 0 | O17: 300401.33 | P17: 366489.62
A18: 00ЦБ-000029 | B18: 46034 | C18: Филиал ООО "Аргос-Строй" Прометей | D18: Шарлаимова Валентина Афанасьевна | E18: Отменено | G18: 2 | H18: Задвижка стальная клиновая с выдвижным шпинделем, фланцевая (исп. F-E) из стали 20ГЛ, ХЛ1 DN150 PN250 с ручным управлением в комплекте с ответными фла | K18: 4 | L18: шт | M18: 0 | N18: 0 | O18: 0 | P18: 0
A19: 00ЦБ-000029 | B19: 46034 | C19: Филиал ООО "Аргос-Строй" Прометей | D19: Шарлаимова Валентина Афанасьевна | E19: Отменено | G19: 3 | H19: Затвор(клапан) обратный фланцевый из стали 20ГЛ в комплекте с ответными фланцами из стали 20А, ХЛ1 DN150 PN250 с прокладками и крепежом с приварными к | K19: 4 | L19: шт | M19: 0 | N19: 0 | O19: 0 | P19: 0
A20: 00ЦБ-000029 | B20: 46034 | C20: Филиал ООО "Аргос-Строй" Прометей | D20: Шарлаимова Валентина Афанасьевна | E20: Отменено | G20: 4 | H20: Трубы стальные бесшовные из стали 20А с внутренним антикоррозионным двухслойным порошковым эпоксидным покрытием ПЭП7150, Ø273х20-20А | I20: Труба г/к 273х20 ст13ХФА с внутренним однослойным эпоксидным покрытием по ТУ 1390-025-39929189-2020 (изм.1) ТРЭПП- ТР-90 МА (температура эксплуатации | K20: 124.8 | L20: т | M20: 65299.02 | N20: 0 | O20: 8149317.7 | P20: 9942167.6
A21: 00ЦБ-000029 | B21: 46034 | C21: Филиал ООО "Аргос-Строй" Прометей | D21: Шарлаимова Валентина Афанасьевна | E21: Отменено | G21: 5 | H21: Трубы стальные бесшовные из стали 20А с внутренним антикоррозионным двухслойным порошковым эпоксидным покрытием ПЭП7150, Ø168х14-20А | I21: Труба г/к 168х14 ст13ХФА с внутренним однослойным эпоксидным покрытием по ТУ 1390-025-39929189-2020 (изм.1) ТРЭПП- ТР-90 МА (температура эксплуатации | K21: 53.7 | L21: т | M21: 30028.67 | N21: 0 | O21: 1612539.6 | P21: 1967298.3
A22: 00ЦБ-000029 | B22: 46034 | C22: Филиал ООО "Аргос-Строй" Прометей | D22: Шарлаимова Валентина Афанасьевна | E22: Отменено | G22: 6 | H22: Трубы стальные бесшовные из стали 20А с внутренним антикоррозионным двухслойным порошковым эпоксидным покрытием ПЭП7150, Ø80х10-20А | I22: Труба г/к 89х10 ст13ХФА с внутренним однослойным эпоксидным покрытием по ТУ 1390-025-39929189-2020 (изм.1) ТРЭПП- ТР-90 МА (температура эксплуатации д | K22: 19.48 | L22: т | M22: 348023.78 | N22: 0 | O22: 6779503.2 | P22: 8270993.9
A23: 00ЦБ-000029 | B23: 46034 | C23: Филиал ООО "Аргос-Строй" Прометей | D23: Шарлаимова Валентина Афанасьевна | E23: Отменено | G23: 7 | H23: Отвод крутоизогнутый бесшовный приварной из стали 20А 90 - 273х20 - 20А | I23: Отвод 90 273х19 ст.13хфа ТУ с геометрией по ГОСТ 17375-01 | K23: 2 | L23: шт | M23: 66979.31 | N23: 0 | O23: 133958.62 | P23: 163429.52
A24: 00ЦБ-000029 | B24: 46034 | C24: Филиал ООО "Аргос-Строй" Прометей | D24: Шарлаимова Валентина Афанасьевна | E24: Отменено | G24: 8 | H24: Отвод крутоизогнутый бесшовный приварной из стали 20А 90 - 168х14 - 20А | I24: Отвод 90 168х14 ст.13хфа ТУ с геометрией по ГОСТ 17375-01 | K24: 13 | L24: шт | M24: 18855.95 | N24: 0 | O24: 245127.35 | P24: 299055.37
A25: 00ЦБ-000029 | B25: 46034 | C25: Филиал ООО "Аргос-Строй" Прометей | D25: Шарлаимова Валентина Афанасьевна | E25: Отменено | G25: 9 | H25: Переход концентрический бесшовный приварной из стали 20А К 168х14-133х18 - 20А | K25: 3 | L25: шт | M25: 0 | N25: 0 | O25: 0 | P25: 0
A26: 00ЦБ-000029 | B26: 46034 | C26: Филиал ООО "Аргос-Строй" Прометей | D26: Шарлаимова Валентина Афанасьевна | E26: Отменено | G26: 10 | H26: Переход концентрический бесшовный приварной из стали 20А К 273х20-168х14 - 20А | K26: 7 | L26: шт | M26: 0 | N26: 0 | O26: 0 | P26: 0
A27: 00ЦБ-000029 | B27: 46034 | C27: Филиал ООО "Аргос-Строй" Прометей | D27: Шарлаимова Валентина Афанасьевна | E27: Отменено | G27: 11 | H27: Тройник бесшовный приварной из стали 20А 273х20-168х14 | K27: 3 | L27: шт | M27: 0 | N27: 0 | O27: 0 | P27: 0
A28: 00ЦБ-000029 | B28: 46034 | C28: Филиал ООО "Аргос-Строй" Прометей | D28: Шарлаимова Валентина Афанасьевна | E28: Отменено | G28: 12 | H28: Опоры 273-КХ-А11 | K28: 4 | L28: шт | M28: 4789.54 | N28: 0 | O28: 19158.16 | P28: 23372.96
A29: 00ЦБ-000029 | B29: 46034 | C29: Филиал ООО "Аргос-Строй" Прометей | D29: Шарлаимова Валентина Афанасьевна | E29: Отменено | G29: 13 | H29: Опоры 159-КХ-А11 | K29: 4 | L29: шт | M29: 2266.77 | N29: 0 | O29: 9067.08 | P29: 11061.84
A30: 00ЦБ-000029 | B30: 46034 | C30: Филиал ООО "Аргос-Строй" Прометей | D30: Шарлаимова Валентина Афанасьевна | E30: Отменено | G30: 14 | H30: Втулка внутренней защиты сварного шва трубопровода CPS 273х20 | K30: 13 | L30: шт | M30: 0 | N30: 0 | O30: 0 | P30: 0
A31: 00ЦБ-000029 | B31: 46034 | C31: Филиал ООО "Аргос-Строй" Прометей | D31: Шарлаимова Валентина Афанасьевна | E31: Отменено | G31: 15 | H31: Втулка внутренней защиты сварного шва трубопровода CPS 168х14 | K31: 30 | L31: шт | M31: 0 | N31: 0 | O31: 0 | P31: 0
A32: 00ЦБ-000029 | B32: 46034 | C32: Филиал ООО "Аргос-Строй" Прометей | D32: Шарлаимова Валентина Афанасьевна | E32: Отменено | G32: 16 | H32: Втулка внутренней защиты сварного шва трубопровода CPS 89х6 | K32: 23 | L32: шт | M32: 0 | N32: 0 | O32: 0 | P32: 0
A33: 00ЦБ-000029 | B33: 46034 | C33: Филиал ООО "Аргос-Строй" Прометей | D33: Шарлаимова Валентина Афанасьевна | E33: Отменено | G33: 17 | H33: Спецдеталь СД.5 ПНГ-012-22-Р-ТХ.2-ОЛ-001 | K33: 3 | L33: шт | M33: 0 | N33: 0 | O33: 0 | P33: 0
A34: 00ЦБ-000029 | B34: 46034 | C34: Филиал ООО "Аргос-Строй" Прометей | D34: Шарлаимова Валентина Афанасьевна | E34: Отменено | G34: 18 | H34: Спецдеталь СД.6 ПНГ-012-22-Р-ТХ.2-ОЛ-001 | K34: 4 | L34: шт | M34: 0 | N34: 0 | O34: 0 | P34: 0
A35: 00ЦБ-000029 | B35: 46034 | C35: Филиал ООО "Аргос-Строй" Прометей | D35: Шарлаимова Валентина Афанасьевна | E35: Отменено | G35: 19 | H35: Спецдеталь СД.7 ПНГ-012-22-Р-ТХ.2-ОЛ-001 | K35: 4 | L35: шт | M35: 0 | N35: 0 | O35: 0 | P35: 0
A36: 00ЦБ-000029 | B36: 46034 | C36: Филиал ООО "Аргос-Строй" Прометей | D36: Шарлаимова Валентина Афанасьевна | E36: Отменено | G36: 20 | H36: Спецдеталь СД.8 ПНГ-012-22-Р-ТХ.2-ОЛ-001 | K36: 1 | L36: шт | M36: 0 | N36: 0 | O36: 0 | P36: 0
... A42: 00ЦБ-000004 | B42: 46035 | C42: Филиал ООО "АРГОС-Строй"-КЕДР | D42: Шарлаимова Валентина Афанасьевна | E42: Отменено | G42: 4 | H42: Трубопоршневая установка | K42: 1 | L42: комп | M42: 56550000 | N42: 0 | O42: 56550000 | P42: 68991000
A43: 00ЦБ-000004 | B43: 46035 | C43: Филиал ООО "АРГОС-Строй"-КЕДР | D43: Шарлаимова Валентина Афанасьевна | E43: Отменено | G43: 5 | H43: Задвижка клиновая фланцевая Ду 200 | I43: Задвижка клиновая литая с выдвижным шпинделем фланцевая (исп. F) ручная 30лс76нж DN 200 PN 6,3 МПа ХЛ1, корпус ст. 20ГЛ, класс герметичности «А» по ГО | K43: 3 | L43: шт | M43: 413844.27 | N43: 0 | O43: 1241532.8 | P43: 1514670
A44: 00ЦБ-000004 | B44: 46035 | C44: Филиал ООО "АРГОС-Строй"-КЕДР | D44: Шарлаимова Валентина Афанасьевна | E44: Отменено | G44: 6 | H44: Задвижка клиновая фланцевая Ду 200 с контролем протечек | I44: Задвижка клиновая литая с выдвижным шпинделем фланцевая (исп. F) ручная 30лс76нж DN 200 PN 6,3 МПа ХЛ1, корпус ст. 20ГЛ, класс герметичности «А» по ГО | K44: 1 | L44: шт | M44: 413844.27 | N44: 0 | O44: 413844.27 | P44: 504890.01
A45: 00ЦБ-000004 | B45: 46035 | C45: Филиал ООО "АРГОС-Строй"-КЕДР | D45: Шарлаимова Валентина Афанасьевна | E45: Отменено | G45: 7 | H45: Кран шаровой Ду15-Ду50 | K45: 18 | L45: шт | M45: 41165.73 | N45: 0 | O45: 740983.14 | P45: 903999.43
A46: 00ЦБ-000004 | B46: 46035 | C46: Филиал ООО "АРГОС-Строй"-КЕДР | D46: Шарлаимова Валентина Афанасьевна | E46: Отменено | G46: 8 | H46: Щелевое пробозаборное устройство | K46: 1 | L46: шт | M46: 297250 | N46: 0 | O46: 297250 | P46: 362645
A47: 00ЦБ-000004 | B47: 46035 | C47: Филиал ООО "АРГОС-Строй"-КЕДР | D47: Шарлаимова Валентина Афанасьевна | E47: Отменено | G47: 9 | H47: Манометр показывающий 6,0 МПа | I47: Манометр МП3-Уф 0-6 МПа кт.1,5 d.100 IP40 M20*1,5 РШ | K47: 3 | L47: шт | M47: 1135.35 | N47: 0 | O47: 3406.05 | P47: 4155.38
A48: 00ЦБ-000004 | B48: 46035 | C48: Филиал ООО "АРГОС-Строй"-КЕДР | D48: Шарлаимова Валентина Афанасьевна | E48: Отменено | G48: 10 | H48: Термометр показывающий | K48: 1 | L48: шт | M48: 0 | N48: 0 | O48: 0 | P48: 0
A49: 00ЦБ-000004 | B49: 46035 | C49: Филиал ООО "АРГОС-Строй"-КЕДР | D49: Шарлаимова Валентина Афанасьевна | E49: Отменено | G49: 11 | H49: Блок предохранительных клапанов | K49: 9 | L49: шт | M49: 1513655 | N49: 0 | O49: 13622895 | P49: 16619932
A50: 00ЦБ-000004 | B50: 46035 | C50: Филиал ООО "АРГОС-Строй"-КЕДР | D50: Шарлаимова Валентина Афанасьевна | E50: Отменено | G50: 12 | H50: Индикатор фазового состояния | I50: Индикатор фазового состояния потока ИФС-1В-700М (ДРФМ.414152.001ТУ) | K50: 3 | L50: комп | M50: 2711500 | N50: 0 | O50: 8134500 | P50: 9924090
A51: 00ЦБ-000004 | B51: 46035 | C51: Филиал ООО "АРГОС-Строй"-КЕДР | D51: Шарлаимова Валентина Афанасьевна | E51: Отменено | G51: 13 | H51: Расходомер - компаратор | K51: 2 | L51: шт | M51: 516584.25 | N51: 0 | O51: 1033168.5 | P51: 1260465.6
A52: 00ЦБ-000004 | B52: 46035 | C52: Филиал ООО "АРГОС-Строй"-КЕДР | D52: Шарлаимова Валентина Афанасьевна | E52: Отменено | G52: 14 | H52: Датчик давления (контроль протечек) | K52: 2 | L52: шт | M52: 0 | N52: 0 | O52: 0 | P52: 0
A53: 00ЦБ-000004 | B53: 46035 | C53: Филиал ООО "АРГОС-Строй"-КЕДР | D53: Шарлаимова Валентина Афанасьевна | E53: Отменено | G53: 15 | H53: Сигнализатор уровня | K53: 4 | L53: шт | M53: 76897.55 | N53: 0 | O53: 307590.2 | P53: 375260.04
A54: 00ЦБ-000004 | B54: 46035 | C54: Филиал ООО "АРГОС-Строй"-КЕДР | D54: Шарлаимова Валентина Афанасьевна | E54: Отменено | G54: 16 | H54: Модульное оборудование СЗО | K54: 10 | L54: комп | M54: 128890.5 | N54: 0 | O54: 1288905 | P54: 1572464.1
A55: 00ЦБ-000004 | B55: 46035 | C55: Филиал ООО "АРГОС-Строй"-КЕДР | D55: Шарлаимова Валентина Афанасьевна | E55: Отменено | G55: 17 | H55: Стационарный газоанализатор | K55: 14 | L55: шт | M55: 82127.04 | N55: 0 | O55: 1149778.6 | P55: 1402729.8
A56: 00ЦБ-000004 | B56: 46035 | C56: Филиал ООО "АРГОС-Строй"-КЕДР | D56: Шарлаимова Валентина Афанасьевна | E56: Отменено | G56: 18 | H56: Преобразователь избыточного давления | K56: 5 | L56: шт | M56: 0 | N56: 0 | O56: 0 | P56: 0
A57: 00ЦБ-000004 | B57: 46035 | C57: Филиал ООО "АРГОС-Строй"-КЕДР | D57: Шарлаимова Валентина Афанасьевна | E57: Отменено | G57: 19 | H57: Расходомер ультразвуковой | K57: 1 | L57: шт | M57: 0 | N57: 0 | O57: 0 | P57: 0
A58: 00ЦБ-000004 | B58: 46035 | C58: Филиал ООО "АРГОС-Строй"-КЕДР | D58: Шарлаимова Валентина Афанасьевна | E58: Отменено | G58: 20 | H58: Уровнемер | K58: 4 | L58: шт | M58: 305926.23 | N58: 0 | O58: 1223704.9 | P58: 1492920
A59: 00ЦБ-000004 | B59: 46035 | C59: Филиал ООО "АРГОС-Строй"-КЕДР | D59: Шарлаимова Валентина Афанасьевна | E59: Отменено | G59: 21 | H59: Сигнализатор уровня | K59: 3 | L59: шт | M59: 76897.55 | N59: 0 | O59: 230692.65 | P59: 281445.03
A60: 00ЦБ-000004 | B60: 46035 | C60: Филиал ООО "АРГОС-Строй"-КЕДР | D60: Шарлаимова Валентина Афанасьевна | E60: Отменено | G60: 22 | H60: Преобразователь избыточного давления | K60: 3 | L60: шт | M60: 0 | N60: 0 | O60: 0 | P60: 0
A61: 00ЦБ-000004 | B61: 46035 | C61: Филиал ООО "АРГОС-Строй"-КЕДР | D61: Шарлаимова Валентина Афанасьевна | E61: Отменено | G61: 23 | H61: НКУ-0,4кВ | K61: 1 | L61: комп | M61: 856225 | N61: 0 | O61: 856225 | P61: 1044594.5
A62: 00ЦБ-000004 | B62: 46035 | C62: Филиал ООО "АРГОС-Строй"-КЕДР | D62: Шарлаимова Валентина Афанасьевна | E62: Отменено | G62: 24 | H62: ИБП | K62: 2 | L62: шт | M62: 1899210 | N62: 0 | O62: 3798420 | P62: 4634072.4
A63: 00ЦБ-000004 | B63: 46035 | C63: Филиал ООО "АРГОС-Строй"-КЕДР | D63: Шарлаимова Валентина Афанасьевна | E63: Отменено | G63: 25 | H63: Шкаф ИБП | K63: 1 | L63: комп | M63: 2222415 | N63: 0 | O63: 2222415 | P63: 2711346.3
A64: 00ЦБ-000004 | B64: 46035 | C64: Филиал ООО "АРГОС-Строй"-КЕДР | D64: Шарлаимова Валентина Афанасьевна | E64: Отменено | G64: 26 | H64: Электроприводы и щиты управления задвижками Ду700 | I64: ЩСУ-П5.1-2 | K64: 2 | L64: шт | M64: 33350 | N64: 0 | O64: 66700 | P64: 81374
A65: 00ЦБ-000004 | B65: 46035 | C65: Филиал ООО "АРГОС-Строй"-КЕДР | D65: Шарлаимова Валентина Афанасьевна | E65: Отменено | G65: 27 | H65: Тепловая завеса со шкафом управления | I65: Завеса воздушная AeroBlast-K-330-07RE27B | K65: 1 | L65: комп | M65: 628853.4 | N65: 0 | O65: 628853.4 | P65: 767201.15
A66: 00ЦБ-000004 | B66: 46035 | C66: Филиал ООО "АРГОС-Строй"-КЕДР | D66: Шарлаимова Валентина Афанасьевна | E66: Отменено | G66: 28 | H66: Шкаф ИБП2 | K66: 1 | L66: комп | M66: 3875850 | N66: 0 | O66: 3875850 | P66: 4728537
A67: 00ЦБ-000004 | B67: 46035 | C67: Филиал ООО "АРГОС-Строй"-КЕДР | D67: Шарлаимова Валентина Афанасьевна | E67: Отменено | G67: 29 | H67: ШКАФЫ СИСТЕМЫ КТСО | K67: 1 | L67: комп | M67: 0 | N67: 0 | O67: 0 | P67: 0
A68: 00ЦБ-000004 | B68: 46035 | C68: Филиал ООО "АРГОС-Строй"-КЕДР | D68: Шарлаимова Валентина Афанасьевна | E68: Отменено | G68: 30 | H68: Комплект АСУ ТП СИКН (СОИ, ПСП) | K68: 1 | L68: комп | M68: 0 | N68: 0 | O68: 0 | P68: 0
A69: 00ЦБ-000004 | B69: 46035 | C69: Филиал ООО "АРГОС-Строй"-КЕДР | D69: Шарлаимова Валентина Афанасьевна | E69: Отменено | G69: 31 | H69: Межсетевой экран | K69: 2 | L69: комп | M69: 1531926.2 | N69: 0 | O69: 3063852.4 | P69: 3737899.9
A70: 00ЦБ-000004 | B70: 46035 | C70: Филиал ООО "АРГОС-Строй"-КЕДР | D70: Шарлаимова Валентина Афанасьевна | E70: Отменено | G70: 32 | H70: Шкаф связи | K70: 1 | L70: компл | M70: 0 | N70: 0 | O70: 0 | P70: 0
A71: 00ЦБ-000004 | B71: 46035 | C71: Филиал ООО "АРГОС-Строй"-КЕДР | D71: Шарлаимова Валентина Афанасьевна | E71: Отменено | G71: 33 | H71: АРМ АСКИД | K71: 1 | L71: шт | M71: 0 | N71: 0 | O71: 0 | P71: 0
A72: 00ЦБ-000004 | B72: 46035 | C72: Филиал ООО "АРГОС-Строй"-КЕДР | D72: Шарлаимова Валентина Афанасьевна | E72: Отменено | G72: 34 | H72: Стол оператора | K72: 1 | L72: шт | M72: 1416650 | N72: 0 | O72: 1416650 | P72: 1728313
A73: 00ЦБ-000004 | B73: 46035 | C73: Филиал ООО "АРГОС-Строй"-КЕДР | D73: Шарлаимова Валентина Афанасьевна | E73: Отменено | G73: 35 | H73: Система обнаружения утечек | K73: 1 | L73: комп | M73: 0 | N73: 0 | O73: 0 | P73: 0
A74: 00ЦБ-000005 | B74: 46035 | C74: Филиал ООО "АРГОС-Строй"-СТПС | D74: Шарлаимова Валентина Афанасьевна | E74: Отменено | G74: 1 | H74: Провод СИП-3 1х95 | K74: 2.58 | L74: км | M74: 166759.5 | N74: 0 | O74: 430239.51 | P74: 524892.2
A75: 00ЦБ-000010 | B75: 46036 | C75: Филиал ООО "АРГОС-Строй"-СТПС | D75: Шарлаимова Валентина Афанасьевна | E75: Отменено | G75: 1 | H75: Интеллектуальный датчик давления | I75: Преобразователь давления измерительный ПД200-ДИ6,0-115-0,25-2-Н-ЕХ | K75: 3 | L75: шт | M75: 66787 | N75: 0 | O75: 200361 | P75: 244440.42
A76: 00ЦБ-000010 | B76: 46036 | C76: Филиал ООО "АРГОС-Строй"-СТПС | D76: Шарлаимова Валентина Афанасьевна | E76: Отменено | G76: 2 | H76: Клапанный блок резьбовой с двумя вентилями | I76: Клапанный блок SS-2R, SFМ20х1,5-MМ20х1,5 (внутр., накидная гайканаруж.), материал - нержавеющая сталь, макс. рабочее давление - 40,0МПа | K76: 3 | L76: шт | M76: 7487.7 | N76: 0 | O76: 22463.1 | P76: 27404.98
A77: 00ЦБ-000010 | B77: 46036 | C77: Филиал ООО "АРГОС-Строй"-СТПС | D77: Шарлаимова Валентина Афанасьевна | E77: Отменено | G77: 3 | H77: КВВГЭнг(A)-ХЛ 4х1,5 | I77: Кабель КВВГЭнг(А)-LS-ХЛ 4х1,5 (ГОСТ) | K77: 1.259 | L77: км | M77: 106640.25 | N77: 0 | O77: 134260.07 | P77: 163797.29
A78: 00ЦБ-000010 | B78: 46036 | C78: Филиал ООО "АРГОС-Строй"-СТПС | D78: Шарлаимова Валентина Афанасьевна | E78: Отменено | G78: 4 | H78: КВВГЭнг(A)-ХЛ 5х1,5 | I78: Кабель КВВГЭнг(А)-LS-ХЛ 5х1,5 (ГОСТ) | K78: 0.421 | L78: км | M78: 138206.75 | N78: 0 | O78: 58185.04 | P78: 70985.75
A79: 00ЦБ-000010 | B79: 46036 | C79: Филиал ООО "АРГОС-Строй"-СТПС | D79: Шарлаимова Валентина Афанасьевна | E79: Отменено | G79: 5 | H79: КВВГЭнг(A)-ХЛ 7х1,5 | I79: Кабель КВВГЭнг(А)-LS-ХЛ 7х1,5 (ГОСТ) | K79: 0.414 | L79: км | M79: 184906.9 | N79: 0 | O79: 76551.46 | P79: 93392.78
A80: 00ЦБ-000010 | B80: 46036 | C80: Филиал ООО "АРГОС-Строй"-СТПС | D80: Шарлаимова Валентина Афанасьевна | E80: Отменено | G80: 6 | H80: КВВГЭнг(A)-ХЛ 10х1,5 | I80: Кабель КВВГЭнг(А)-LS-ХЛ 10х1,5 (ГОСТ) | K80: 1.265 | L80: км | M80: 251045.75 | N80: 0 | O80: 317572.87 | P80: 387438.9
A81: 00ЦБ-000010 | B81: 46036 | C81: Филиал ООО "АРГОС-Строй"-СТПС | D81: Шарлаимова Валентина Афанасьевна | E81: Отменено | G81: 7 | H81: КВВГЭнг(A)-ХЛ 14х1,5 | I81: Кабель КВВГЭнг(А)-LS-ХЛ 14х1,5 (ГОСТ) | K81: 0.414 | L81: км | M81: 351656.9 | N81: 0 | O81: 145585.96 | P81: 177614.87
A82: 00ЦБ-000010 | B82: 46036 | C82: Филиал ООО "АРГОС-Строй"-СТПС | D82: Шарлаимова Валентина Афанасьевна | E82: Отменено | G82: 8 | H82: Кабель "Витая пара" FTP cat5e 2x2x1,5 | I82: Витая пара F/UTP кат 5e 4х2хAWG24 | K82: 0.414 | L82: км | M82: 26.33 | N82: 0 | O82: 10.9 | P82: 13.3
A83: 00ЦБ-000010 | B83: 46036 | C83: Филиал ООО "АРГОС-Строй"-СТПС | D83: Шарлаимова Валентина Афанасьевна | E83: Отменено | G83: 9 | H83: Провод с поливинилхлоридной изоляцией с медной жилой на напряжение до 380В ПуГВ 1х4 | K83: 0.015 | L83: км | M83: 68672 | N83: 0 | O83: 1030.08 | P83: 1256.7
A84: 00ЦБ-000010 | B84: 46036 | C84: Филиал ООО "АРГОС-Строй"-СТПС | D84: Шарлаимова Валентина Афанасьевна | E84: Отменено | G84: 10 | H84: Металлорукав РЗ-Ц-П-15 | K84: 15 | L84: м | M84: 80.16 | N84: 0 | O84: 1202.4 | P84: 1466.93
A85: 00ЦБ-000010 | B85: 46036 | C85: Филиал ООО "АРГОС-Строй"-СТПС | D85: Шарлаимова Валентина Афанасьевна | E85: Отменено | G85: 11 | H85: Металлорукав РЗ-Ц-П-20 | K85: 4 | L85: м | M85: 117.03 | N85: 0 | O85: 468.12 | P85: 571.11
A86: 00ЦБ-000010 | B86: 46036 | C86: Филиал ООО "АРГОС-Строй"-СТПС | D86: Шарлаимова Валентина Афанасьевна | E86: Отменено | G86: 12 | H86: Металлорукав РЗ-Ц-П-25 | K86: 10 | L86: м | M86: 177.67 | N86: 0 | O86: 1776.7 | P86: 2167.57
A87: 00ЦБ-000010 | B87: 46036 | C87: Филиал ООО "АРГОС-Строй"-СТПС | D87: Шарлаимова Валентина Афанасьевна | E87: Отменено | G87: 13 | H87: Термочехол взрывозащищенный | K87: 2 | L87: шт | M87: 29000 | N87: 0 | O87: 58000 | P87: 70760
A88: 00ЦБ-000010 | B88: 46036 | C88: Филиал ООО "АРГОС-Строй"-СТПС | D88: Шарлаимова Валентина Афанасьевна | E88: Отменено | G88: 14 | H88: Коробка зажимов КЗП2.2-25/10-(Л-5М-М20-КЗ)х2(А)-(Л-5М-М20-КЗ)x1(С)-1ExeIIT6Gb-В1,5 | I88: Коробка соединительная взрывозащищенная К-СП 12.12.09 24/10 2ВЛм1-М20/МР20(А) 1ВЛм1-М20/МР20(В) УХЛ1 1ExeIIT5Gb IP66 | K88: 1 | L88: шт | M88: 4785 | N88: 0 | O88: 4785 | P88: 5837.7
A89: 00ЦБ-000010 | B89: 46036 | C89: Филиал ООО "АРГОС-Строй"-СТПС | D89: Шарлаимова Валентина Афанасьевна | E89: Отменено | G89: 15 | H89: Муфта для металлорукава: наружная резьба диаметр условного прохода 15мм, метрическая резьба М20x1,5 | K89: 8 | L89: шт | M89: 1317.35 | N89: 0 | O89: 10538.8 | P89: 12857.34
A90: 00ЦБ-000010 | B90: 46036 | C90: Филиал ООО "АРГОС-Строй"-СТПС | D90: Шарлаимова Валентина Афанасьевна | E90: Отменено | G90: 16 | H90: Муфта для металлорукава: наружная резьба диаметр условного прохода 20мм, метрическая резьба М25x1,5 | K90: 2 | L90: шт | M90: 1661.93 | N90: 0 | O90: 3323.86 | P90: 4055.11
A91: 00ЦБ-000010 | B91: 46036 | C91: Филиал ООО "АРГОС-Строй"-СТПС | D91: Шарлаимова Валентина Афанасьевна | E91: Отменено | G91: 17 | H91: Муфта для металлорукава: наружная резьба диаметр условного прохода 25мм, метрическая резьба М32x1,5 | K91: 4 | L91: шт | M91: 2627.99 | N91: 0 | O91: 10511.96 | P91: 12824.59
A92: 00ЦБ-000010 | B92: 46036 | C92: Филиал ООО "АРГОС-Строй"-СТПС | D92: Шарлаимова Валентина Афанасьевна | E92: Отменено | G92: 18 | H92: Шайба рифленая метрическая резьба М20x1,5 | I92: Шайба DIN 125 М20 плоская покрытие цинк | K92: 8 | L92: шт | M92: 9.5 | N92: 0 | O92: 76 | P92: 92.72
A93: 00ЦБ-000010 | B93: 46036 | C93: Филиал ООО "АРГОС-Строй"-СТПС | D93: Шарлаимова Валентина Афанасьевна | E93: Отменено | G93: 19 | H93: Шайба рифленая метрическая резьба М25x1,5 | I93: Плоская шайба DIN125 А М24 | K93: 2 | L93: шт | M93: 36.25 | N93: 0 | O93: 72.5 | P93: 88.45
A94: 00ЦБ-000010 | B94: 46036 | C94: Филиал ООО "АРГОС-Строй"-СТПС | D94: Шарлаимова Валентина Афанасьевна | E94: Отменено | G94: 20 | H94: Шайба рифленая метрическая резьба М32x1,5 | I94: Шайба DIN 125 М32 | K94: 4 | L94: шт | M94: 50.75 | N94: 0 | O94: 203 | P94: 247.66
A95: 00ЦБ-000010 | B95: 46036 | C95: Филиал ООО "АРГОС-Строй"-СТПС | D95: Шарлаимова Валентина Афанасьевна | E95: Отменено | G95: 21 | H95: Секция прямая 100x100x3000мм ONL 100х100, арт.0N0101830012 | I95: Лоток неперфорированный 100х100х3000 | K95: 42 | L95: шт | M95: 2494.03 | N95: 0 | O95: 104749.26 | P95: 127794.1
A96: 00ЦБ-000010 | B96: 46036 | C96: Филиал ООО "АРГОС-Строй"-СТПС | D96: Шарлаимова Валентина Афанасьевна | E96: Отменено | G96: 22 | H96: Секция угловая горизонтальная поворота трассы на 90гр, 100x100 мм ONL 100х100 U90, арт.0N01018U9015 | I96: Поворот на 90 градусов 100х100 мм | K96: 12 | L96: шт | M96: 901.73 | N96: 0 | O96: 10820.76 | P96: 13201.33
A97: 00ЦБ-000010 | B97: 46036 | C97: Филиал ООО "АРГОС-Строй"-СТПС | D97: Шарлаимова Валентина Афанасьевна | E97: Отменено | G97: 23 | H97: Секция тройниковая, 100x100 мм ONL 100х100 Т, арт.0N01018Т0015 | I97: Разветвитель Т-образный 100х100 | K97: 4 | L97: шт | M97: 1479.96 | N97: 0 | O97: 5919.84 | P97: 7222.2
A98: 00ЦБ-000010 | B98: 46036 | C98: Филиал ООО "АРГОС-Строй"-СТПС | D98: Шарлаимова Валентина Афанасьевна | E98: Отменено | G98: 24 | H98: Крышка лотка прямого 100х3000 мм KL 100, арт.KL0100030012 | I98: Крышка на лоток основание 100 | K98: 42 | L98: шт | M98: 1902.34 | N98: 0 | O98: 79898.28 | P98: 97475.9
A99: 00ЦБ-000010 | B99: 46036 | C99: Филиал ООО "АРГОС-Строй"-СТПС | D99: Шарлаимова Валентина Афанасьевна | E99: Отменено | G99: 25 | H99: Крышка лотка углового горизонтальный поворота трассы на 90°, ширина 100 мм KL 100 U90, арт.KL01000U9010 | I99: Крышка поворота плавн. 90град | K99: 12 | L99: шт | M99: 827.69 | N99: 0 | O99: 9932.28 | P99: 12117.38
A100: 00ЦБ-000010 | B100: 46036 | C100: Филиал ООО "АРГОС-Строй"-СТПС | D100: Шарлаимова Валентина Афанасьевна | E100: Отменено | G100: 26 | H100: Крышка лотка тройникового, ширина 100 мм KL 100 T, арт.KL01000T0010 | I100: Крышка разв. Т-обр. плавн. | K100: 4 | L100: шт | M100: 1047.42 | N100: 0 | O100: 4189.68 | P100: 5111.41
A101: 00ЦБ-000010 | B101: 46036 | C101: Филиал ООО "АРГОС-Строй"-СТПС | D101: Шарлаимова Валентина Афанасьевна | E101: Отменено | G101: 27 | H101: Пластина заземления ПТСЕ арт. ON0000006615 латунь | I101: Пластина для заземления PTCE никелированная | K101: 42 | L101: шт | M101: 113.61 | N101: 0 | O101: 4771.62 | P101: 5821.38
A102: 00ЦБ-000010 | B102: 46036 | C102: Филиал ООО "АРГОС-Строй"-СТПС | D102: Шарлаимова Валентина Афанасьевна | E102: Отменено | G102: 28 | H102: Швеллер перфорированный ШП 60х35 | K102: 1 | L102: м | M102: 1756.04 | N102: 0 | O102: 1756.04 | P102: 2142.37
A103: 00ЦБ-000011 | B103: 46036 | C103: Филиал ООО "АРГОС-Строй"-СТПС | D103: Шарлаимова Валентина Афанасьевна | E103: Отменено | G103: 1 | H103: Силовой трехполюсной автоматический выключатель ВА57Ф35-340010-16А-160-400АС | K103: 1 | L103: шт | M103: 4256.13 | N103: 0 | O103: 4256.13 | P103: 5192.48
A104: 00ЦБ-000011 | B104: 46036 | C104: Филиал ООО "АРГОС-Строй"-СТПС | D104: Шарлаимова Валентина Афанасьевна | E104: Отменено | G104: 2 | H104: Стойка кабельная горячеоцинкованная, S2,5 мм, H=400 мм, К1150 УТ1,5 | K104: 55 | L104: шт | M104: 333.76 | N104: 0 | O104: 18356.8 | P104: 22395.3
A105: 00ЦБ-000011 | B105: 46036 | C105: Филиал ООО "АРГОС-Строй"-СТПС | D105: Шарлаимова Валентина Афанасьевна | E105: Отменено | G105: 3 | H105: Полка кабельная горячеоцинкованная, S2,0 мм, L=450 мм, К1163 УТ1,5 | K105: 110 | L105: шт | M105: 693.54 | N105: 0 | O105: 76289.4 | P105: 93073.07
...

Sheet Со сроком подачи КП
A1: КП | B1: Дата КП | C1: Клиент | D1: Менеджер | E1: Статус КП | F1: Срок подачи КП | G1: № строки | H1: Номенклатура | I1: Аналог | J1: Адрес доставки | K1: Количество | L1: Ед. изм. | M1: Цена, ₽ | N1: Цена с НДС, ₽ | O1: Сумма, ₽ | P1: Сумма с НДС, ₽
A2: 00ЦБ-000455 | B2: 46204 | C2: Филиал ООО "АРГОС-Строй"-КЕДР | D2: Шарлаимова Валентина Афанасьевна | E2: Отменено | F2: 46218 | G2: 1 | H2: Выключатель однополюсный Viva, 2 модуль, белый, код 45021 | K2: 39 | L2: шт | M2: 1010.61 | N2: 0 | O2: 39413.79 | P2: 48084.82
A3: 00ЦБ-000455 | B3: 46204 | C3: Филиал ООО "АРГОС-Строй"-КЕДР | D3: Шарлаимова Валентина Афанасьевна | E3: Отменено | F3: 46218 | G3: 2 | H3: Выключатель однополюсный, одноклавишный, настенный, IP66, номинальный ток-20А, номинальное напряжение-250 | K3: 5 | L3: шт | M3: 3358.91 | N3: 0 | O3: 16794.55 | P3: 20489.35
A4: 00ЦБ-000455 | B4: 46204 | C4: Филиал ООО "АРГОС-Строй"-КЕДР | D4: Шарлаимова Валентина Афанасьевна | E4: Отменено | F4: 46218 | G4: 3 | H4: Заглушка на 1 модуль, Viva, белая арт.45016 | K4: 11 | L4: шт | M4: 67.97 | N4: 0 | O4: 747.67 | P4: 912.16
A5: 00ЦБ-000455 | B5: 46204 | C5: Филиал ООО "АРГОС-Строй"-КЕДР | D5: Шарлаимова Валентина Афанасьевна | E5: Отменено | F5: 46218 | G5: 4 | H5: Изолятор 2РС для наконечника, для кабелей сечением 4-6 мм2 | K5: 30 | L5: шт | M5: 10.14 | N5: 0 | O5: 304.2 | P5: 371.12
A6: 00ЦБ-000455 | B6: 46204 | C6: Филиал ООО "АРГОС-Строй"-КЕДР | D6: Шарлаимова Валентина Афанасьевна | E6: Отменено | F6: 46218 | G6: 5 | H6: Изолятор для наконечников по типу 2PD, для кабелей сечением 10 мм2 | K6: 40 | L6: шт | M6: 14.18 | N6: 0 | O6: 567.2 | P6: 691.98
A7: 00ЦБ-000455 | B7: 46204 | C7: Филиал ООО "АРГОС-Строй"-КЕДР | D7: Шарлаимова Валентина Афанасьевна | E7: Отменено | F7: 46218 | G7: 6 | H7: Изолятор для наконечников по типу 2РВ, для кабелей сечением 2,5 мм2 | K7: 145 | L7: шт | M7: 6.26 | N7: 0 | O7: 907.7 | P7: 1107.39
A8: 00ЦБ-000455 | B8: 46204 | C8: Филиал ООО "АРГОС-Строй"-КЕДР | D8: Шарлаимова Валентина Афанасьевна | E8: Отменено | F8: 46218 | G8: 7 | H8: Изолятор для наконечников по типу 2РС, для кабелей сечением 4-6 мм2 | K8: 115 | L8: шт | M8: 10.14 | N8: 0 | O8: 1166.1 | P8: 1422.64
A9: 00ЦБ-000455 | B9: 46204 | C9: Филиал ООО "АРГОС-Строй"-КЕДР | D9: Шарлаимова Валентина Афанасьевна | E9: Отменено | F9: 46218 | G9: 8 | H9: Кабельный ввод для коробок по типу 305315.001 | K9: 9 | L9: шт | M9: 262.4 | N9: 0 | O9: 2361.6 | P9: 2881.15
A10: 00ЦБ-000455 | B10: 46204 | C10: Филиал ООО "АРГОС-Строй"-КЕДР | D10: Шарлаимова Валентина Афанасьевна | E10: Отменено | F10: 46218 | G10: 9 | H10: Клеммник винтовой по типу TU150-2-GY для кабеля сечением 150 мм2 | K10: 20 | L10: шт | M10: 2141.95 | N10: 0 | O10: 42839 | P10: 52263.58
A11: 00ЦБ-000455 | B11: 46204 | C11: Филиал ООО "АРГОС-Строй"-КЕДР | D11: Шарлаимова Валентина Афанасьевна | E11: Отменено | F11: 46218 | G11: 10 | H11: Клеммник винтовой по типу TU240-2-GY для кабеля сечением 240 мм2 | K11: 50 | L11: шт | M11: 3396.8 | N11: 0 | O11: 169840 | P11: 207204.8
A12: 00ЦБ-000455 | B12: 46204 | C12: Филиал ООО "АРГОС-Строй"-КЕДР | D12: Шарлаимова Валентина Афанасьевна | E12: Отменено | F12: 46218 | G12: 11 | H12: Клеммник винтовой по типу TU50-2-BU для кабеля сечением 16-70 мм2, синий | K12: 20 | L12: шт | M12: 546.98 | N12: 0 | O12: 10939.6 | P12: 13346.31
A13: 00ЦБ-000455 | B13: 46204 | C13: Филиал ООО "АРГОС-Строй"-КЕДР | D13: Шарлаимова Валентина Афанасьевна | E13: Отменено | F13: 46218 | G13: 12 | H13: Клеммник винтовой по типу TU50-2-GY для кабеля сечением 16-70 мм2, серый | K13: 20 | L13: шт | M13: 546.98 | N13: 0 | O13: 10939.6 | P13: 13346.31
... A139: 00ЦБ-000482 | B139: 46212 | C139: Филиал ООО "Аргос-Строй" Прометей | D139: Шарлаимова Валентина Афанасьевна | E139: Отменено | F139: 46218 | G139: 2 | H139: Гайка М30 ГОСТ ISO 4032-2014 | K139: 40 | L139: шт | M139: 66.83 | N139: 0 | O139: 2673.2 | P139: 3261.3
A140: 00ЦБ-000482 | B140: 46212 | C140: Филиал ООО "Аргос-Строй" Прометей | D140: Шарлаимова Валентина Афанасьевна | E140: Отменено | F140: 46218 | G140: 3 | H140: Мачта прожекторная ВГН-16 02-3647-Р455-С027-ЭС.ОЛ4 | I140: Мачта МГФ-16-I-СП-2,1х1,4-МО-4-ОП2(09Г2С,Г\Ц) | K140: 1 | L140: шт | M140: 636100.83 | N140: 0 | O140: 636100.83 | P140: 776043.01
A141: 00ЦБ-000482 | B141: 46212 | C141: Филиал ООО "Аргос-Строй" Прометей | D141: Шарлаимова Валентина Афанасьевна | E141: Отменено | F141: 46218 | G141: 4 | H141: Опора освещения ОГКС-10,5 02-3647-Р455-С027-ЭС.ОЛ3 | I141: Опора ОГКСкл-10,5(100/225-4) фл.К400-мц 4х32-300 | K141: 2 | L141: шт | M141: 102963.73 | N141: 0 | O141: 205927.46 | P141: 251231.5
A142: 00ЦБ-000482 | B142: 46212 | C142: Филиал ООО "Аргос-Строй" Прометей | D142: Шарлаимова Валентина Афанасьевна | E142: Отменено | F142: 46218 | G142: 5 | H142: Шайба 12 ГОСТ 11371-78 | K142: 192 | L142: шт | M142: 2.2 | N142: 0 | O142: 422.4 | P142: 515.33
A143: 00ЦБ-000482 | B143: 46212 | C143: Филиал ООО "Аргос-Строй" Прометей | D143: Шарлаимова Валентина Афанасьевна | E143: Отменено | F143: 46218 | G143: 6 | H143: Шайба 30 ГОСТ 11371-78 | K143: 40 | L143: шт | M143: 15.49 | N143: 0 | O143: 619.6 | P143: 755.91
A144: 00ЦБ-000483 | B144: 46212 | C144: Филиал ООО "АРГОС-Строй"-КЕДР | D144: Шарлаимова Валентина Афанасьевна | E144: Отменено | F144: 46227 | G144: 1 | H144: Изолятор 2РС для наконечника, для кабелей сечением 4-6 мм2 | K144: 70 | L144: шт | M144: 6.4 | N144: 7.81 | O144: 448 | P144: 546.56
A145: 00ЦБ-000483 | B145: 46212 | C145: Филиал ООО "АРГОС-Строй"-КЕДР | D145: Шарлаимова Валентина Афанасьевна | E145: Отменено | F145: 46227 | G145: 2 | H145: Коробка концевая РТВ401-ИС 2 ExeIIT6 | I145: Коробка соединительная РТВ 401-0/0-ИС | K145: 4 | L145: комп | M145: 7150 | N145: 8723 | O145: 28600 | P145: 34892
A146: 00ЦБ-000483 | B146: 46212 | C146: Филиал ООО "АРГОС-Строй"-КЕДР | D146: Шарлаимова Валентина Афанасьевна | E146: Отменено | F146: 46227 | G146: 3 | H146: Коробка соединительная РТВ401 1Б/02 ExeIIT6 | I146: Коробка соединительная РТВ 401-1Б/0 | K146: 4 | L146: комп | M146: 5750 | N146: 7015 | O146: 23000 | P146: 28060
A147: 00ЦБ-000483 | B147: 46212 | C147: Филиал ООО "АРГОС-Строй"-КЕДР | D147: Шарлаимова Валентина Афанасьевна | E147: Отменено | F147: 46227 | G147: 4 | H147: Лента нагревательная 15НТР2-ВР | K147: 44 | L147: м | M147: 487 | N147: 594.14 | O147: 21428 | P147: 26142.16
A148: 00ЦБ-000483 | B148: 46212 | C148: Филиал ООО "АРГОС-Строй"-КЕДР | D148: Шарлаимова Валентина Афанасьевна | E148: Отменено | F148: 46227 | G148: 5 | H148: Маркировка для кабеля квадрат 55/55 CIC55554SQW DKC | K148: 448 | L148: шт | M148: 11 | N148: 13.42 | O148: 4928 | P148: 6012.16
A149: 00ЦБ-000483 | B149: 46212 | C149: Филиал ООО "АРГОС-Строй"-КЕДР | D149: Шарлаимова Валентина Афанасьевна | E149: Отменено | F149: 46227 | G149: 6 | H149: Маркировка для кабеля круг D 55 CIC55554CIW DKC | K149: 96 | L149: шт | M149: 11 | N149: 13.42 | O149: 1056 | P149: 1288.32
A150: 00ЦБ-000483 | B150: 46212 | C150: Филиал ООО "АРГОС-Строй"-КЕДР | D150: Шарлаимова Валентина Афанасьевна | E150: Отменено | F150: 46227 | G150: 7 | H150: Маркировка для кабеля треугольник 58/55 CIC58554TRW DKC | K150: 160 | L150: шт | M150: 11 | N150: 13.42 | O150: 1760 | P150: 2147.2
A151: 00ЦБ-000483 | B151: 46212 | C151: Филиал ООО "АРГОС-Строй"-КЕДР | D151: Шарлаимова Валентина Афанасьевна | E151: Отменено | F151: 46227 | G151: 8 | H151: Наконечник кабельный 2СТ6 DKC | K151: 70 | L151: шт | M151: 12 | N151: 14.64 | O151: 840 | P151: 1024.8
A152: 00ЦБ-000485 | B152: 46212 | C152: Филиал ООО "АРГОС-Строй"-КЕДР | D152: Шарлаимова Валентина Афанасьевна | E152: Отменено | F152: 46217 | G152: 1 | H152: Грунт-эмаль СБЭ-111 "Унипол" марка АМ RAL - 7004 ТУ 2313-001-92638584-2011 | I152: Эмаль СБЭ-111 "УНИПОЛ" марка AM (RAL 7004) | K152: 2036.16 | L152: кг | M152: 974.4 | N152: 0 | O152: 1984034.3 | P152: 2420521.9
A153: 00ЦБ-000487 | B153: 46212 | C153: Филиал ООО "Аргос-Строй" Прометей | D153: Шарлаимова Валентина Афанасьевна | E153: Отменено | F153: 46213 | G153: 1 | H153: Профлист С21-1000-0,7 RAL 9016 в комплекте с крепежным элементом | K153: 648 | L153: м2 | M153: 0 | N153: 0 | O153: 0 | P153: 0
A154: 00ЦБ-000484 | B154: 46212 | C154: Филиал ООО "Аргос-Строй" Прометей | D154: Шарлаимова Валентина Афанасьевна | E154: Отменено | F154: 46219 | G154: 1 | H154: Грунт-эмаль "Олиспринт-ФА" марка Б белая Pantone White | I154: Грунт-эмаль "Олиспринт-ФА" марка Б белая | K154: 40 | L154: кг | M154: 897 | N154: 1094.34 | O154: 35880 | P154: 43773.6
A155: 00ЦБ-000484 | B155: 46212 | C155: Филиал ООО "Аргос-Строй" Прометей | D155: Шарлаимова Валентина Афанасьевна | E155: Отменено | F155: 46219 | G155: 2 | H155: Грунт-эмаль "Олиспринт-ФА" марка Б красная Pantone 186С | I155: Грунт-эмаль "Олиспринт-ФА" марка Б красная | K155: 40 | L155: кг | M155: 897 | N155: 1094.34 | O155: 35880 | P155: 43773.6
A156: 00ЦБ-000484 | B156: 46212 | C156: Филиал ООО "Аргос-Строй" Прометей | D156: Шарлаимова Валентина Афанасьевна | E156: Отменено | F156: 46219 | G156: 3 | H156: Опора 114-КХ-170-Ст20 ОСТ 36-146-88 | K156: 4 | L156: шт | M156: 1825.34 | N156: 2226.92 | O156: 7301.36 | P156: 8907.66
A157: 00ЦБ-000490 | B157: 46212 | C157: Филиал ООО "Аргос-Строй" Прометей | D157: Шарлаимова Валентина Афанасьевна | E157: Отменено | F157: 46218 | G157: 1 | H157: Полка кабельная, l=250 мм, S=2,0 горячее цинкование, УХЛ1 | K157: 285 | L157: шт | M157: 118.59 | N157: 0 | O157: 33798.15 | P157: 41233.74
A158: 00ЦБ-000490 | B158: 46212 | C158: Филиал ООО "Аргос-Строй" Прометей | D158: Шарлаимова Валентина Афанасьевна | E158: Отменено | F158: 46218 | G158: 2 | H158: Полка кабельная, l=450 мм, S=2,0 горячее цинкование, УХЛ1 | K158: 1455 | L158: шт | M158: 208.35 | N158: 0 | O158: 303149.25 | P158: 369842.09
A159: 00ЦБ-000490 | B159: 46212 | C159: Филиал ООО "Аргос-Строй" Прометей | D159: Шарлаимова Валентина Афанасьевна | E159: Отменено | F159: 46218 | G159: 3 | H159: Стойка кабельная горячеоцинкованная (ГЦ) Н=400мм | K159: 57 | L159: шт | M159: 238.69 | N159: 0 | O159: 13605.33 | P159: 16598.5
A160: 00ЦБ-000490 | B160: 46212 | C160: Филиал ООО "Аргос-Строй" Прометей | D160: Шарлаимова Валентина Афанасьевна | E160: Отменено | F160: 46218 | G160: 4 | H160: Стойка кабельная горячеоцинкованная (ГЦ) Н=600мм ширина 60 мм, глубина 26 мм, толщина металла 2,5 мм | K160: 102 | L160: шт | M160: 432.63 | N160: 0 | O160: 44128.26 | P160: 53836.48
A161: 00ЦБ-000490 | B161: 46212 | C161: Филиал ООО "Аргос-Строй" Прометей | D161: Шарлаимова Валентина Афанасьевна | E161: Отменено | F161: 46218 | G161: 5 | H161: Стойка кабельная горячеоцинкованная (ГЦ) Н=800мм | K161: 343 | L161: шт | M161: 531.09 | N161: 0 | O161: 182163.87 | P161: 222239.92
A162: 00ЦБ-000489 | B162: 46212 | C162: Филиал ООО "Аргос-Строй" Прометей | D162: Шарлаимова Валентина Афанасьевна | E162: Отменено | F162: 46220 | G162: 1 | H162: Отвод 90-1,5DN - 168х16(168х14)-250-Сталь 20А ТУ 14-1-5598-2011 | K162: 2 | L162: шт | M162: 52745.9 | N162: 65835 | O162: 105491.8 | P162: 128700
A163: 00ЦБ-000489 | B163: 46212 | C163: Филиал ООО "Аргос-Строй" Прометей | D163: Шарлаимова Валентина Афанасьевна | E163: Отменено | F163: 46220 | G163: 2 | H163: Отвод 90-1,5DN - 219х20(219х18)-250-Сталь 20А ТУ 14-1-5598-2011 | K163: 11 | L163: шт | M163: 63614.76 | N163: 79401 | O163: 699762.36 | P163: 853710.08
A164: 00ЦБ-000489 | B164: 46212 | C164: Филиал ООО "Аргос-Строй" Прометей | D164: Шарлаимова Валентина Афанасьевна | E164: Отменено | F164: 46220 | G164: 3 | H164: Отвод 90-1,5DN - 273х24(273х22)-250-Сталь 20А ТУ 14-1-5598-2011 | K164: 14 | L164: шт | M164: 81516.4 | N164: 101745 | O164: 1141229.6 | P164: 1392300.1
A165: 00ЦБ-000489 | B165: 46212 | C165: Филиал ООО "Аргос-Строй" Прометей | D165: Шарлаимова Валентина Афанасьевна | E165: Отменено | F165: 46220 | G165: 4 | H165: Переход ПШ К-219х20(219х18)-168х16(168х14)-250-Сталь 20А ТУ 14-1-5598-2011 | K165: 3 | L165: шт | M165: 72672.6 | N165: 90706.59 | O165: 218017.8 | P165: 265981.72
A166: 00ЦБ-000489 | B166: 46212 | C166: Филиал ООО "Аргос-Строй" Прометей | D166: Шарлаимова Валентина Афанасьевна | E166: Отменено | F166: 46220 | G166: 5 | H166: Переход ПШ К 273х24(273х22)-168х16(168х14)-250-Сталь 20А ТУ 14-1-5598-2011 | K166: 2 | L166: шт | M166: 84713.12 | N166: 105735.01 | O166: 169426.24 | P166: 206700.01
A167: 00ЦБ-000489 | B167: 46212 | C167: Филиал ООО "Аргос-Строй" Прометей | D167: Шарлаимова Валентина Афанасьевна | E167: Отменено | F167: 46220 | G167: 6 | H167: Тройник ТШС 219х20(218х18)-168х16(168х14)-250-Сталь 20А ТУ 14-1-5598-2011 | K167: 1 | L167: шт | M167: 83114.76 | N167: 103740 | O167: 83114.76 | P167: 101400.01
A168: 00ЦБ-000489 | B168: 46212 | C168: Филиал ООО "Аргос-Строй" Прометей | D168: Шарлаимова Валентина Афанасьевна | E168: Отменено | F168: 46220 | G168: 7 | H168: Тройник ТШС 273х24(273х22)-168х16(168х14)-250-Сталь 20А ТУ 14-1-5598-2011 | K168: 7 | L168: шт | M168: 89827.88 | N168: 112119.01 | O168: 628795.16 | P168: 767130.1
A169: 00ЦБ-000488 | B169: 46212 | C169: Филиал ООО "АРГОС-Строй"-КЕДР | D169: Шарлаимова Валентина Афанасьевна | E169: Отменено | F169: 46223 | G169: 1 | H169: Крепление приварное по типу BSW4101 для профилей BPL-41/BPM-41/BPD-41, не оцинкованное | I169: Соединитель стоек ССх6-св УХЛ1, горячее цинкование, S6,0 | K169: 3165 | L169: шт | M169: 646.61 | N169: 0 | O169: 2046520.6 | P169: 2496755.2
A170: 00ЦБ-000488 | B170: 46212 | C170: Филиал ООО "АРГОС-Строй"-КЕДР | D170: Шарлаимова Валентина Афанасьевна | E170: Отменено | F170: 46223 | G170: 2 | H170: Крышка на Т-образный ответвитель 400, 1,5 мм SKTM400KHDZ, горячий цинк, в комплекте с крепежными элементами необходимыми для монтажа | I170: Крышка к тройниковому лотку замковому КЛТЗ 400 УХЛ1, горячее цинкование S1,5 | K170: 30 | L170: шт | M170: 2328.37 | N170: 0 | O170: 69851.1 | P170: 85218.34
A171: 00ЦБ-000488 | B171: 46212 | C171: Филиал ООО "АРГОС-Строй"-КЕДР | D171: Шарлаимова Валентина Афанасьевна | E171: Отменено | F171: 46223 | G171: 3 | H171: Крышка на Т-ответвитель, осн.400, R=300мм, горячеоцинкованная в комплекте с крепежными элементами и соединительными пластинами, необходимыми для монта | I171: Крышка к тройниковому лотку замковому КЛТЗ 400 (Rп300) УХЛ1, радиус поворота трассы 300 мм, горячее цинкование , S1,5 | K171: 5 | L171: шт | M171: 4878.76 | N171: 0 | O171: 24393.8 | P171: 29760.44
A172: 00ЦБ-000488 | B172: 46212 | C172: Филиал ООО "АРГОС-Строй"-КЕДР | D172: Шарлаимова Валентина Афанасьевна | E172: Отменено | F172: 46223 | G172: 4 | H172: Крышка на угол горизонтальный 90 градусов 400, 1,5 мм, по типу SKDM400KHDZ, горячий цинк, в комплекте с крепежными элементами необходимыми для монтажа | I172: Крышка к угловому лотку замковому КЛУЗ 400-90 УХЛ1 поворот на 90, горячее цинкование, S1,5 | K172: 4 | L172: шт | M172: 1813.23 | N172: 0 | O172: 7252.92 | P172: 8848.56
A173: 00ЦБ-000488 | B173: 46212 | C173: Филиал ООО "АРГОС-Строй"-КЕДР | D173: Шарлаимова Валентина Афанасьевна | E173: Отменено | F173: 46223 | G173: 5 | H173: Крышка на угол горизонтальный 90 градусов, осн.400, R=300 мм, по типу LK0043KHDZ, горячеоцинкованная в комплекте с крепежными элементами и соединитель | I173: Крышка к угловому лотку замковому КЛУЗ 400-90 (Rп300) УХЛ1 поворот на 90, радиус поворота трассы 300 мм, горячее цинкование, S1,5 | K173: 20 | L173: шт | M173: 3036.32 | N173: 0 | O173: 60726.4 | P173: 74086.21
A174: 00ЦБ-000488 | B174: 46212 | C174: Филиал ООО "АРГОС-Строй"-КЕДР | D174: Шарлаимова Валентина Афанасьевна | E174: Отменено | F174: 46223 | G174: 6 | H174: Ответвитель Т-образный 80х400, 1,5 мм, горячий цинк,STM840KHDZ, в комплекте с крепежными элементами и соединительными пластинами, необходимыми для мон | I174: Лоток тройниковый замковый глухой ОТЗГ 400х80 УХЛ1, горячее цинкование S1,5 | K174: 30 | L174: шт | M174: 4850.52 | N174: 0 | O174: 145515.6 | P174: 177529.03
A175: 00ЦБ-000488 | B175: 46212 | C175: Филиал ООО "АРГОС-Строй"-КЕДР | D175: Шарлаимова Валентина Афанасьевна | E175: Отменено | F175: 46223 | G175: 7 | H175: Профиль С-образный по типу BPD4112HDZ двойной, 41х41, длиной 1200 мм, толщиной 2,5, горячеоцинкованный | I175: Стойка сдвоенная ССД 1200 УХЛ1, горячее цинкование, S2,5 | K175: 85 | L175: шт | M175: 1541.53 | N175: 0 | O175: 131030.05 | P175: 159856.66
A176: 00ЦБ-000488 | B176: 46212 | C176: Филиал ООО "АРГОС-Строй"-КЕДР | D176: Шарлаимова Валентина Афанасьевна | E176: Отменено | F176: 46223 | G176: 8 | H176: Профиль С-образный по типу BPD4104HDZ двойной, 41х41, длиной 400 мм, толщиной 2,5, горячеоцинкованный | I176: Стойка сдвоенная ССД 400 УХЛ1, горячее цинкование, S2,5 | K176: 1262 | L176: шт | M176: 618.36 | N176: 0 | O176: 780370.32 | P176: 952051.79
A177: 00ЦБ-000488 | B177: 46212 | C177: Филиал ООО "АРГОС-Строй"-КЕДР | D177: Шарлаимова Валентина Афанасьевна | E177: Отменено | F177: 46223 | G177: 9 | H177: Профиль С-образный по типу BPD4107HDZ двойной, 41х41, длиной 700 мм, толщиной 2,5, горячеоцинкованный | I177: Стойка сдвоенная ССД 720 УХЛ1, горячее цинкование, S2,5 | K177: 712 | L177: шт | M177: 1030.29 | N177: 0 | O177: 733566.48 | P177: 894951.11
A178: 00ЦБ-000488 | B178: 46212 | C178: Филиал ООО "АРГОС-Строй"-КЕДР | D178: Шарлаимова Валентина Афанасьевна | E178: Отменено | F178: 46223 | G178: 10 | H178: Профиль С-образный по типу BPD4109HDZ двойной, 41х41, длиной 900 мм, толщиной 2,5, горячеоцинкованный | I178: Стойка сдвоенная ССД 920 УХЛ1, горячее цинкование, S2,5 | K178: 1256 | L178: шт | M178: 1238.68 | N178: 0 | O178: 1555782.1 | P178: 1898054.1
A179: 00ЦБ-000488 | B179: 46212 | C179: Филиал ООО "АРГОС-Строй"-КЕДР | D179: Шарлаимова Валентина Афанасьевна | E179: Отменено | F179: 46223 | G179: 11 | H179: Профиль С-образный по типу BPD4113HDZ двойной, 41х41, длиной 1300 мм, толщиной 2,5, горячеоцинкованный | I179: Стойка сдвоенная ССД 1320 УХЛ1, горячее цинкование, S2,5 | K179: 779 | L179: шт | M179: 1618.46 | N179: 0 | O179: 1260780.3 | P179: 1538152
A180: 00ЦБ-000488 | B180: 46212 | C180: Филиал ООО "АРГОС-Строй"-КЕДР | D180: Шарлаимова Валентина Афанасьевна | E180: Отменено | F180: 46223 | G180: 12 | H180: Профиль С-образный по типу BPD4115HDZ двойной, 41х41, длиной 1500 мм, толщиной 2,5, горячеоцинкованный | I180: Стойка сдвоенная ССД 1500 УХЛ1, горячее цинкование, S2,5 | K180: 734 | L180: шт | M180: 1899.9 | N180: 0 | O180: 1394526.6 | P180: 1701322.4
... A184: 00ЦБ-000488 | B184: 46212 | C184: Филиал ООО "АРГОС-Строй"-КЕДР | D184: Шарлаимова Валентина Афанасьевна | E184: Отменено | F184: 46223 | G184: 16 | H184: Угол горизонтальный 90 градусов 80х400, 1,5 мм, по типу SDM840KHDZ, горячий цинк, в комплекте с крепежными элементами и соединительными пластинами, не | I184: Лоток угловой замковый перфорированный КГЗ 400х80-90 УХЛ1 поворот на 90, горячее цинкование S1,5 | K184: 4 | L184: шт | M184: 4918.68 | N184: 0 | O184: 19674.72 | P184: 24003.16
A185: 00ЦБ-000491 | B185: 46212 | C185: Филиал ООО "АРГОС-Строй"-КЕДР | D185: Шарлаимова Валентина Афанасьевна | E185: Отменено | F185: 46218 | G185: 1 | H185: Арматура 12 А240с ГОСТ 34028-2016 | K185: 0.01 | L185: т | M185: 101355 | N185: 0 | O185: 1013.55 | P185: 1236.53
A186: 00ЦБ-000491 | B186: 46212 | C186: Филиал ООО "АРГОС-Строй"-КЕДР | D186: Шарлаимова Валентина Афанасьевна | E186: Отменено | F186: 46218 | G186: 2 | H186: Двутавр 30Ш2 ГОСТ Р 57837-2017 С345-6 ГОСТ 27772-2021 | I186: Балки двутавровые низколегир. 30 Ш2 дл 12000 ГОСТ35087/Р57837 (АСЧМ 20-93) С 355 | K186: 0.21 | L186: т | M186: 108155.75 | N186: 0 | O186: 22712.71 | P186: 27709.51
A187: 00ЦБ-000491 | B187: 46212 | C187: Филиал ООО "АРГОС-Строй"-КЕДР | D187: Шарлаимова Валентина Афанасьевна | E187: Отменено | F187: 46218 | G187: 3 | H187: Круг 18-В-II ГОСТ 2590-2006 Ст3сп ГОСТ 535-2005 оцинкованный | K187: 0.309 | L187: т | M187: 177209.02 | N187: 0 | O187: 54757.59 | P187: 66804.26
A188: 00ЦБ-000491 | B188: 46212 | C188: Филиал ООО "АРГОС-Строй"-КЕДР | D188: Шарлаимова Валентина Афанасьевна | E188: Отменено | F188: 46218 | G188: 4 | H188: Круг 20-В1 ГОСТ 2590-2006 345-3 ГОСТ 27772-2021 | I188: Сталь сорт.констр круг г/к о/т 09Г2С 20 | K188: 0.62 | L188: т | M188: 83659.07 | N188: 0 | O188: 51868.62 | P188: 63279.72
A189: 00ЦБ-000491 | B189: 46212 | C189: Филиал ООО "АРГОС-Строй"-КЕДР | D189: Шарлаимова Валентина Афанасьевна | E189: Отменено | F189: 46218 | G189: 5 | H189: Круг 20-В1 ГОСТ 2590-2006 345-9-1 ГОСТ 19281-2014 | I189: Сталь сорт.констр круг г/к о/т 09Г2С 20 | K189: 8.65 | L189: т | M189: 89459.07 | N189: 0 | O189: 773820.96 | P189: 944061.57
A190: 00ЦБ-000491 | B190: 46212 | C190: Филиал ООО "АРГОС-Строй"-КЕДР | D190: Шарлаимова Валентина Афанасьевна | E190: Отменено | F190: 46218 | G190: 6 | H190: Круг 32-В1 ГОСТ 2590-2006 345-9-1 ГОСТ 19281-2014 | I190: Сталь сорт.констр круг г/к о/т 30ХГСА 32 | K190: 0.01 | L190: т | M190: 100325.5 | N190: 0 | O190: 1003.26 | P190: 1223.98
A191: 00ЦБ-000491 | B191: 46212 | C191: Филиал ООО "АРГОС-Строй"-КЕДР | D191: Шарлаимова Валентина Афанасьевна | E191: Отменено | F191: 46218 | G191: 7 | H191: Лист 10 ГОСТ 19903-2015 С255-4 ГОСТ 27772-2021 | K191: 0.15 | L191: т | M191: 135734.5 | N191: 0 | O191: 20360.18 | P191: 24839.42
A192: 00ЦБ-000491 | B192: 46212 | C192: Филиал ООО "АРГОС-Строй"-КЕДР | D192: Шарлаимова Валентина Афанасьевна | E192: Отменено | F192: 46218 | G192: 8 | H192: Лист 10 ГОСТ 19903-2015 С345-6 ГОСТ 27772-2021 | I192: Лист г/к ГОСТ 19281-2014 09Г2С-15 10х1500х3000 | K192: 1.58 | L192: т | M192: 97135.5 | N192: 0 | O192: 153474.09 | P192: 187238.39
A193: 00ЦБ-000491 | B193: 46212 | C193: Филиал ООО "АРГОС-Строй"-КЕДР | D193: Шарлаимова Валентина Афанасьевна | E193: Отменено | F193: 46218 | G193: 9 | H193: Лист 20 ГОСТ 19903-2015 С345-6 ГОСТ 27772-2021 | K193: 0.79 | L193: т | M193: 101920.5 | N193: 0 | O193: 80517.2 | P193: 98230.98
A194: 00ЦБ-000491 | B194: 46212 | C194: Филиал ООО "АРГОС-Строй"-КЕДР | D194: Шарлаимова Валентина Афанасьевна | E194: Отменено | F194: 46218 | G194: 10 | H194: Лист 4 ГОСТ 19903-2015 С255 ГОСТ 27772-2021 | K194: 1 | L194: т | M194: 92811.89 | N194: 0 | O194: 92811.89 | P194: 113230.51
A195: 00ЦБ-000491 | B195: 46212 | C195: Филиал ООО "АРГОС-Строй"-КЕДР | D195: Шарлаимова Валентина Афанасьевна | E195: Отменено | F195: 46218 | G195: 11 | H195: Лист 4 ГОСТ 19903-2015 С255-4 ГОСТ 27772-2021 | K195: 0.25 | L195: т | M195: 113230.5 | N195: 0 | O195: 28307.63 | P195: 34535.31
A196: 00ЦБ-000491 | B196: 46212 | C196: Филиал ООО "АРГОС-Строй"-КЕДР | D196: Шарлаимова Валентина Афанасьевна | E196: Отменено | F196: 46218 | G196: 12 | H196: Лист 6 ГОСТ 19903-2015 С345-6 ГОСТ 27772-2021 | I196: Лист НЛГ 6 ГОСТ 19281 | K196: 0.14 | L196: т | M196: 113230.5 | N196: 0 | O196: 15852.27 | P196: 19339.77
A197: 00ЦБ-000491 | B197: 46212 | C197: Филиал ООО "АРГОС-Строй"-КЕДР | D197: Шарлаимова Валентина Афанасьевна | E197: Отменено | F197: 46218 | G197: 13 | H197: Лист 6 ГОСТ 19904-90 С255 ГОСТ 27772-2021 | I197: Лист НЛГ 6 ГОСТ 19281 | K197: 0.06 | L197: т | M197: 113230.5 | N197: 0 | O197: 6793.83 | P197: 8288.47
A198: 00ЦБ-000491 | B198: 46212 | C198: Филиал ООО "АРГОС-Строй"-КЕДР | D198: Шарлаимова Валентина Афанасьевна | E198: Отменено | F198: 46218 | G198: 14 | H198: Лист 8 ГОСТ 19903-2015 С255-4 ГОСТ 27772-2021 | I198: Лист НЛГ 8 ГОСТ 19281 | K198: 0.03 | L198: т | M198: 115710 | N198: 0 | O198: 3471.3 | P198: 4234.99
A199: 00ЦБ-000491 | B199: 46212 | C199: Филиал ООО "АРГОС-Строй"-КЕДР | D199: Шарлаимова Валентина Афанасьевна | E199: Отменено | F199: 46218 | G199: 15 | H199: Лист 8 ГОСТ 19903-2015 С345-6 ГОСТ 27772-2021 | I199: Лист НЛГ 8 ГОСТ 19281 | K199: 2.281 | L199: т | M199: 97459.02 | N199: 0 | O199: 222304.02 | P199: 271210.91
A200: 00ЦБ-000491 | B200: 46212 | C200: Филиал ООО "АРГОС-Строй"-КЕДР | D200: Шарлаимова Валентина Афанасьевна | E200: Отменено | F200: 46218 | G200: 16 | H200: Лист ПВ 406 ТУ 36.26.11-5-89 С255-4 ГОСТ 27772-2021 | I200: ПРОСЕЧНО-ВЫТЯЖНОЙ ЛИСТ ПВЛ-406 | K200: 0.26 | L200: т | M200: 96258.61 | N200: 0 | O200: 25027.24 | P200: 30533.23
A201: 00ЦБ-000491 | B201: 46212 | C201: Филиал ООО "АРГОС-Строй"-КЕДР | D201: Шарлаимова Валентина Афанасьевна | E201: Отменено | F201: 46218 | G201: 17 | H201: Лист ПВ 506 ТУ 36.26.11-5-89 С255-4 ГОСТ 27772-2021 | I201: ПРОСЕЧНО-ВЫТЯЖНОЙ ЛИСТ ПВЛ-506 | K201: 2.71 | L201: т | M201: 91861.07 | N201: 0 | O201: 248943.5 | P201: 303711.07
A202: 00ЦБ-000491 | B202: 46212 | C202: Филиал ООО "АРГОС-Строй"-КЕДР | D202: Шарлаимова Валентина Афанасьевна | E202: Отменено | F202: 46218 | G202: 18 | H202: Полоса 4х40 ГОСТ 103-2006 Ст3 ГОСТ 380-2005 | K202: 0.693 | L202: т | M202: 106314 | N202: 0 | O202: 73675.6 | P202: 89884.23
A203: 00ЦБ-000491 | B203: 46212 | C203: Филиал ООО "АРГОС-Строй"-КЕДР | D203: Шарлаимова Валентина Афанасьевна | E203: Отменено | F203: 46218 | G203: 19 | H203: Уголок 45х45х5 ГОСТ 8509-93 С255 ГОСТ 27772-2021 | K203: 0.4 | L203: т | M203: 94547.25 | N203: 0 | O203: 37818.9 | P203: 46139.06
A204: 00ЦБ-000491 | B204: 46212 | C204: Филиал ООО "АРГОС-Строй"-КЕДР | D204: Шарлаимова Валентина Афанасьевна | E204: Отменено | F204: 46218 | G204: 20 | H204: Уголок 50х50х3 ГОСТ 8509-93 С255 ГОСТ 27772-2021 | K204: 0.08 | L204: т | M204: 94547.25 | N204: 0 | O204: 7563.78 | P204: 9227.81
A205: 00ЦБ-000491 | B205: 46212 | C205: Филиал ООО "АРГОС-Строй"-КЕДР | D205: Шарлаимова Валентина Афанасьевна | E205: Отменено | F205: 46218 | G205: 21 | H205: Уголок 50х50х5 ГОСТ 8509-93 С255 ГОСТ 27772-2021 | I205: Уголок 50х50х5 Ст3пс5 ГОСТ 8509 | K205: 1.35 | L205: т | M205: 190377.88 | N205: 0 | O205: 257010.14 | P205: 313552.37
A206: 00ЦБ-000491 | B206: 46212 | C206: Филиал ООО "АРГОС-Строй"-КЕДР | D206: Шарлаимова Валентина Афанасьевна | E206: Отменено | F206: 46218 | G206: 22 | H206: Уголок 50х50х5 ГОСТ 8509-93 С255-4 ГОСТ 27772-2021 | I206: Уголок 50х50х5 Ст3пс5 ГОСТ 8509 | K206: 0.88 | L206: т | M206: 190377.88 | N206: 0 | O206: 167532.53 | P206: 204389.69
A207: 00ЦБ-000491 | B207: 46212 | C207: Филиал ООО "АРГОС-Строй"-КЕДР | D207: Шарлаимова Валентина Афанасьевна | E207: Отменено | F207: 46218 | G207: 23 | H207: Уголок 50х50х5 ГОСТ 8509-93 С345-5 ГОСТ 27772-2021 | I207: Уголок НЛГ 50х50х5 ст 09г2С-15 | K207: 0.06 | L207: т | M207: 107323.78 | N207: 0 | O207: 6439.43 | P207: 7856.1
A208: 00ЦБ-000491 | B208: 46212 | C208: Филиал ООО "АРГОС-Строй"-КЕДР | D208: Шарлаимова Валентина Афанасьевна | E208: Отменено | F208: 46218 | G208: 24 | H208: Уголок 50х50х5 ГОСТ 8509-93 С345-6 ГОСТ 27772-2021 | I208: Уголок НЛГ 50х50х5 ст 09г2С-15 | K208: 0.19 | L208: т | M208: 107323.78 | N208: 0 | O208: 20391.52 | P208: 24877.65
A209: 00ЦБ-000491 | B209: 46212 | C209: Филиал ООО "АРГОС-Строй"-КЕДР | D209: Шарлаимова Валентина Афанасьевна | E209: Отменено | F209: 46218 | G209: 25 | H209: Уголок 60х60х4 ГОСТ 8509-93 С245 ГОСТ 27772-2021 | I209: Уголок НЛГ 63 63 5 ст.09г2с-15 | K209: 0.03 | L209: т | M209: 130935 | N209: 0 | O209: 3928.05 | P209: 4792.22
A210: 00ЦБ-000491 | B210: 46212 | C210: Филиал ООО "АРГОС-Строй"-КЕДР | D210: Шарлаимова Валентина Афанасьевна | E210: Отменено | F210: 46218 | G210: 26 | H210: Уголок 75х75х5 ГОСТ 8509-93 С255 ГОСТ 27772-2021 | K210: 1.45 | L210: т | M210: 94547.13 | N210: 0 | O210: 137093.34 | P210: 167253.87
A211: 00ЦБ-000491 | B211: 46212 | C211: Филиал ООО "АРГОС-Строй"-КЕДР | D211: Шарлаимова Валентина Афанасьевна | E211: Отменено | F211: 46218 | G211: 27 | H211: Уголок 75х75х5 ГОСТ 8509-93 С345-6 ГОСТ 27772-2021 | I211: Уголок НЛГ 75 75 5 ст 09г2с-15 | K211: 0.76 | L211: т | M211: 108607.9 | N211: 0 | O211: 82542 | P211: 100701.24
A212: 00ЦБ-000491 | B212: 46212 | C212: Филиал ООО "АРГОС-Строй"-КЕДР | D212: Шарлаимова Валентина Афанасьевна | E212: Отменено | F212: 46218 | G212: 28 | H212: Уголок 75х75х6 ГОСТ 8509-93 С255-4 ГОСТ 27772-2021 | K212: 0.01 | L212: т | M212: 132501 | N212: 0 | O212: 1325.01 | P212: 1616.51
A213: 00ЦБ-000491 | B213: 46212 | C213: Филиал ООО "АРГОС-Строй"-КЕДР | D213: Шарлаимова Валентина Афанасьевна | E213: Отменено | F213: 46218 | G213: 29 | H213: Уголок 75х75х6 ГОСТ 8509-93 С345-6 ГОСТ 27772-2021 | K213: 1.7 | L213: т | M213: 108607.9 | N213: 0 | O213: 184633.43 | P213: 225252.78
A214: 00ЦБ-000491 | B214: 46212 | C214: Филиал ООО "АРГОС-Строй"-КЕДР | D214: Шарлаимова Валентина Афанасьевна | E214: Отменено | F214: 46218 | G214: 30 | H214: Швеллер 12У ГОСТ 8240-97 С345-6 ГОСТ 27772-2021 | I214: Швеллер НЛГ 12 У ст. 09г2с-15 | K214: 8.87 | L214: т | M214: 103496.8 | N214: 0 | O214: 918016.62 | P214: 1119980.3
A215: 00ЦБ-000491 | B215: 46212 | C215: Филиал ООО "АРГОС-Строй"-КЕДР | D215: Шарлаимова Валентина Афанасьевна | E215: Отменено | F215: 46218 | G215: 31 | H215: Швеллер 140х60х5 ГОСТ 8278-83 С255 ГОСТ 27772-2021 | I215: Профиль гнутый швеллер 140х60х5 дл 12000 ГОСТ11474-76 | K215: 0.27 | L215: т | M215: 89885.5 | N215: 0 | O215: 24269.09 | P215: 29608.29
A216: 00ЦБ-000491 | B216: 46212 | C216: Филиал ООО "АРГОС-Строй"-КЕДР | D216: Шарлаимова Валентина Афанасьевна | E216: Отменено | F216: 46218 | G216: 32 | H216: Швеллер 160х50х4 ГОСТ 8278-83 С255 ГОСТ 27772-2021 | I216: Профиль гнутый швеллер 160х50х4 дл 12000 | K216: 0.06 | L216: т | M216: 91335.5 | N216: 0 | O216: 5480.13 | P216: 6685.76
A217: 00ЦБ-000491 | B217: 46212 | C217: Филиал ООО "АРГОС-Строй"-КЕДР | D217: Шарлаимова Валентина Афанасьевна | E217: Отменено | F217: 46218 | G217: 33 | H217: Швеллер 160х60х4 ГОСТ 8278-83 С255 ГОСТ 27772-2021 | K217: 0.19 | L217: т | M217: 107604.5 | N217: 0 | O217: 20444.86 | P217: 24942.73
A218: 00ЦБ-000491 | B218: 46212 | C218: Филиал ООО "АРГОС-Строй"-КЕДР | D218: Шарлаимова Валентина Афанасьевна | E218: Отменено | F218: 46218 | G218: 34 | H218: Швеллер 16У ГОСТ 8240-97 С255-4 ГОСТ 27772-2021 | K218: 0.14 | L218: т | M218: 94547.25 | N218: 0 | O218: 13236.62 | P218: 16148.68
A219: 00ЦБ-000491 | B219: 46212 | C219: Филиал ООО "АРГОС-Строй"-КЕДР | D219: Шарлаимова Валентина Афанасьевна | E219: Отменено | F219: 46218 | G219: 35 | H219: Швеллер 16У ГОСТ 8240-97 С345-6 ГОСТ 27772-2021 | I219: Швеллер НЛГ 16 У ст. 09г2с-15 | K219: 0.16 | L219: т | M219: 126266 | N219: 0 | O219: 20202.56 | P219: 24647.12
A220: 00ЦБ-000491 | B220: 46212 | C220: Филиал ООО "АРГОС-Строй"-КЕДР | D220: Шарлаимова Валентина Афанасьевна | E220: Отменено | F220: 46218 | G220: 36 | H220: Швеллер 20У ГОСТ 8240-97 С345-6 ГОСТ 27772-2021 | I220: Швеллер НЛГ 20 У ст. 09г2с-15 | K220: 0.21 | L220: т | M220: 204827 | N220: 0 | O220: 43013.67 | P220: 52476.68
A221: 00ЦБ-000491 | B221: 46212 | C221: Филиал ООО "АРГОС-Строй"-КЕДР | D221: Шарлаимова Валентина Афанасьевна | E221: Отменено | F221: 46218 | G221: 37 | H221: Швеллер 70х70х4 ГОСТ 8278-83 С255 ГОСТ 27772-2021 | I221: Швеллер гнутый низколегир 80х60х4, длина 12 м | K221: 0.09 | L221: т | M221: 125632.15 | N221: 0 | O221: 11306.89 | P221: 13794.41
A222: 00ЦБ-000486 | B222: 46212 | C222: Филиал ООО "АРГОС-Строй"-КЕДР | D222: Шарлаимова Валентина Афанасьевна | E222: Отменено | F222: 46224 | G222: 1 | H222: Труба 168х14 ГОСТ 8732-78 К52-В20 ГОСТ 8731-74 термообработанная внутр. антикор. 2х слойн. порошк. покр. ПЭП 7150. ТУ 7304-005-128760-12 | K222: 1.32 | L222: т | M222: 0 | N222: 0 | O222: 0 | P222: 0
A223: 00ЦБ-000486 | B223: 46212 | C223: Филиал ООО "АРГОС-Строй"-КЕДР | D223: Шарлаимова Валентина Афанасьевна | E223: Отменено | F223: 46224 | G223: 2 | H223: Труба 219х8 ГОСТ 8732-78 К52-В20 ГОСТ 8731-74 термообработанная внутр. антикор. 2х слойн. порошк. покр. ПЭП 7150. ТУ 7304-005-128760-12 | K223: 4.593 | L223: т | M223: 0 | N223: 0 | O223: 0 | P223: 0
A224: 00ЦБ-000486 | B224: 46212 | C224: Филиал ООО "АРГОС-Строй"-КЕДР | D224: Шарлаимова Валентина Афанасьевна | E224: Отменено | F224: 46224 | G224: 3 | H224: Труба 273х22 ГОСТ 8732-78 К52-В20 ГОСТ 8731-74 термообработанная внутр. антикор. 2х слойн. порошк. покр. ПЭП 7150. ТУ 7304-005-128760-12 | K224: 7.218 | L224: т | M224: 0 | N224: 0 | O224: 0 | P224: 0
A225: 00ЦБ-000494 | B225: 46213 | C225: Филиал ООО "АРГОС-Строй"-СТПС | D225: Шарлаимова Валентина Афанасьевна | E225: Действует | F225: 46220 | G225: 1 | H225: Задвижка запорная с электроприводом DN 250 PN 40 | I225: Задвижка 30лс915нж DN 250 PN 40 исп. E тип В САЗ/Электропривод ЭП4В-В-630-90-Э11-3-11111 (взрывозащита 1ExdbIIBT4Gb, питание 380 В, управление 24 В DC | K225: 2 | L225: шт | M225: 2082173.5 | N225: 2622195.2 | O225: 4164346.9 | P225: 5080503.3
A226: 00ЦБ-000495 | B226: 46213 | C226: Филиал ООО "АРГОС-Строй"-КЕДР | D226: Шарлаимова Валентина Афанасьевна | E226: Отменено | F226: 46234 | G226: 1 | H226: Щиток защиты от импульсных перенапряжений 3688.001.Р.0/0.0007.КЭ.000.0923.000-ЭС.ОЛ1 ТУ 3434-001-79740390-2007 | I226: Щиток защиты от импульсных перенапряжений ЩЗИП-91.6ЯУО-9601-3474/8-IP44-У ХЛ3 о.л. 3688.001.Р.0/0.0007.КЭ.000.0923.00 0-ЭС.ОЛ1 | K226: 1 | L226: шт | M226: 583031.15 | N226: 736701.5 | O226: 583031.15 | P226: 711298
A227: 00ЦБ-000495 | B227: 46213 | C227: Филиал ООО "АРГОС-Строй"-КЕДР | D227: Шарлаимова Валентина Афанасьевна | E227: Отменено | F227: 46234 | G227: 2 | H227: Щиток защиты от импульсных перенапряжений 3688.001.Р.0/0.0007.КЭ.000.0923.000-ЭС.ОЛ2 ТУ 3434-001-79740390-2007 | I227: Щиток защиты от импульсных перенапряжений ЩЗИП-Н1-М318/12-20-IP54-УХЛ1 о.л. 3688.001.Р.0/0.0007.КЭ.000.0923.00 0-ЭС.ОЛ2 | K227: 1 | L227: шт | M227: 324571.8 | N227: 273088 | O227: 324571.8 | P227: 395977.6
A228: 00ЦБ-000495 | B228: 46213 | C228: Филиал ООО "АРГОС-Строй"-КЕДР | D228: Шарлаимова Валентина Афанасьевна | E228: Отменено | F228: 46234 | G228: 3 | H228: Щиток защиты от импульсных перенапряжений 3688.001.Р.0/0.0007.УКПГ.000.0923.029.3-ЭС.ОЛ1, ТУ 3434-001-79740390-2007 | I228: Щиток защиты от импульсных перенапряжений ЩЗИП-ЯУО-3474/11-IP44-УХЛ3 о.л. 3688.001.Р.0/0.0007.УКПГ.000.0923. 029.3-ЭС.ОЛ1 | K228: 1 | L228: шт | M228: 663626.97 | N228: 558362 | O228: 663626.97 | P228: 809624.9
...

Sheet Свод по номенклатуре
A1: Номенклатура | B1: Ед. изм. | C1: Строк в КП | D1: Количество, всего | E1: Сумма с НДС, всего, ₽ | F1: Строк в КП со сроком подачи | G1: Есть в КП со сроком подачи
A2: "Емкость канализационная для бытовых стоков V=25 м3 в комплекте с КНС (поз. 15)" | B2: комп | C2: =COUNTIFS('Все позиции'!$H$2:$H$10401,A2,'Все позиции'!$L$2:$L$10401,B2) -> 1 | D2: =SUMIFS('Все позиции'!$K$2:$K$10401,'Все позиции'!$H$2:$H$10401,A2,'Все позиции'!$L$2:$L$10401,B2) -> 1 | E2: =SUMIFS('Все позиции'!$P$2:$P$10401,'Все позиции'!$H$2:$H$10401,A2,'Все позиции'!$L$2:$L$10401,B2) -> 0 | F2: =COUNTIFS('Все позиции'!$H$2:$H$10401,A2,'Все позиции'!$L$2:$L$10401,B2,'Все позиции'!$F$2:$F$10401,"<>") -> 1 | G2: =IF(F2>0,"да","нет") -> да
A3: "Емкость канализационная для бытовых стоков V=25 м3 в комплекте с КНС (поз. 15)2" | B3: комп | C3: =COUNTIFS('Все позиции'!$H$2:$H$10401,A3,'Все позиции'!$L$2:$L$10401,B3) -> 1 | D3: =SUMIFS('Все позиции'!$K$2:$K$10401,'Все позиции'!$H$2:$H$10401,A3,'Все позиции'!$L$2:$L$10401,B3) -> 1 | E3: =SUMIFS('Все позиции'!$P$2:$P$10401,'Все позиции'!$H$2:$H$10401,A3,'Все позиции'!$L$2:$L$10401,B3) -> 0 | F3: =COUNTIFS('Все позиции'!$H$2:$H$10401,A3,'Все позиции'!$L$2:$L$10401,B3,'Все позиции'!$F$2:$F$10401,"<>") -> 1 | G3: =IF(F3>0,"да","нет") -> да
A4: 0034.4213, Предохранительные: плавкая вставка; быстрый; 250 мА; 125 ВАС; РСВ, ТНТ (chipdip) | B4: шт | C4: =COUNTIFS('Все позиции'!$H$2:$H$10401,A4,'Все позиции'!$L$2:$L$10401,B4) -> 1 | D4: =SUMIFS('Все позиции'!$K$2:$K$10401,'Все позиции'!$H$2:$H$10401,A4,'Все позиции'!$L$2:$L$10401,B4) -> 300 | E4: =SUMIFS('Все позиции'!$P$2:$P$10401,'Все позиции'!$H$2:$H$10401,A4,'Все позиции'!$L$2:$L$10401,B4) -> 79945.38 | F4: =COUNTIFS('Все позиции'!$H$2:$H$10401,A4,'Все позиции'!$L$2:$L$10401,B4,'Все позиции'!$F$2:$F$10401,"<>") -> 0 | G4: =IF(F4>0,"да","нет") -> нет
A5: 09-3242_20С1775-ВЖК-1-АС | B5: компл | C5: =COUNTIFS('Все позиции'!$H$2:$H$10401,A5,'Все позиции'!$L$2:$L$10401,B5) -> 1 | D5: =SUMIFS('Все позиции'!$K$2:$K$10401,'Все позиции'!$H$2:$H$10401,A5,'Все позиции'!$L$2:$L$10401,B5) -> 1 | E5: =SUMIFS('Все позиции'!$P$2:$P$10401,'Все позиции'!$H$2:$H$10401,A5,'Все позиции'!$L$2:$L$10401,B5) -> 93348981 | F5: =COUNTIFS('Все позиции'!$H$2:$H$10401,A5,'Все позиции'!$L$2:$L$10401,B5,'Все позиции'!$F$2:$F$10401,"<>") -> 1 | G5: =IF(F5>0,"да","нет") -> да
A6: 09-3242_20С1775-ВЖК-1-ВК | B6: компл | C6: =COUNTIFS('Все позиции'!$H$2:$H$10401,A6,'Все позиции'!$L$2:$L$10401,B6) -> 1 | D6: =SUMIFS('Все позиции'!$K$2:$K$10401,'Все позиции'!$H$2:$H$10401,A6,'Все позиции'!$L$2:$L$10401,B6) -> 1 | E6: =SUMIFS('Все позиции'!$P$2:$P$10401,'Все позиции'!$H$2:$H$10401,A6,'Все позиции'!$L$2:$L$10401,B6) -> 12886933 | F6: =COUNTIFS('Все позиции'!$H$2:$H$10401,A6,'Все позиции'!$L$2:$L$10401,B6,'Все позиции'!$F$2:$F$10401,"<>") -> 1 | G6: =IF(F6>0,"да","нет") -> да
A7: 09-3242_20С1775-ВЖК-1-КМ | B7: компл | C7: =COUNTIFS('Все позиции'!$H$2:$H$10401,A7,'Все позиции'!$L$2:$L$10401,B7) -> 1 | D7: =SUMIFS('Все позиции'!$K$2:$K$10401,'Все позиции'!$H$2:$H$10401,A7,'Все позиции'!$L$2:$L$10401,B7) -> 1 | E7: =SUMIFS('Все позиции'!$P$2:$P$10401,'Все позиции'!$H$2:$H$10401,A7,'Все позиции'!$L$2:$L$10401,B7) -> 93822244 | F7: =COUNTIFS('Все позиции'!$H$2:$H$10401,A7,'Все позиции'!$L$2:$L$10401,B7,'Все позиции'!$F$2:$F$10401,"<>") -> 1 | G7: =IF(F7>0,"да","нет") -> да
A8: 09-3242_20С1775-ВЖК-1-ОВ | B8: компл | C8: =COUNTIFS('Все позиции'!$H$2:$H$10401,A8,'Все позиции'!$L$2:$L$10401,B8) -> 1 | D8: =SUMIFS('Все позиции'!$K$2:$K$10401,'Все позиции'!$H$2:$H$10401,A8,'Все позиции'!$L$2:$L$10401,B8) -> 1 | E8: =SUMIFS('Все позиции'!$P$2:$P$10401,'Все позиции'!$H$2:$H$10401,A8,'Все позиции'!$L$2:$L$10401,B8) -> 51256057 | F8: =COUNTIFS('Все позиции'!$H$2:$H$10401,A8,'Все позиции'!$L$2:$L$10401,B8,'Все позиции'!$F$2:$F$10401,"<>") -> 1 | G8: =IF(F8>0,"да","нет") -> да
A9: 09-3242_20С1775-ВЖК-1-ОС | B9: компл | C9: =COUNTIFS('Все позиции'!$H$2:$H$10401,A9,'Все позиции'!$L$2:$L$10401,B9) -> 1 | D9: =SUMIFS('Все позиции'!$K$2:$K$10401,'Все позиции'!$H$2:$H$10401,A9,'Все позиции'!$L$2:$L$10401,B9) -> 1 | E9: =SUMIFS('Все позиции'!$P$2:$P$10401,'Все позиции'!$H$2:$H$10401,A9,'Все позиции'!$L$2:$L$10401,B9) -> 1177531 | F9: =COUNTIFS('Все позиции'!$H$2:$H$10401,A9,'Все позиции'!$L$2:$L$10401,B9,'Все позиции'!$F$2:$F$10401,"<>") -> 1 | G9: =IF(F9>0,"да","нет") -> да
A10: 09-3242_20С1775-ВЖК-1-ТХТ | B10: компл | C10: =COUNTIFS('Все позиции'!$H$2:$H$10401,A10,'Все позиции'!$L$2:$L$10401,B10) -> 1 | D10: =SUMIFS('Все позиции'!$K$2:$K$10401,'Все позиции'!$H$2:$H$10401,A10,'Все позиции'!$L$2:$L$10401,B10) -> 1 | E10: =SUMIFS('Все позиции'!$P$2:$P$10401,'Все позиции'!$H$2:$H$10401,A10,'Все позиции'!$L$2:$L$10401,B10) -> 41770516 | F10: =COUNTIFS('Все позиции'!$H$2:$H$10401,A10,'Все позиции'!$L$2:$L$10401,B10,'Все позиции'!$F$2:$F$10401,"<>") -> 1 | G10: =IF(F10>0,"да","нет") -> да
A11: 09-3242_20С1775-ВЖК-1-ЭОМ | B11: компл | C11: =COUNTIFS('Все позиции'!$H$2:$H$10401,A11,'Все позиции'!$L$2:$L$10401,B11) -> 1 | D11: =SUMIFS('Все позиции'!$K$2:$K$10401,'Все позиции'!$H$2:$H$10401,A11,'Все позиции'!$L$2:$L$10401,B11) -> 1 | E11: =SUMIFS('Все позиции'!$P$2:$P$10401,'Все позиции'!$H$2:$H$10401,A11,'Все позиции'!$L$2:$L$10401,B11) -> 7788617.8 | F11: =COUNTIFS('Все позиции'!$H$2:$H$10401,A11,'Все позиции'!$L$2:$L$10401,B11,'Все позиции'!$F$2:$F$10401,"<>") -> 1 | G11: =IF(F11>0,"да","нет") -> да
A12: 09-3242_20С1775-ВЖК-2-АС | B12: компл | C12: =COUNTIFS('Все позиции'!$H$2:$H$10401,A12,'Все позиции'!$L$2:$L$10401,B12) -> 1 | D12: =SUMIFS('Все позиции'!$K$2:$K$10401,'Все позиции'!$H$2:$H$10401,A12,'Все позиции'!$L$2:$L$10401,B12) -> 1 | E12: =SUMIFS('Все позиции'!$P$2:$P$10401,'Все позиции'!$H$2:$H$10401,A12,'Все позиции'!$L$2:$L$10401,B12) -> 1.1772003e+08 | F12: =COUNTIFS('Все позиции'!$H$2:$H$10401,A12,'Все позиции'!$L$2:$L$10401,B12,'Все позиции'!$F$2:$F$10401,"<>") -> 1 | G12: =IF(F12>0,"да","нет") -> да
A13: 09-3242_20С1775-ВЖК-2-ВК | B13: компл | C13: =COUNTIFS('Все позиции'!$H$2:$H$10401,A13,'Все позиции'!$L$2:$L$10401,B13) -> 1 | D13: =SUMIFS('Все позиции'!$K$2:$K$10401,'Все позиции'!$H$2:$H$10401,A13,'Все позиции'!$L$2:$L$10401,B13) -> 1 | E13: =SUMIFS('Все позиции'!$P$2:$P$10401,'Все позиции'!$H$2:$H$10401,A13,'Все позиции'!$L$2:$L$10401,B13) -> 8970383.4 | F13: =COUNTIFS('Все позиции'!$H$2:$H$10401,A13,'Все позиции'!$L$2:$L$10401,B13,'Все позиции'!$F$2:$F$10401,"<>") -> 1 | G13: =IF(F13>0,"да","нет") -> да
... A8133: Ящик ЯТПВ-0,25-2А УХЛЗ ТУ 16-536.024-75 с понижающим разделительным трансформатором 220/24 В, степень защиты IР54 | B8133: шт | C8133: =COUNTIFS('Все позиции'!$H$2:$H$10401,A8133,'Все позиции'!$L$2:$L$10401,B8133) -> 2 | D8133: =SUMIFS('Все позиции'!$K$2:$K$10401,'Все позиции'!$H$2:$H$10401,A8133,'Все позиции'!$L$2:$L$10401,B8133) -> 7 | E8133: =SUMIFS('Все позиции'!$P$2:$P$10401,'Все позиции'!$H$2:$H$10401,A8133,'Все позиции'!$L$2:$L$10401,B8133) -> 69777.9 | F8133: =COUNTIFS('Все позиции'!$H$2:$H$10401,A8133,'Все позиции'!$L$2:$L$10401,B8133,'Все позиции'!$F$2:$F$10401,"<>") -> 1 | G8133: =IF(F8133>0,"да","нет") -> да
