Workbook

Sheet Продажи
B2: ТРАНСТЕХКОМ Продажи и исполнение | C2: ТРАНСТЕХКОМ Продажи и исполнение | D2: ТРАНСТЕХКОМ Продажи и исполнение | E2: ТРАНСТЕХКОМ Продажи и исполнение | F2: ТРАНСТЕХКОМ Продажи и исполнение | G2: ТРАНСТЕХКОМ Продажи и исполнение | H2: ТРАНСТЕХКОМ Продажи и исполнение | I2: ТРАНСТЕХКОМ Продажи и исполнение | J2: ТРАНСТЕХКОМ Продажи и исполнение | K2: ТРАНСТЕХКОМ Продажи и исполнение | L2: ТРАНСТЕХКОМ Продажи и исполнение | M2: ТРАНСТЕХКОМ Продажи и исполнение | N2: ТРАНСТЕХКОМ Продажи и исполнение | O2: ТРАНСТЕХКОМ Продажи и исполнение | P2: ТРАНСТЕХКОМ Продажи и исполнение | Q2: ТРАНСТЕХКОМ Продажи и исполнение
B3: Демонстрационные данные. Обновлённый макет под процессы ТТК, без подключения к учётным системам. | C3: Демонстрационные данные. Обновлённый макет под процессы ТТК, без подключения к учётным системам. | D3: Демонстрационные данные. Обновлённый макет под процессы ТТК, без подключения к учётным системам. | E3: Демонстрационные данные. Обновлённый макет под процессы ТТК, без подключения к учётным системам. | F3: Демонстрационные данные. Обновлённый макет под процессы ТТК, без подключения к учётным системам. | G3: Демонстрационные данные. Обновлённый макет под процессы ТТК, без подключения к учётным системам. | H3: Демонстрационные данные. Обновлённый макет под процессы ТТК, без подключения к учётным системам. | I3: Демонстрационные данные. Обновлённый макет под процессы ТТК, без подключения к учётным системам. | J3: Демонстрационные данные. Обновлённый макет под процессы ТТК, без подключения к учётным системам. | K3: Демонстрационные данные. Обновлённый макет под процессы ТТК, без подключения к учётным системам. | L3: Демонстрационные данные. Обновлённый макет под процессы ТТК, без подключения к учётным системам. | M3: Демонстрационные данные. Обновлённый макет под процессы ТТК, без подключения к учётным системам. | N3: Демонстрационные данные. Обновлённый макет под процессы ТТК, без подключения к учётным системам. | O3: Демонстрационные данные. Обновлённый макет под процессы ТТК, без подключения к учётным системам. | P3: Демонстрационные данные. Обновлённый макет под процессы ТТК, без подключения к учётным системам. | Q3: Демонстрационные данные. Обновлённый макет под процессы ТТК, без подключения к учётным системам.
B4: Срез | C4: Срез | D4: 46321.375 | E4: 46321.375 | F4: 46321.375 | G4: Сотрудник | H4: Сотрудник | I4: Все | J4: Все | K4: Все | L4: Все | M4: Продажи | N4: Продажи | O4: Все | P4: Все | Q4: Все
B7: Действия на сегодня | C7: Действия на сегодня | D7: Действия на сегодня | E7: Действия на сегодня | F7: Жёсткие сроки ≤ 48 ч | G7: Жёсткие сроки ≤ 48 ч | H7: Жёсткие сроки ≤ 48 ч | I7: Жёсткие сроки ≤ 48 ч | J7: Просрочено у продаж | K7: Просрочено у продаж | L7: Просрочено у продаж | M7: Просрочено у продаж | N7: Ожидание других | O7: Ожидание других | P7: Ожидание других | Q7: Ожидание других
B8: =COUNTIFS(Действия!$S$7:$S$106,1,Действия!$F$7:$F$106,">="&INT($D$4),Действия!$F$7:$F$106,"<"&INT($D$4)+1) -> 9 | F8: =COUNTIFS(Действия!$S$7:$S$106,1,Действия!$P$7:$P$106,1) -> 4 | J8: =COUNTIFS(Действия!$S$7:$S$106,1,Действия!$Q$7:$Q$106,1) -> 2 | N8: =COUNTIFS(Действия!$S$7:$S$106,1,Действия!$R$7:$R$106,1) -> 7
B10: ="Объектов: "&SUM(Реестр!$X$7:$X$106)&" • без следующего действия продавца: "&COUNTIFS(Реестр!$X$7:$X$106,1,Реестр!$Z$7:$Z$106,1)&" • без срока этапа: "&COUNTIFS(Реестр!$X$7:$X$106,1,Реестр!$AC$7:$AC$106,1)&" • карточки сверху считают действия, не сделки" -> Объектов: 15 • без следующего действия продавца: 4 • без срока этапа: 0 • карточки сверху считают действия, не сделки
B12: СЕГОДНЯ И КРИТИЧЕСКИЕ СРОКИ | C12: СЕГОДНЯ И КРИТИЧЕСКИЕ СРОКИ | D12: СЕГОДНЯ И КРИТИЧЕСКИЕ СРОКИ | E12: СЕГОДНЯ И КРИТИЧЕСКИЕ СРОКИ | F12: СЕГОДНЯ И КРИТИЧЕСКИЕ СРОКИ | G12: СЕГОДНЯ И КРИТИЧЕСКИЕ СРОКИ | H12: СЕГОДНЯ И КРИТИЧЕСКИЕ СРОКИ | I12: СЕГОДНЯ И КРИТИЧЕСКИЕ СРОКИ | J12: СЕГОДНЯ И КРИТИЧЕСКИЕ СРОКИ | K12: СЕГОДНЯ И КРИТИЧЕСКИЕ СРОКИ | L12: СЕГОДНЯ И КРИТИЧЕСКИЕ СРОКИ | M12: СЕГОДНЯ И КРИТИЧЕСКИЕ СРОКИ | N12: СЕГОДНЯ И КРИТИЧЕСКИЕ СРОКИ | O12: СЕГОДНЯ И КРИТИЧЕСКИЕ СРОКИ | P12: СЕГОДНЯ И КРИТИЧЕСКИЕ СРОКИ | Q12: СЕГОДНЯ И КРИТИЧЕСКИЕ СРОКИ
B13: Объект | C13: Объект | D13: Действие | E13: Действие | F13: Действие | G13: Действие | H13: Действие | I13: Кто выполняет | J13: Кто выполняет | K13: Кто выполняет | L13: Срок | M13: Срок | N13: Срок | O13: Причина приоритета | P13: Причина приоритета | Q13: Причина приоритета
B14: =IF(COUNT(Действия!$U$7:$U$106)<1,"",IF(INDEX(Действия!$B$7:$B$106,MATCH(1,Действия!$U$7:$U$106,0))=0,"Нет данных",INDEX(Действия!$B$7:$B$106,MATCH(1,Действия!$U$7:$U$106,0)))) -> С-107 | D14: =IF(COUNT(Действия!$U$7:$U$106)<1,"",IF(INDEX(Действия!$C$7:$C$106,MATCH(1,Действия!$U$7:$U$106,0))=0,"Нет данных",INDEX(Действия!$C$7:$C$106,MATCH(1,Действия!$U$7:$U$106,0)))) -> Подать ответ на технический дозапрос | I14: =IF(COUNT(Действия!$U$7:$U$106)<1,"",IF(INDEX(Действия!$E$7:$E$106,MATCH(1,Действия!$U$7:$U$106,0))=0,"Нет данных",INDEX(Действия!$E$7:$E$106,MATCH(1,Действия!$U$7:$U$106,0)))) -> Тендерный специалист | L14: =IF(COUNT(Действия!$U$7:$U$106)<1,"",IF(INDEX(Действия!$F$7:$F$106,MATCH(1,Действия!$U$7:$U$106,0))=0,"Нет данных",INDEX(Действия!$F$7:$F$106,MATCH(1,Действия!$U$7:$U$106,0)))) -> 46321.458 | O14: =IF(COUNT(Действия!$U$7:$U$106)<1,"",IF(INDEX(Действия!$P$7:$P$106,MATCH(1,Действия!$U$7:$U$106,0))=1,"Жёсткий срок",IF(INDEX(Действия!$Q$7:$Q$106,MATCH(1,Действия!$U$7:$U$106,0))=1,"Просрочка продаж",IF(INDEX(Действия!$O$7:$O$106,MATCH(1,Действия!$U$7:$U$106,0))>0,"Просрочка ожидания",IF(INDEX(Действия!$I$7:$I$106,MATCH(1,Действия!$U$7:$U$106,0))="Да","Решение ИД","Сегодня"))))) -> Жёсткий срок
B15: =IF(COUNT(Действия!$U$7:$U$106)<2,"",IF(INDEX(Действия!$B$7:$B$106,MATCH(2,Действия!$U$7:$U$106,0))=0,"Нет данных",INDEX(Действия!$B$7:$B$106,MATCH(2,Действия!$U$7:$U$106,0)))) -> И-202 | D15: =IF(COUNT(Действия!$U$7:$U$106)<2,"",IF(INDEX(Действия!$C$7:$C$106,MATCH(2,Действия!$U$7:$U$106,0))=0,"Нет данных",INDEX(Действия!$C$7:$C$106,MATCH(2,Действия!$U$7:$U$106,0)))) -> Согласовать изменённую дату с клиентом | I15: =IF(COUNT(Действия!$U$7:$U$106)<2,"",IF(INDEX(Действия!$E$7:$E$106,MATCH(2,Действия!$U$7:$U$106,0))=0,"Нет данных",INDEX(Действия!$E$7:$E$106,MATCH(2,Действия!$U$7:$U$106,0)))) -> Менеджер 2 | L15: =IF(COUNT(Действия!$U$7:$U$106)<2,"",IF(INDEX(Действия!$F$7:$F$106,MATCH(2,Действия!$U$7:$U$106,0))=0,"Нет данных",INDEX(Действия!$F$7:$F$106,MATCH(2,Действия!$U$7:$U$106,0)))) -> 46321.542 | O15: =IF(COUNT(Действия!$U$7:$U$106)<2,"",IF(INDEX(Действия!$P$7:$P$106,MATCH(2,Действия!$U$7:$U$106,0))=1,"Жёсткий срок",IF(INDEX(Действия!$Q$7:$Q$106,MATCH(2,Действия!$U$7:$U$106,0))=1,"Просрочка продаж",IF(INDEX(Действия!$O$7:$O$106,MATCH(2,Действия!$U$7:$U$106,0))>0,"Просрочка ожидания",IF(INDEX(Действия!$I$7:$I$106,MATCH(2,Действия!$U$7:$U$106,0))="Да","Решение ИД","Сегодня"))))) -> Жёсткий срок
B16: =IF(COUNT(Действия!$U$7:$U$106)<3,"",IF(INDEX(Действия!$B$7:$B$106,MATCH(3,Действия!$U$7:$U$106,0))=0,"Нет данных",INDEX(Действия!$B$7:$B$106,MATCH(3,Действия!$U$7:$U$106,0)))) -> С-109 | D16: =IF(COUNT(Действия!$U$7:$U$106)<3,"",IF(INDEX(Действия!$C$7:$C$106,MATCH(3,Действия!$U$7:$U$106,0))=0,"Нет данных",INDEX(Действия!$C$7:$C$106,MATCH(3,Действия!$U$7:$U$106,0)))) -> Подтвердить обеспечение заявки | I16: =IF(COUNT(Действия!$U$7:$U$106)<3,"",IF(INDEX(Действия!$E$7:$E$106,MATCH(3,Действия!$U$7:$U$106,0))=0,"Нет данных",INDEX(Действия!$E$7:$E$106,MATCH(3,Действия!$U$7:$U$106,0)))) -> Финансовый блок | L16: =IF(COUNT(Действия!$U$7:$U$106)<3,"",IF(INDEX(Действия!$F$7:$F$106,MATCH(3,Действия!$U$7:$U$106,0))=0,"Нет данных",INDEX(Действия!$F$7:$F$106,MATCH(3,Действия!$U$7:$U$106,0)))) -> 46321.667 | O16: =IF(COUNT(Действия!$U$7:$U$106)<3,"",IF(INDEX(Действия!$P$7:$P$106,MATCH(3,Действия!$U$7:$U$106,0))=1,"Жёсткий срок",IF(INDEX(Действия!$Q$7:$Q$106,MATCH(3,Действия!$U$7:$U$106,0))=1,"Просрочка продаж",IF(INDEX(Действия!$O$7:$O$106,MATCH(3,Действия!$U$7:$U$106,0))>0,"Просрочка ожидания",IF(INDEX(Действия!$I$7:$I$106,MATCH(3,Действия!$U$7:$U$106,0))="Да","Решение ИД","Сегодня"))))) -> Жёсткий срок
B17: =IF(COUNT(Действия!$U$7:$U$106)<4,"",IF(INDEX(Действия!$B$7:$B$106,MATCH(4,Действия!$U$7:$U$106,0))=0,"Нет данных",INDEX(Действия!$B$7:$B$106,MATCH(4,Действия!$U$7:$U$106,0)))) -> С-109 | D17: =IF(COUNT(Действия!$U$7:$U$106)<4,"",IF(INDEX(Действия!$C$7:$C$106,MATCH(4,Действия!$U$7:$U$106,0))=0,"Нет данных",INDEX(Действия!$C$7:$C$106,MATCH(4,Действия!$U$7:$U$106,0)))) -> Подать тендерную заявку | I17: =IF(COUNT(Действия!$U$7:$U$106)<4,"",IF(INDEX(Действия!$E$7:$E$106,MATCH(4,Действия!$U$7:$U$106,0))=0,"Нет данных",INDEX(Действия!$E$7:$E$106,MATCH(4,Действия!$U$7:$U$106,0)))) -> Тендерный специалист | L17: =IF(COUNT(Действия!$U$7:$U$106)<4,"",IF(INDEX(Действия!$F$7:$F$106,MATCH(4,Действия!$U$7:$U$106,0))=0,"Нет данных",INDEX(Действия!$F$7:$F$106,MATCH(4,Действия!$U$7:$U$106,0)))) -> 46322.5 | O17: =IF(COUNT(Действия!$U$7:$U$106)<4,"",IF(INDEX(Действия!$P$7:$P$106,MATCH(4,Действия!$U$7:$U$106,0))=1,"Жёсткий срок",IF(INDEX(Действия!$Q$7:$Q$106,MATCH(4,Действия!$U$7:$U$106,0))=1,"Просрочка продаж",IF(INDEX(Действия!$O$7:$O$106,MATCH(4,Действия!$U$7:$U$106,0))>0,"Просрочка ожидания",IF(INDEX(Действия!$I$7:$I$106,MATCH(4,Действия!$U$7:$U$106,0))="Да","Решение ИД","Сегодня"))))) -> Жёсткий срок
B18: =IF(COUNT(Действия!$U$7:$U$106)<5,"",IF(INDEX(Действия!$B$7:$B$106,MATCH(5,Действия!$U$7:$U$106,0))=0,"Нет данных",INDEX(Действия!$B$7:$B$106,MATCH(5,Действия!$U$7:$U$106,0)))) -> С-102 | D18: =IF(COUNT(Действия!$U$7:$U$106)<5,"",IF(INDEX(Действия!$C$7:$C$106,MATCH(5,Действия!$U$7:$U$106,0))=0,"Нет данных",INDEX(Действия!$C$7:$C$106,MATCH(5,Действия!$U$7:$U$106,0)))) -> Получить сопоставимое КП завода | I18: =IF(COUNT(Действия!$U$7:$U$106)<5,"",IF(INDEX(Действия!$E$7:$E$106,MATCH(5,Действия!$U$7:$U$106,0))=0,"Нет данных",INDEX(Действия!$E$7:$E$106,MATCH(5,Действия!$U$7:$U$106,0)))) -> Снабженец | L18: =IF(COUNT(Действия!$U$7:$U$106)<5,"",IF(INDEX(Действия!$F$7:$F$106,MATCH(5,Действия!$U$7:$U$106,0))=0,"Нет данных",INDEX(Действия!$F$7:$F$106,MATCH(5,Действия!$U$7:$U$106,0)))) -> 46319.667 | O18: =IF(COUNT(Действия!$U$7:$U$106)<5,"",IF(INDEX(Действия!$P$7:$P$106,MATCH(5,Действия!$U$7:$U$106,0))=1,"Жёсткий срок",IF(INDEX(Действия!$Q$7:$Q$106,MATCH(5,Действия!$U$7:$U$106,0))=1,"Просрочка продаж",IF(INDEX(Действия!$O$7:$O$106,MATCH(5,Действия!$U$7:$U$106,0))>0,"Просрочка ожидания",IF(INDEX(Действия!$I$7:$I$106,MATCH(5,Действия!$U$7:$U$106,0))="Да","Решение ИД","Сегодня"))))) -> Просрочка ожидания
B19: =IF(COUNT(Действия!$U$7:$U$106)<6,"",IF(INDEX(Действия!$B$7:$B$106,MATCH(6,Действия!$U$7:$U$106,0))=0,"Нет данных",INDEX(Действия!$B$7:$B$106,MATCH(6,Действия!$U$7:$U$106,0)))) -> И-203 | D19: =IF(COUNT(Действия!$U$7:$U$106)<6,"",IF(INDEX(Действия!$C$7:$C$106,MATCH(6,Действия!$U$7:$U$106,0))=0,"Нет данных",INDEX(Действия!$C$7:$C$106,MATCH(6,Действия!$U$7:$U$106,0)))) -> Согласовать дату погашения долга | I19: =IF(COUNT(Действия!$U$7:$U$106)<6,"",IF(INDEX(Действия!$E$7:$E$106,MATCH(6,Действия!$U$7:$U$106,0))=0,"Нет данных",INDEX(Действия!$E$7:$E$106,MATCH(6,Действия!$U$7:$U$106,0)))) -> Тендерный специалист | L19: =IF(COUNT(Действия!$U$7:$U$106)<6,"",IF(INDEX(Действия!$F$7:$F$106,MATCH(6,Действия!$U$7:$U$106,0))=0,"Нет данных",INDEX(Действия!$F$7:$F$106,MATCH(6,Действия!$U$7:$U$106,0)))) -> 46320.583 | O19: =IF(COUNT(Действия!$U$7:$U$106)<6,"",IF(INDEX(Действия!$P$7:$P$106,MATCH(6,Действия!$U$7:$U$106,0))=1,"Жёсткий срок",IF(INDEX(Действия!$Q$7:$Q$106,MATCH(6,Действия!$U$7:$U$106,0))=1,"Просрочка продаж",IF(INDEX(Действия!$O$7:$O$106,MATCH(6,Действия!$U$7:$U$106,0))>0,"Просрочка ожидания",IF(INDEX(Действия!$I$7:$I$106,MATCH(6,Действия!$U$7:$U$106,0))="Да","Решение ИД","Сегодня"))))) -> Просрочка продаж
B20: Сначала жёсткие сроки, затем прочие просрочки и задачи на сегодня. Внутри группы — ближайший срок. | C20: Сначала жёсткие сроки, затем прочие просрочки и задачи на сегодня. Внутри группы — ближайший срок. | D20: Сначала жёсткие сроки, затем прочие просрочки и задачи на сегодня. Внутри группы — ближайший срок. | E20: Сначала жёсткие сроки, затем прочие просрочки и задачи на сегодня. Внутри группы — ближайший срок. | F20: Сначала жёсткие сроки, затем прочие просрочки и задачи на сегодня. Внутри группы — ближайший срок. | G20: Сначала жёсткие сроки, затем прочие просрочки и задачи на сегодня. Внутри группы — ближайший срок. | H20: Сначала жёсткие сроки, затем прочие просрочки и задачи на сегодня. Внутри группы — ближайший срок. | I20: Сначала жёсткие сроки, затем прочие просрочки и задачи на сегодня. Внутри группы — ближайший срок. | J20: Сначала жёсткие сроки, затем прочие просрочки и задачи на сегодня. Внутри группы — ближайший срок. | K20: Сначала жёсткие сроки, затем прочие просрочки и задачи на сегодня. Внутри группы — ближайший срок. | L20: Сначала жёсткие сроки, затем прочие просрочки и задачи на сегодня. Внутри группы — ближайший срок. | M20: Сначала жёсткие сроки, затем прочие просрочки и задачи на сегодня. Внутри группы — ближайший срок. | N20: Сначала жёсткие сроки, затем прочие просрочки и задачи на сегодня. Внутри группы — ближайший срок. | O20: Сначала жёсткие сроки, затем прочие просрочки и задачи на сегодня. Внутри группы — ближайший срок. | P20: Сначала жёсткие сроки, затем прочие просрочки и задачи на сегодня. Внутри группы — ближайший срок. | Q20: Сначала жёсткие сроки, затем прочие просрочки и задачи на сегодня. Внутри группы — ближайший срок.
B22: ГДЕ НАХОДИТСЯ РАБОТА | C22: ГДЕ НАХОДИТСЯ РАБОТА | D22: ГДЕ НАХОДИТСЯ РАБОТА | E22: ГДЕ НАХОДИТСЯ РАБОТА | F22: ГДЕ НАХОДИТСЯ РАБОТА | G22: ГДЕ НАХОДИТСЯ РАБОТА | H22: ГДЕ НАХОДИТСЯ РАБОТА | I22: ГДЕ НАХОДИТСЯ РАБОТА | K22: ЧЕГО НЕ ХВАТАЕТ ДЛЯ РАСЧЁТА | L22: ЧЕГО НЕ ХВАТАЕТ ДЛЯ РАСЧЁТА | M22: ЧЕГО НЕ ХВАТАЕТ ДЛЯ РАСЧЁТА | N22: ЧЕГО НЕ ХВАТАЕТ ДЛЯ РАСЧЁТА | O22: ЧЕГО НЕ ХВАТАЕТ ДЛЯ РАСЧЁТА | P22: ЧЕГО НЕ ХВАТАЕТ ДЛЯ РАСЧЁТА | Q22: ЧЕГО НЕ ХВАТАЕТ ДЛЯ РАСЧЁТА
B23: Группа этапов | C23: Группа этапов | D23: Группа этапов | E23: Группа этапов | F23: Группа этапов | G23: Всего | H23: Просрочено | I23: Просрочено
B24: Лиды | C24: Лиды | D24: Лиды | E24: Лиды | F24: Лиды | G24: =COUNTIFS(Реестр!$X$7:$X$106,1,Реестр!$AB$7:$AB$106,B24) -> 3 | H24: =COUNTIFS(Реестр!$X$7:$X$106,1,Реестр!$AB$7:$AB$106,B24,Реестр!$Y$7:$Y$106,1) -> 1 | K24: ТЗ и объёмы | L24: ТЗ и объёмы | M24: ТЗ и объёмы | N24: ТЗ и объёмы | O24: ТЗ и объёмы | P24: =COUNTIFS(Реестр!$X$7:$X$106,1,Реестр!$AB$7:$AB$106,"Расчёт / решение",Реестр!$I$7:$I$106,"Нет")+COUNTIFS(Реестр!$X$7:$X$106,1,Реестр!$AB$7:$AB$106,"Расчёт / решение",Реестр!$I$7:$I$106,"") -> 0
B25: Запрос / проверка | C25: Запрос / проверка | D25: Запрос / проверка | E25: Запрос / проверка | F25: Запрос / проверка | G25: =COUNTIFS(Реестр!$X$7:$X$106,1,Реестр!$AB$7:$AB$106,B25) -> 1 | H25: =COUNTIFS(Реестр!$X$7:$X$106,1,Реестр!$AB$7:$AB$106,B25,Реестр!$Y$7:$Y$106,1) -> 1 | K25: Предложение завода | L25: Предложение завода | M25: Предложение завода | N25: Предложение завода | O25: Предложение завода | P25: =COUNTIFS(Реестр!$X$7:$X$106,1,Реестр!$AB$7:$AB$106,"Расчёт / решение",Реестр!$J$7:$J$106,"Нет")+COUNTIFS(Реестр!$X$7:$X$106,1,Реестр!$AB$7:$AB$106,"Расчёт / решение",Реестр!$J$7:$J$106,"") -> 1
B26: Расчёт / решение | C26: Расчёт / решение | D26: Расчёт / решение | E26: Расчёт / решение | F26: Расчёт / решение | G26: =COUNTIFS(Реестр!$X$7:$X$106,1,Реестр!$AB$7:$AB$106,B26) -> 2 | H26: =COUNTIFS(Реестр!$X$7:$X$106,1,Реестр!$AB$7:$AB$106,B26,Реестр!$Y$7:$Y$106,1) -> 1 | K26: Расчёт логистики | L26: Расчёт логистики | M26: Расчёт логистики | N26: Расчёт логистики | O26: Расчёт логистики | P26: =COUNTIFS(Реестр!$X$7:$X$106,1,Реестр!$AB$7:$AB$106,"Расчёт / решение",Реестр!$K$7:$K$106,"Нет")+COUNTIFS(Реестр!$X$7:$X$106,1,Реестр!$AB$7:$AB$106,"Расчёт / решение",Реестр!$K$7:$K$106,"") -> 1
B27: КП / подготовка | C27: КП / подготовка | D27: КП / подготовка | E27: КП / подготовка | F27: КП / подготовка | G27: =COUNTIFS(Реестр!$X$7:$X$106,1,Реестр!$AB$7:$AB$106,B27) -> 3 | H27: =COUNTIFS(Реестр!$X$7:$X$106,1,Реестр!$AB$7:$AB$106,B27,Реестр!$Y$7:$Y$106,1) -> 1 | K27: Дополнительные расходы | L27: Дополнительные расходы | M27: Дополнительные расходы | N27: Дополнительные расходы | O27: Дополнительные расходы | P27: =COUNTIFS(Реестр!$X$7:$X$106,1,Реестр!$AB$7:$AB$106,"Расчёт / решение",Реестр!$L$7:$L$106,"Нет")+COUNTIFS(Реестр!$X$7:$X$106,1,Реестр!$AB$7:$AB$106,"Расчёт / решение",Реестр!$L$7:$L$106,"") -> 0
B28: Переговоры / подача | C28: Переговоры / подача | D28: Переговоры / подача | E28: Переговоры / подача | F28: Переговоры / подача | G28: =COUNTIFS(Реестр!$X$7:$X$106,1,Реестр!$AB$7:$AB$106,B28) -> 2 | H28: =COUNTIFS(Реестр!$X$7:$X$106,1,Реестр!$AB$7:$AB$106,B28,Реестр!$Y$7:$Y$106,1) -> 0 | K28: Согласованная цена | L28: Согласованная цена | M28: Согласованная цена | N28: Согласованная цена | O28: Согласованная цена | P28: =COUNTIFS(Реестр!$X$7:$X$106,1,Реестр!$AB$7:$AB$106,"Расчёт / решение",Реестр!$M$7:$M$106,"Нет")+COUNTIFS(Реестр!$X$7:$X$106,1,Реестр!$AB$7:$AB$106,"Расчёт / решение",Реестр!$M$7:$M$106,"") -> 2
B29: Договор / результат | C29: Договор / результат | D29: Договор / результат | E29: Договор / результат | F29: Договор / результат | G29: =COUNTIFS(Реестр!$X$7:$X$106,1,Реестр!$AB$7:$AB$106,B29) -> 1 | H29: =COUNTIFS(Реестр!$X$7:$X$106,1,Реестр!$AB$7:$AB$106,B29,Реестр!$Y$7:$Y$106,1) -> 1
B30: Передача / исполнение | C30: Передача / исполнение | D30: Передача / исполнение | E30: Передача / исполнение | F30: Передача / исполнение | G30: =COUNTIFS(Реестр!$X$7:$X$106,1,Реестр!$AB$7:$AB$106,B30) -> 2 | H30: =COUNTIFS(Реестр!$X$7:$X$106,1,Реестр!$AB$7:$AB$106,B30,Реестр!$Y$7:$Y$106,1) -> 0 | K30: Количество объектов на расчёте с отсутствующей частью. Готовность — по данным реестра. | L30: Количество объектов на расчёте с отсутствующей частью. Готовность — по данным реестра. | M30: Количество объектов на расчёте с отсутствующей частью. Готовность — по данным реестра. | N30: Количество объектов на расчёте с отсутствующей частью. Готовность — по данным реестра. | O30: Количество объектов на расчёте с отсутствующей частью. Готовность — по данным реестра. | P30: Количество объектов на расчёте с отсутствующей частью. Готовность — по данным реестра. | Q30: Количество объектов на расчёте с отсутствующей частью. Готовность — по данным реестра.
B31: Приёмка / оплата | C31: Приёмка / оплата | D31: Приёмка / оплата | E31: Приёмка / оплата | F31: Приёмка / оплата | G31: =COUNTIFS(Реестр!$X$7:$X$106,1,Реестр!$AB$7:$AB$106,B31) -> 1 | H31: =COUNTIFS(Реестр!$X$7:$X$106,1,Реестр!$AB$7:$AB$106,B31,Реестр!$Y$7:$Y$106,1) -> 0 | K31: Количество объектов на расчёте с отсутствующей частью. Готовность — по данным реестра. | L31: Количество объектов на расчёте с отсутствующей частью. Готовность — по данным реестра. | M31: Количество объектов на расчёте с отсутствующей частью. Готовность — по данным реестра. | N31: Количество объектов на расчёте с отсутствующей частью. Готовность — по данным реестра. | O31: Количество объектов на расчёте с отсутствующей частью. Готовность — по данным реестра. | P31: Количество объектов на расчёте с отсутствующей частью. Готовность — по данным реестра. | Q31: Количество объектов на расчёте с отсутствующей частью. Готовность — по данным реестра.
B33: ОЧЕРЕДЬ СОТРУДНИКОВ | C33: ОЧЕРЕДЬ СОТРУДНИКОВ | D33: ОЧЕРЕДЬ СОТРУДНИКОВ | E33: ОЧЕРЕДЬ СОТРУДНИКОВ | F33: ОЧЕРЕДЬ СОТРУДНИКОВ | G33: ОЧЕРЕДЬ СОТРУДНИКОВ | H33: ОЧЕРЕДЬ СОТРУДНИКОВ | I33: ОЧЕРЕДЬ СОТРУДНИКОВ | J33: ОЧЕРЕДЬ СОТРУДНИКОВ | K33: ОЧЕРЕДЬ СОТРУДНИКОВ | L33: ОЧЕРЕДЬ СОТРУДНИКОВ | M33: ОЧЕРЕДЬ СОТРУДНИКОВ | N33: ОЧЕРЕДЬ СОТРУДНИКОВ | O33: ОЧЕРЕДЬ СОТРУДНИКОВ | P33: ОЧЕРЕДЬ СОТРУДНИКОВ | Q33: ОЧЕРЕДЬ СОТРУДНИКОВ
B34: Сотрудник | C34: Сотрудник | D34: Сотрудник | E34: Сотрудник | F34: Сотрудник | G34: Лиды | H34: Лиды | I34: Сделки | J34: Сделки | K34: Исполнение | L34: Исполнение | M34: Просрочки продаж | N34: Просрочки продаж | O34: Ожидания других | P34: Ожидания других | Q34: Ожидания других
B35: =Реестр!A138 -> Менеджер 1 | G35: =COUNTIFS(Реестр!$X$7:$X$106,1,Реестр!$D$7:$D$106,B35,Реестр!$B$7:$B$106,"Лид") -> 2 | I35: =COUNTIFS(Реестр!$X$7:$X$106,1,Реестр!$D$7:$D$106,B35,Реестр!$B$7:$B$106,"Сделка") -> 3 | K35: =COUNTIFS(Реестр!$X$7:$X$106,1,Реестр!$D$7:$D$106,B35,Реестр!$B$7:$B$106,"Исполнение") -> 1 | M35: =COUNTIFS(Действия!$S$7:$S$106,1,Действия!$L$7:$L$106,B35,Действия!$Q$7:$Q$106,1) -> 0 | O35: =COUNTIFS(Действия!$S$7:$S$106,1,Действия!$L$7:$L$106,B35,Действия!$R$7:$R$106,1) -> 2
B36: =Реестр!A139 -> Менеджер 2 | G36: =COUNTIFS(Реестр!$X$7:$X$106,1,Реестр!$D$7:$D$106,B36,Реестр!$B$7:$B$106,"Лид") -> 1 | I36: =COUNTIFS(Реестр!$X$7:$X$106,1,Реестр!$D$7:$D$106,B36,Реестр!$B$7:$B$106,"Сделка") -> 3 | K36: =COUNTIFS(Реестр!$X$7:$X$106,1,Реестр!$D$7:$D$106,B36,Реестр!$B$7:$B$106,"Исполнение") -> 1 | M36: =COUNTIFS(Действия!$S$7:$S$106,1,Действия!$L$7:$L$106,B36,Действия!$Q$7:$Q$106,1) -> 1 | O36: =COUNTIFS(Действия!$S$7:$S$106,1,Действия!$L$7:$L$106,B36,Действия!$R$7:$R$106,1) -> 2
B37: =Реестр!A140 -> Тендерный специалист | G37: =COUNTIFS(Реестр!$X$7:$X$106,1,Реестр!$D$7:$D$106,B37,Реестр!$B$7:$B$106,"Лид") -> 0 | I37: =COUNTIFS(Реестр!$X$7:$X$106,1,Реестр!$D$7:$D$106,B37,Реестр!$B$7:$B$106,"Сделка") -> 3 | K37: =COUNTIFS(Реестр!$X$7:$X$106,1,Реестр!$D$7:$D$106,B37,Реестр!$B$7:$B$106,"Исполнение") -> 1 | M37: =COUNTIFS(Действия!$S$7:$S$106,1,Действия!$L$7:$L$106,B37,Действия!$Q$7:$Q$106,1) -> 1 | O37: =COUNTIFS(Действия!$S$7:$S$106,1,Действия!$L$7:$L$106,B37,Действия!$R$7:$R$106,1) -> 3
B39: ТРЕБУЕТ РЕШЕНИЯ ИД | C39: ТРЕБУЕТ РЕШЕНИЯ ИД | D39: ТРЕБУЕТ РЕШЕНИЯ ИД | E39: ТРЕБУЕТ РЕШЕНИЯ ИД | F39: ТРЕБУЕТ РЕШЕНИЯ ИД | G39: ТРЕБУЕТ РЕШЕНИЯ ИД | H39: ТРЕБУЕТ РЕШЕНИЯ ИД | I39: ТРЕБУЕТ РЕШЕНИЯ ИД | J39: ТРЕБУЕТ РЕШЕНИЯ ИД | K39: ТРЕБУЕТ РЕШЕНИЯ ИД | L39: ТРЕБУЕТ РЕШЕНИЯ ИД | M39: ТРЕБУЕТ РЕШЕНИЯ ИД | N39: ТРЕБУЕТ РЕШЕНИЯ ИД | O39: ТРЕБУЕТ РЕШЕНИЯ ИД | P39: ТРЕБУЕТ РЕШЕНИЯ ИД | Q39: ТРЕБУЕТ РЕШЕНИЯ ИД
B40: ="Открытых вопросов: "&COUNTIFS(Действия!$S$7:$S$106,1,Действия!$I$7:$I$106,"Да")&". Все вопросы — фильтр «Нужно решение ИД = Да» на листе «Действия»." -> Открытых вопросов: 4. Все вопросы — фильтр «Нужно решение ИД = Да» на листе «Действия».
B41: =IF(COUNT(Действия!$X$7:$X$106)<1,"",INDEX(Действия!$B$7:$B$106,MATCH(1,Действия!$X$7:$X$106,0))) -> С-102 | D41: =IF(COUNT(Действия!$X$7:$X$106)<1,"",IF(INDEX(Действия!$J$7:$J$106,MATCH(1,Действия!$X$7:$X$106,0))=0,"Сформулировать вопрос для ИД",INDEX(Действия!$J$7:$J$106,MATCH(1,Действия!$X$7:$X$106,0)))) -> Определить замену поставщика или согласовать перенос расчёта | N41: =IF(COUNT(Действия!$X$7:$X$106)<1,"",INDEX(Действия!$F$7:$F$106,MATCH(1,Действия!$X$7:$X$106,0))) -> 46319.667
B42: =IF(COUNT(Действия!$X$7:$X$106)<2,"",INDEX(Действия!$B$7:$B$106,MATCH(2,Действия!$X$7:$X$106,0))) -> С-108 | D42: =IF(COUNT(Действия!$X$7:$X$106)<2,"",IF(INDEX(Действия!$J$7:$J$106,MATCH(2,Действия!$X$7:$X$106,0))=0,"Сформулировать вопрос для ИД",INDEX(Действия!$J$7:$J$106,MATCH(2,Действия!$X$7:$X$106,0)))) -> Решить вопрос по ответственности и срокам договора | N42: =IF(COUNT(Действия!$X$7:$X$106)<2,"",INDEX(Действия!$F$7:$F$106,MATCH(2,Действия!$X$7:$X$106,0))) -> 46320.625
B43: =IF(COUNT(Действия!$X$7:$X$106)<3,"",INDEX(Действия!$B$7:$B$106,MATCH(3,Действия!$X$7:$X$106,0))) -> И-202 | D43: =IF(COUNT(Действия!$X$7:$X$106)<3,"",IF(INDEX(Действия!$J$7:$J$106,MATCH(3,Действия!$X$7:$X$106,0))=0,"Сформулировать вопрос для ИД",INDEX(Действия!$J$7:$J$106,MATCH(3,Действия!$X$7:$X$106,0)))) -> Определить допустимое решение по переносу поставки | N43: =IF(COUNT(Действия!$X$7:$X$106)<3,"",INDEX(Действия!$F$7:$F$106,MATCH(3,Действия!$X$7:$X$106,0))) -> 46321.542
B44: =IF(COUNT(Действия!$X$7:$X$106)<4,"",INDEX(Действия!$B$7:$B$106,MATCH(4,Действия!$X$7:$X$106,0))) -> С-103 | D44: =IF(COUNT(Действия!$X$7:$X$106)<4,"",IF(INDEX(Действия!$J$7:$J$106,MATCH(4,Действия!$X$7:$X$106,0))=0,"Сформулировать вопрос для ИД",INDEX(Действия!$J$7:$J$106,MATCH(4,Действия!$X$7:$X$106,0)))) -> Утвердить цену с учётом доставки и обеспечения | N44: =IF(COUNT(Действия!$X$7:$X$106)<4,"",INDEX(Действия!$F$7:$F$106,MATCH(4,Действия!$X$7:$X$106,0))) -> 46321.583
B46: Жёлтые ячейки — ввод. Реестр: объекты, готовность и данные 1С. Действия: задачи, ожидания и решения. Имена — Реестр!A138:A140. | C46: Жёлтые ячейки — ввод. Реестр: объекты, готовность и данные 1С. Действия: задачи, ожидания и решения. Имена — Реестр!A138:A140. | D46: Жёлтые ячейки — ввод. Реестр: объекты, готовность и данные 1С. Действия: задачи, ожидания и решения. Имена — Реестр!A138:A140. | E46: Жёлтые ячейки — ввод. Реестр: объекты, готовность и данные 1С. Действия: задачи, ожидания и решения. Имена — Реестр!A138:A140. | F46: Жёлтые ячейки — ввод. Реестр: объекты, готовность и данные 1С. Действия: задачи, ожидания и решения. Имена — Реестр!A138:A140. | G46: Жёлтые ячейки — ввод. Реестр: объекты, готовность и данные 1С. Действия: задачи, ожидания и решения. Имена — Реестр!A138:A140. | H46: Жёлтые ячейки — ввод. Реестр: объекты, готовность и данные 1С. Действия: задачи, ожидания и решения. Имена — Реестр!A138:A140. | I46: Жёлтые ячейки — ввод. Реестр: объекты, готовность и данные 1С. Действия: задачи, ожидания и решения. Имена — Реестр!A138:A140. | J46: Жёлтые ячейки — ввод. Реестр: объекты, готовность и данные 1С. Действия: задачи, ожидания и решения. Имена — Реестр!A138:A140. | K46: Жёлтые ячейки — ввод. Реестр: объекты, готовность и данные 1С. Действия: задачи, ожидания и решения. Имена — Реестр!A138:A140. | L46: Жёлтые ячейки — ввод. Реестр: объекты, готовность и данные 1С. Действия: задачи, ожидания и решения. Имена — Реестр!A138:A140. | M46: Жёлтые ячейки — ввод. Реестр: объекты, готовность и данные 1С. Действия: задачи, ожидания и решения. Имена — Реестр!A138:A140. | N46: Жёлтые ячейки — ввод. Реестр: объекты, готовность и данные 1С. Действия: задачи, ожидания и решения. Имена — Реестр!A138:A140. | O46: Жёлтые ячейки — ввод. Реестр: объекты, готовность и данные 1С. Действия: задачи, ожидания и решения. Имена — Реестр!A138:A140. | P46: Жёлтые ячейки — ввод. Реестр: объекты, готовность и данные 1С. Действия: задачи, ожидания и решения. Имена — Реестр!A138:A140. | Q46: Жёлтые ячейки — ввод. Реестр: объекты, готовность и данные 1С. Действия: задачи, ожидания и решения. Имена — Реестр!A138:A140.
B47: Ожидания других отделов не снимают ответственность продавца за контакт с клиентом. Сроки этапов и жёсткие сроки — разные поля. | C47: Ожидания других отделов не снимают ответственность продавца за контакт с клиентом. Сроки этапов и жёсткие сроки — разные поля. | D47: Ожидания других отделов не снимают ответственность продавца за контакт с клиентом. Сроки этапов и жёсткие сроки — разные поля. | E47: Ожидания других отделов не снимают ответственность продавца за контакт с клиентом. Сроки этапов и жёсткие сроки — разные поля. | F47: Ожидания других отделов не снимают ответственность продавца за контакт с клиентом. Сроки этапов и жёсткие сроки — разные поля. | G47: Ожидания других отделов не снимают ответственность продавца за контакт с клиентом. Сроки этапов и жёсткие сроки — разные поля. | H47: Ожидания других отделов не снимают ответственность продавца за контакт с клиентом. Сроки этапов и жёсткие сроки — разные поля. | I47: Ожидания других отделов не снимают ответственность продавца за контакт с клиентом. Сроки этапов и жёсткие сроки — разные поля. | J47: Ожидания других отделов не снимают ответственность продавца за контакт с клиентом. Сроки этапов и жёсткие сроки — разные поля. | K47: Ожидания других отделов не снимают ответственность продавца за контакт с клиентом. Сроки этапов и жёсткие сроки — разные поля. | L47: Ожидания других отделов не снимают ответственность продавца за контакт с клиентом. Сроки этапов и жёсткие сроки — разные поля. | M47: Ожидания других отделов не снимают ответственность продавца за контакт с клиентом. Сроки этапов и жёсткие сроки — разные поля. | N47: Ожидания других отделов не снимают ответственность продавца за контакт с клиентом. Сроки этапов и жёсткие сроки — разные поля. | O47: Ожидания других отделов не снимают ответственность продавца за контакт с клиентом. Сроки этапов и жёсткие сроки — разные поля. | P47: Ожидания других отделов не снимают ответственность продавца за контакт с клиентом. Сроки этапов и жёсткие сроки — разные поля. | Q47: Ожидания других отделов не снимают ответственность продавца за контакт с клиентом. Сроки этапов и жёсткие сроки — разные поля.
B48: ="Контроль данных: действий без связи с объектом — "&COUNTIF(Действия!$L$7:$L$106,"Нет связи")&"; выбранных действий без срока — "&COUNTIFS(Действия!$S$7:$S$106,1,Действия!$O$7:$O$106,"Нет срока") -> Контроль данных: действий без связи с объектом — 0; выбранных действий без срока — 0

Sheet Реестр
A2: Реестр продаж ТТК | B2: Реестр продаж ТТК | C2: Реестр продаж ТТК | D2: Реестр продаж ТТК | E2: Реестр продаж ТТК | F2: Реестр продаж ТТК | G2: Реестр продаж ТТК | H2: Реестр продаж ТТК | I2: Реестр продаж ТТК | J2: Реестр продаж ТТК | K2: Реестр продаж ТТК | L2: Реестр продаж ТТК | M2: Реестр продаж ТТК | N2: Реестр продаж ТТК | O2: Реестр продаж ТТК | P2: Реестр продаж ТТК | Q2: Реестр продаж ТТК | R2: Реестр продаж ТТК | S2: Реестр продаж ТТК | T2: Реестр продаж ТТК | U2: Реестр продаж ТТК
A3: Жёлтые ячейки — ввод. Сохранены 12 исходных примеров, добавлены 3 примера исполнения. Все данные условные. | B3: Жёлтые ячейки — ввод. Сохранены 12 исходных примеров, добавлены 3 примера исполнения. Все данные условные. | C3: Жёлтые ячейки — ввод. Сохранены 12 исходных примеров, добавлены 3 примера исполнения. Все данные условные. | D3: Жёлтые ячейки — ввод. Сохранены 12 исходных примеров, добавлены 3 примера исполнения. Все данные условные. | E3: Жёлтые ячейки — ввод. Сохранены 12 исходных примеров, добавлены 3 примера исполнения. Все данные условные. | F3: Жёлтые ячейки — ввод. Сохранены 12 исходных примеров, добавлены 3 примера исполнения. Все данные условные. | G3: Жёлтые ячейки — ввод. Сохранены 12 исходных примеров, добавлены 3 примера исполнения. Все данные условные. | H3: Жёлтые ячейки — ввод. Сохранены 12 исходных примеров, добавлены 3 примера исполнения. Все данные условные. | I3: Жёлтые ячейки — ввод. Сохранены 12 исходных примеров, добавлены 3 примера исполнения. Все данные условные. | J3: Жёлтые ячейки — ввод. Сохранены 12 исходных примеров, добавлены 3 примера исполнения. Все данные условные. | K3: Жёлтые ячейки — ввод. Сохранены 12 исходных примеров, добавлены 3 примера исполнения. Все данные условные. | L3: Жёлтые ячейки — ввод. Сохранены 12 исходных примеров, добавлены 3 примера исполнения. Все данные условные. | M3: Жёлтые ячейки — ввод. Сохранены 12 исходных примеров, добавлены 3 примера исполнения. Все данные условные. | N3: Жёлтые ячейки — ввод. Сохранены 12 исходных примеров, добавлены 3 примера исполнения. Все данные условные. | O3: Жёлтые ячейки — ввод. Сохранены 12 исходных примеров, добавлены 3 примера исполнения. Все данные условные. | P3: Жёлтые ячейки — ввод. Сохранены 12 исходных примеров, добавлены 3 примера исполнения. Все данные условные. | Q3: Жёлтые ячейки — ввод. Сохранены 12 исходных примеров, добавлены 3 примера исполнения. Все данные условные. | R3: Жёлтые ячейки — ввод. Сохранены 12 исходных примеров, добавлены 3 примера исполнения. Все данные условные. | S3: Жёлтые ячейки — ввод. Сохранены 12 исходных примеров, добавлены 3 примера исполнения. Все данные условные. | T3: Жёлтые ячейки — ввод. Сохранены 12 исходных примеров, добавлены 3 примера исполнения. Все данные условные. | U3: Жёлтые ячейки — ввод. Сохранены 12 исходных примеров, добавлены 3 примера исполнения. Все данные условные.
A4: До 100 объектов. ID уникален. Прямые продажи и тендеры ведутся по своим этапам. На один объект может быть несколько действий. | B4: До 100 объектов. ID уникален. Прямые продажи и тендеры ведутся по своим этапам. На один объект может быть несколько действий. | C4: До 100 объектов. ID уникален. Прямые продажи и тендеры ведутся по своим этапам. На один объект может быть несколько действий. | D4: До 100 объектов. ID уникален. Прямые продажи и тендеры ведутся по своим этапам. На один объект может быть несколько действий. | E4: До 100 объектов. ID уникален. Прямые продажи и тендеры ведутся по своим этапам. На один объект может быть несколько действий. | F4: До 100 объектов. ID уникален. Прямые продажи и тендеры ведутся по своим этапам. На один объект может быть несколько действий. | G4: До 100 объектов. ID уникален. Прямые продажи и тендеры ведутся по своим этапам. На один объект может быть несколько действий. | H4: До 100 объектов. ID уникален. Прямые продажи и тендеры ведутся по своим этапам. На один объект может быть несколько действий. | I4: До 100 объектов. ID уникален. Прямые продажи и тендеры ведутся по своим этапам. На один объект может быть несколько действий. | J4: До 100 объектов. ID уникален. Прямые продажи и тендеры ведутся по своим этапам. На один объект может быть несколько действий. | K4: До 100 объектов. ID уникален. Прямые продажи и тендеры ведутся по своим этапам. На один объект может быть несколько действий. | L4: До 100 объектов. ID уникален. Прямые продажи и тендеры ведутся по своим этапам. На один объект может быть несколько действий. | M4: До 100 объектов. ID уникален. Прямые продажи и тендеры ведутся по своим этапам. На один объект может быть несколько действий. | N4: До 100 объектов. ID уникален. Прямые продажи и тендеры ведутся по своим этапам. На один объект может быть несколько действий. | O4: До 100 объектов. ID уникален. Прямые продажи и тендеры ведутся по своим этапам. На один объект может быть несколько действий. | P4: До 100 объектов. ID уникален. Прямые продажи и тендеры ведутся по своим этапам. На один объект может быть несколько действий. | Q4: До 100 объектов. ID уникален. Прямые продажи и тендеры ведутся по своим этапам. На один объект может быть несколько действий. | R4: До 100 объектов. ID уникален. Прямые продажи и тендеры ведутся по своим этапам. На один объект может быть несколько действий. | S4: До 100 объектов. ID уникален. Прямые продажи и тендеры ведутся по своим этапам. На один объект может быть несколько действий. | T4: До 100 объектов. ID уникален. Прямые продажи и тендеры ведутся по своим этапам. На один объект может быть несколько действий. | U4: До 100 объектов. ID уникален. Прямые продажи и тендеры ведутся по своим этапам. На один объект может быть несколько действий.
A6: ID | B6: Тип | C6: Клиент / объект | D6: Сотрудник | E6: Канал | F6: Этап | G6: Вход на этап | H6: Срок результата этапа | I6: Требования / ТЗ | J6: Предложение завода | K6: Расчёт логистики | L6: Дополнительные расходы | M6: Цена согласована | N6: Результат готов | O6: Подтверждение результата | P6: Передача принята | Q6: Документы приняты | R6: Связанный заказ 1С | S6: Долг, ₽ с НДС | T6: Срок оплаты | U6: Ссылка Битрикс | V6: Ожидаемый результат | W6: Что ещё нужно | X6: Выбран фильтром | Y6: Просрочен этап | Z6: Без открытого действия | AA6: Просроченный долг, ₽ | AB6: Группа этапов | AC6: Без срока этапа | AD6: Сумма предложения, ₽ без НДС
A7: Л-001 | B7: Лид | C7: Компания А | D7: Менеджер 1 | E7: Прямые | F7: Лиды | G7: 46318 | H7: 46321.75 | I7: Не требуется | J7: Не требуется | K7: Не требуется | L7: Не требуется | M7: Не требуется | N7: Нет | P7: Не требуется | Q7: Не требуется | V7: =IF(A7="","",IFERROR(VLOOKUP(F7,$A$111:$C$127,2,FALSE),"Не задан этап")) -> Контакт и подтверждённая потребность | W7: =IF(A7="","",IF(V7="Закрыто","",IF(OR(F7="Расчёт",F7="Решение об участии"),IF(COUNTIF(I7:M7,"Готово")+COUNTIF(I7:M7,"Не требуется")<5,IF(OR(I7="",I7="Нет"),"ТЗ; ","")&IF(OR(J7="",J7="Нет"),"КП завода; ","")&IF(OR(K7="",K7="Нет"),"логистика; ","")&IF(OR(L7="",L7="Нет"),"допрасходы; ","")&IF(OR(M7="",M7="Нет"),"цена продажи; ",""),IF(COUNTIF(I7:M7,"Не требуется")=5,"Проверить применимость расчёта",IF(AND(N7="Готово",O7<>""),"","Подтверждение калькуляции"))),IF(F7="Передача в исполнение",IF(AND(P7="Принято",O7<>""),"","Приём заказа смежниками"),IF(F7="Приёмка и оплата",IF(Q7<>"Принято","Подтверждение приёмки; ","")&IF(S7="","Остаток долга не загружен",IF(S7>0,"Оплата клиента","")),IF(AND(N7="Готово",O7<>""),"",V7)))))) -> Контакт и подтверждённая потребность | X7: =IF(AND(A7<>"",V7<>"Закрыто",OR(Продажи!$I$4="Все",D7=Продажи!$I$4),OR(Продажи!$O$4="Все",E7=Продажи!$O$4)),1,0) -> 1 | Y7: =IF(A7="","",IF(AND(ISNUMBER(H7),H7<Продажи!$D$4,W7<>"",V7<>"Закрыто"),1,0)) -> 0 | Z7: =IF(A7="","",IF(V7="Закрыто",0,IF(COUNTIFS(Действия!$B$7:$B$106,A7,Действия!$N$7:$N$106,1,Действия!$D$7:$D$106,"Продажи")=0,1,0))) -> 0 | AA7: =IF(A7="","",IF(OR(S7="",T7=""),"Нет данных",IF(AND(S7>0,T7<INT(Продажи!$D$4)),S7,0))) -> Нет данных | AB7: =IF(A7="","",IFERROR(VLOOKUP(F7,$A$111:$C$127,3,FALSE),"Не классифицировано")) -> Лиды | AC7: =IF(AND(A7<>"",V7<>"Закрыто",H7=""),1,0) -> 0
A8: Л-002 | B8: Лид | C8: Компания Б | D8: Менеджер 2 | E8: Прямые | F8: Лиды | G8: 46315 | H8: 46319.75 | I8: Не требуется | J8: Не требуется | K8: Не требуется | L8: Не требуется | M8: Не требуется | N8: Нет | P8: Не требуется | Q8: Не требуется | V8: =IF(A8="","",IFERROR(VLOOKUP(F8,$A$111:$C$127,2,FALSE),"Не задан этап")) -> Контакт и подтверждённая потребность | W8: =IF(A8="","",IF(V8="Закрыто","",IF(OR(F8="Расчёт",F8="Решение об участии"),IF(COUNTIF(I8:M8,"Готово")+COUNTIF(I8:M8,"Не требуется")<5,IF(OR(I8="",I8="Нет"),"ТЗ; ","")&IF(OR(J8="",J8="Нет"),"КП завода; ","")&IF(OR(K8="",K8="Нет"),"логистика; ","")&IF(OR(L8="",L8="Нет"),"допрасходы; ","")&IF(OR(M8="",M8="Нет"),"цена продажи; ",""),IF(COUNTIF(I8:M8,"Не требуется")=5,"Проверить применимость расчёта",IF(AND(N8="Готово",O8<>""),"","Подтверждение калькуляции"))),IF(F8="Передача в исполнение",IF(AND(P8="Принято",O8<>""),"","Приём заказа смежниками"),IF(F8="Приёмка и оплата",IF(Q8<>"Принято","Подтверждение приёмки; ","")&IF(S8="","Остаток долга не загружен",IF(S8>0,"Оплата клиента","")),IF(AND(N8="Готово",O8<>""),"",V8)))))) -> Контакт и подтверждённая потребность | X8: =IF(AND(A8<>"",V8<>"Закрыто",OR(Продажи!$I$4="Все",D8=Продажи!$I$4),OR(Продажи!$O$4="Все",E8=Продажи!$O$4)),1,0) -> 1 | Y8: =IF(A8="","",IF(AND(ISNUMBER(H8),H8<Продажи!$D$4,W8<>"",V8<>"Закрыто"),1,0)) -> 1 | Z8: =IF(A8="","",IF(V8="Закрыто",0,IF(COUNTIFS(Действия!$B$7:$B$106,A8,Действия!$N$7:$N$106,1,Действия!$D$7:$D$106,"Продажи")=0,1,0))) -> 0 | AA8: =IF(A8="","",IF(OR(S8="",T8=""),"Нет данных",IF(AND(S8>0,T8<INT(Продажи!$D$4)),S8,0))) -> Нет данных | AB8: =IF(A8="","",IFERROR(VLOOKUP(F8,$A$111:$C$127,3,FALSE),"Не классифицировано")) -> Лиды | AC8: =IF(AND(A8<>"",V8<>"Закрыто",H8=""),1,0) -> 0
A9: Л-003 | B9: Лид | C9: Компания В | D9: Менеджер 1 | E9: Прямые | F9: Лиды | G9: 46319 | H9: 46323.75 | I9: Не требуется | J9: Не требуется | K9: Не требуется | L9: Не требуется | M9: Не требуется | N9: Готово | O9: Демо: карточка потребности | P9: Не требуется | Q9: Не требуется | V9: =IF(A9="","",IFERROR(VLOOKUP(F9,$A$111:$C$127,2,FALSE),"Не задан этап")) -> Контакт и подтверждённая потребность | W9: =IF(A9="","",IF(V9="Закрыто","",IF(OR(F9="Расчёт",F9="Решение об участии"),IF(COUNTIF(I9:M9,"Готово")+COUNTIF(I9:M9,"Не требуется")<5,IF(OR(I9="",I9="Нет"),"ТЗ; ","")&IF(OR(J9="",J9="Нет"),"КП завода; ","")&IF(OR(K9="",K9="Нет"),"логистика; ","")&IF(OR(L9="",L9="Нет"),"допрасходы; ","")&IF(OR(M9="",M9="Нет"),"цена продажи; ",""),IF(COUNTIF(I9:M9,"Не требуется")=5,"Проверить применимость расчёта",IF(AND(N9="Готово",O9<>""),"","Подтверждение калькуляции"))),IF(F9="Передача в исполнение",IF(AND(P9="Принято",O9<>""),"","Приём заказа смежниками"),IF(F9="Приёмка и оплата",IF(Q9<>"Принято","Подтверждение приёмки; ","")&IF(S9="","Остаток долга не загружен",IF(S9>0,"Оплата клиента","")),IF(AND(N9="Готово",O9<>""),"",V9)))))) | X9: =IF(AND(A9<>"",V9<>"Закрыто",OR(Продажи!$I$4="Все",D9=Продажи!$I$4),OR(Продажи!$O$4="Все",E9=Продажи!$O$4)),1,0) -> 1 | Y9: =IF(A9="","",IF(AND(ISNUMBER(H9),H9<Продажи!$D$4,W9<>"",V9<>"Закрыто"),1,0)) -> 0 | Z9: =IF(A9="","",IF(V9="Закрыто",0,IF(COUNTIFS(Действия!$B$7:$B$106,A9,Действия!$N$7:$N$106,1,Действия!$D$7:$D$106,"Продажи")=0,1,0))) -> 0 | AA9: =IF(A9="","",IF(OR(S9="",T9=""),"Нет данных",IF(AND(S9>0,T9<INT(Продажи!$D$4)),S9,0))) -> Нет данных | AB9: =IF(A9="","",IFERROR(VLOOKUP(F9,$A$111:$C$127,3,FALSE),"Не классифицировано")) -> Лиды | AC9: =IF(AND(A9<>"",V9<>"Закрыто",H9=""),1,0) -> 0
A10: С-101 | B10: Сделка | C10: Компания Г | D10: Менеджер 1 | E10: Прямые | F10: Запрос | G10: 46317 | H10: 46320.75 | I10: Не требуется | J10: Не требуется | K10: Не требуется | L10: Не требуется | M10: Не требуется | N10: Нет | P10: Не требуется | Q10: Не требуется | V10: =IF(A10="","",IFERROR(VLOOKUP(F10,$A$111:$C$127,2,FALSE),"Не задан этап")) -> Ведомость требований клиента | W10: =IF(A10="","",IF(V10="Закрыто","",IF(OR(F10="Расчёт",F10="Решение об участии"),IF(COUNTIF(I10:M10,"Готово")+COUNTIF(I10:M10,"Не требуется")<5,IF(OR(I10="",I10="Нет"),"ТЗ; ","")&IF(OR(J10="",J10="Нет"),"КП завода; ","")&IF(OR(K10="",K10="Нет"),"логистика; ","")&IF(OR(L10="",L10="Нет"),"допрасходы; ","")&IF(OR(M10="",M10="Нет"),"цена продажи; ",""),IF(COUNTIF(I10:M10,"Не требуется")=5,"Проверить применимость расчёта",IF(AND(N10="Готово",O10<>""),"","Подтверждение калькуляции"))),IF(F10="Передача в исполнение",IF(AND(P10="Принято",O10<>""),"","Приём заказа смежниками"),IF(F10="Приёмка и оплата",IF(Q10<>"Принято","Подтверждение приёмки; ","")&IF(S10="","Остаток долга не загружен",IF(S10>0,"Оплата клиента","")),IF(AND(N10="Готово",O10<>""),"",V10)))))) -> Ведомость требований клиента | X10: =IF(AND(A10<>"",V10<>"Закрыто",OR(Продажи!$I$4="Все",D10=Продажи!$I$4),OR(Продажи!$O$4="Все",E10=Продажи!$O$4)),1,0) -> 1 | Y10: =IF(A10="","",IF(AND(ISNUMBER(H10),H10<Продажи!$D$4,W10<>"",V10<>"Закрыто"),1,0)) -> 1 | Z10: =IF(A10="","",IF(V10="Закрыто",0,IF(COUNTIFS(Действия!$B$7:$B$106,A10,Действия!$N$7:$N$106,1,Действия!$D$7:$D$106,"Продажи")=0,1,0))) -> 0 | AA10: =IF(A10="","",IF(OR(S10="",T10=""),"Нет данных",IF(AND(S10>0,T10<INT(Продажи!$D$4)),S10,0))) -> Нет данных | AB10: =IF(A10="","",IFERROR(VLOOKUP(F10,$A$111:$C$127,3,FALSE),"Не классифицировано")) -> Запрос / проверка | AC10: =IF(AND(A10<>"",V10<>"Закрыто",H10=""),1,0) -> 0 | AD10: 4800000
A11: С-102 | B11: Сделка | C11: Компания Д | D11: Менеджер 2 | E11: Прямые | F11: Расчёт | G11: 46315 | H11: 46319.75 | I11: Готово | J11: Нет | K11: Готово | L11: Готово | M11: Нет | N11: Нет | P11: Не требуется | Q11: Не требуется | V11: =IF(A11="","",IFERROR(VLOOKUP(F11,$A$111:$C$127,2,FALSE),"Не задан этап")) -> Согласованная калькуляция | W11: =IF(A11="","",IF(V11="Закрыто","",IF(OR(F11="Расчёт",F11="Решение об участии"),IF(COUNTIF(I11:M11,"Готово")+COUNTIF(I11:M11,"Не требуется")<5,IF(OR(I11="",I11="Нет"),"ТЗ; ","")&IF(OR(J11="",J11="Нет"),"КП завода; ","")&IF(OR(K11="",K11="Нет"),"логистика; ","")&IF(OR(L11="",L11="Нет"),"допрасходы; ","")&IF(OR(M11="",M11="Нет"),"цена продажи; ",""),IF(COUNTIF(I11:M11,"Не требуется")=5,"Проверить применимость расчёта",IF(AND(N11="Готово",O11<>""),"","Подтверждение калькуляции"))),IF(F11="Передача в исполнение",IF(AND(P11="Принято",O11<>""),"","Приём заказа смежниками"),IF(F11="Приёмка и оплата",IF(Q11<>"Принято","Подтверждение приёмки; ","")&IF(S11="","Остаток долга не загружен",IF(S11>0,"Оплата клиента","")),IF(AND(N11="Готово",O11<>""),"",V11)))))) -> КП завода; цена продажи; | X11: =IF(AND(A11<>"",V11<>"Закрыто",OR(Продажи!$I$4="Все",D11=Продажи!$I$4),OR(Продажи!$O$4="Все",E11=Продажи!$O$4)),1,0) -> 1 | Y11: =IF(A11="","",IF(AND(ISNUMBER(H11),H11<Продажи!$D$4,W11<>"",V11<>"Закрыто"),1,0)) -> 1 | Z11: =IF(A11="","",IF(V11="Закрыто",0,IF(COUNTIFS(Действия!$B$7:$B$106,A11,Действия!$N$7:$N$106,1,Действия!$D$7:$D$106,"Продажи")=0,1,0))) -> 1 | AA11: =IF(A11="","",IF(OR(S11="",T11=""),"Нет данных",IF(AND(S11>0,T11<INT(Продажи!$D$4)),S11,0))) -> Нет данных | AB11: =IF(A11="","",IFERROR(VLOOKUP(F11,$A$111:$C$127,3,FALSE),"Не классифицировано")) -> Расчёт / решение | AC11: =IF(AND(A11<>"",V11<>"Закрыто",H11=""),1,0) -> 0 | AD11: 12500000
A12: С-103 | B12: Сделка | C12: Компания Е | D12: Тендерный специалист | E12: Тендеры | F12: Решение об участии | G12: 46318 | H12: 46322.75 | I12: Готово | J12: Готово | K12: Нет | L12: Готово | M12: Нет | N12: Нет | P12: Не требуется | Q12: Не требуется | V12: =IF(A12="","",IFERROR(VLOOKUP(F12,$A$111:$C$127,2,FALSE),"Не задан этап")) -> Согласованная цена и решение участвовать | W12: =IF(A12="","",IF(V12="Закрыто","",IF(OR(F12="Расчёт",F12="Решение об участии"),IF(COUNTIF(I12:M12,"Готово")+COUNTIF(I12:M12,"Не требуется")<5,IF(OR(I12="",I12="Нет"),"ТЗ; ","")&IF(OR(J12="",J12="Нет"),"КП завода; ","")&IF(OR(K12="",K12="Нет"),"логистика; ","")&IF(OR(L12="",L12="Нет"),"допрасходы; ","")&IF(OR(M12="",M12="Нет"),"цена продажи; ",""),IF(COUNTIF(I12:M12,"Не требуется")=5,"Проверить применимость расчёта",IF(AND(N12="Готово",O12<>""),"","Подтверждение калькуляции"))),IF(F12="Передача в исполнение",IF(AND(P12="Принято",O12<>""),"","Приём заказа смежниками"),IF(F12="Приёмка и оплата",IF(Q12<>"Принято","Подтверждение приёмки; ","")&IF(S12="","Остаток долга не загружен",IF(S12>0,"Оплата клиента","")),IF(AND(N12="Готово",O12<>""),"",V12)))))) -> логистика; цена продажи; | X12: =IF(AND(A12<>"",V12<>"Закрыто",OR(Продажи!$I$4="Все",D12=Продажи!$I$4),OR(Продажи!$O$4="Все",E12=Продажи!$O$4)),1,0) -> 1 | Y12: =IF(A12="","",IF(AND(ISNUMBER(H12),H12<Продажи!$D$4,W12<>"",V12<>"Закрыто"),1,0)) -> 0 | Z12: =IF(A12="","",IF(V12="Закрыто",0,IF(COUNTIFS(Действия!$B$7:$B$106,A12,Действия!$N$7:$N$106,1,Действия!$D$7:$D$106,"Продажи")=0,1,0))) -> 0 | AA12: =IF(A12="","",IF(OR(S12="",T12=""),"Нет данных",IF(AND(S12>0,T12<INT(Продажи!$D$4)),S12,0))) -> Нет данных | AB12: =IF(A12="","",IFERROR(VLOOKUP(F12,$A$111:$C$127,3,FALSE),"Не классифицировано")) -> Расчёт / решение | AC12: =IF(AND(A12<>"",V12<>"Закрыто",H12=""),1,0) -> 0 | AD12: 28000000
A13: С-104 | B13: Сделка | C13: Компания Ж | D13: Менеджер 1 | E13: Прямые | F13: КП | G13: 46316 | H13: 46321.75 | I13: Не требуется | J13: Не требуется | K13: Не требуется | L13: Не требуется | M13: Не требуется | N13: Нет | P13: Не требуется | Q13: Не требуется | V13: =IF(A13="","",IFERROR(VLOOKUP(F13,$A$111:$C$127,2,FALSE),"Не задан этап")) -> Ответ клиента на предложение | W13: =IF(A13="","",IF(V13="Закрыто","",IF(OR(F13="Расчёт",F13="Решение об участии"),IF(COUNTIF(I13:M13,"Готово")+COUNTIF(I13:M13,"Не требуется")<5,IF(OR(I13="",I13="Нет"),"ТЗ; ","")&IF(OR(J13="",J13="Нет"),"КП завода; ","")&IF(OR(K13="",K13="Нет"),"логистика; ","")&IF(OR(L13="",L13="Нет"),"допрасходы; ","")&IF(OR(M13="",M13="Нет"),"цена продажи; ",""),IF(COUNTIF(I13:M13,"Не требуется")=5,"Проверить применимость расчёта",IF(AND(N13="Готово",O13<>""),"","Подтверждение калькуляции"))),IF(F13="Передача в исполнение",IF(AND(P13="Принято",O13<>""),"","Приём заказа смежниками"),IF(F13="Приёмка и оплата",IF(Q13<>"Принято","Подтверждение приёмки; ","")&IF(S13="","Остаток долга не загружен",IF(S13>0,"Оплата клиента","")),IF(AND(N13="Готово",O13<>""),"",V13)))))) -> Ответ клиента на предложение | X13: =IF(AND(A13<>"",V13<>"Закрыто",OR(Продажи!$I$4="Все",D13=Продажи!$I$4),OR(Продажи!$O$4="Все",E13=Продажи!$O$4)),1,0) -> 1 | Y13: =IF(A13="","",IF(AND(ISNUMBER(H13),H13<Продажи!$D$4,W13<>"",V13<>"Закрыто"),1,0)) -> 0 | Z13: =IF(A13="","",IF(V13="Закрыто",0,IF(COUNTIFS(Действия!$B$7:$B$106,A13,Действия!$N$7:$N$106,1,Действия!$D$7:$D$106,"Продажи")=0,1,0))) -> 0 | AA13: =IF(A13="","",IF(OR(S13="",T13=""),"Нет данных",IF(AND(S13>0,T13<INT(Продажи!$D$4)),S13,0))) -> Нет данных | AB13: =IF(A13="","",IFERROR(VLOOKUP(F13,$A$111:$C$127,3,FALSE),"Не классифицировано")) -> КП / подготовка | AC13: =IF(AND(A13<>"",V13<>"Закрыто",H13=""),1,0) -> 0 | AD13: 6750000
A14: С-105 | B14: Сделка | C14: Компания З | D14: Менеджер 2 | E14: Прямые | F14: КП | G14: 46314 | H14: 46318.75 | I14: Не требуется | J14: Не требуется | K14: Не требуется | L14: Не требуется | M14: Не требуется | N14: Нет | P14: Не требуется | Q14: Не требуется | V14: =IF(A14="","",IFERROR(VLOOKUP(F14,$A$111:$C$127,2,FALSE),"Не задан этап")) -> Ответ клиента на предложение | W14: =IF(A14="","",IF(V14="Закрыто","",IF(OR(F14="Расчёт",F14="Решение об участии"),IF(COUNTIF(I14:M14,"Готово")+COUNTIF(I14:M14,"Не требуется")<5,IF(OR(I14="",I14="Нет"),"ТЗ; ","")&IF(OR(J14="",J14="Нет"),"КП завода; ","")&IF(OR(K14="",K14="Нет"),"логистика; ","")&IF(OR(L14="",L14="Нет"),"допрасходы; ","")&IF(OR(M14="",M14="Нет"),"цена продажи; ",""),IF(COUNTIF(I14:M14,"Не требуется")=5,"Проверить применимость расчёта",IF(AND(N14="Готово",O14<>""),"","Подтверждение калькуляции"))),IF(F14="Передача в исполнение",IF(AND(P14="Принято",O14<>""),"","Приём заказа смежниками"),IF(F14="Приёмка и оплата",IF(Q14<>"Принято","Подтверждение приёмки; ","")&IF(S14="","Остаток долга не загружен",IF(S14>0,"Оплата клиента","")),IF(AND(N14="Готово",O14<>""),"",V14)))))) -> Ответ клиента на предложение | X14: =IF(AND(A14<>"",V14<>"Закрыто",OR(Продажи!$I$4="Все",D14=Продажи!$I$4),OR(Продажи!$O$4="Все",E14=Продажи!$O$4)),1,0) -> 1 | Y14: =IF(A14="","",IF(AND(ISNUMBER(H14),H14<Продажи!$D$4,W14<>"",V14<>"Закрыто"),1,0)) -> 1 | Z14: =IF(A14="","",IF(V14="Закрыто",0,IF(COUNTIFS(Действия!$B$7:$B$106,A14,Действия!$N$7:$N$106,1,Действия!$D$7:$D$106,"Продажи")=0,1,0))) -> 1 | AA14: =IF(A14="","",IF(OR(S14="",T14=""),"Нет данных",IF(AND(S14>0,T14<INT(Продажи!$D$4)),S14,0))) -> Нет данных | AB14: =IF(A14="","",IFERROR(VLOOKUP(F14,$A$111:$C$127,3,FALSE),"Не классифицировано")) -> КП / подготовка | AC14: =IF(AND(A14<>"",V14<>"Закрыто",H14=""),1,0) -> 0 | AD14: 3200000
A15: С-106 | B15: Сделка | C15: Компания И | D15: Менеджер 1 | E15: Прямые | F15: Переговоры | G15: 46317 | H15: 46322.75 | I15: Не требуется | J15: Не требуется | K15: Не требуется | L15: Не требуется | M15: Не требуется | N15: Готово | O15: Демо: протокол переговоров | P15: Не требуется | Q15: Не требуется | V15: =IF(A15="","",IFERROR(VLOOKUP(F15,$A$111:$C$127,2,FALSE),"Не задан этап")) -> Согласованные условия и открытые вопросы | W15: =IF(A15="","",IF(V15="Закрыто","",IF(OR(F15="Расчёт",F15="Решение об участии"),IF(COUNTIF(I15:M15,"Готово")+COUNTIF(I15:M15,"Не требуется")<5,IF(OR(I15="",I15="Нет"),"ТЗ; ","")&IF(OR(J15="",J15="Нет"),"КП завода; ","")&IF(OR(K15="",K15="Нет"),"логистика; ","")&IF(OR(L15="",L15="Нет"),"допрасходы; ","")&IF(OR(M15="",M15="Нет"),"цена продажи; ",""),IF(COUNTIF(I15:M15,"Не требуется")=5,"Проверить применимость расчёта",IF(AND(N15="Готово",O15<>""),"","Подтверждение калькуляции"))),IF(F15="Передача в исполнение",IF(AND(P15="Принято",O15<>""),"","Приём заказа смежниками"),IF(F15="Приёмка и оплата",IF(Q15<>"Принято","Подтверждение приёмки; ","")&IF(S15="","Остаток долга не загружен",IF(S15>0,"Оплата клиента","")),IF(AND(N15="Готово",O15<>""),"",V15)))))) | X15: =IF(AND(A15<>"",V15<>"Закрыто",OR(Продажи!$I$4="Все",D15=Продажи!$I$4),OR(Продажи!$O$4="Все",E15=Продажи!$O$4)),1,0) -> 1 | Y15: =IF(A15="","",IF(AND(ISNUMBER(H15),H15<Продажи!$D$4,W15<>"",V15<>"Закрыто"),1,0)) -> 0 | Z15: =IF(A15="","",IF(V15="Закрыто",0,IF(COUNTIFS(Действия!$B$7:$B$106,A15,Действия!$N$7:$N$106,1,Действия!$D$7:$D$106,"Продажи")=0,1,0))) -> 0 | AA15: =IF(A15="","",IF(OR(S15="",T15=""),"Нет данных",IF(AND(S15>0,T15<INT(Продажи!$D$4)),S15,0))) -> Нет данных | AB15: =IF(A15="","",IFERROR(VLOOKUP(F15,$A$111:$C$127,3,FALSE),"Не классифицировано")) -> Переговоры / подача | AC15: =IF(AND(A15<>"",V15<>"Закрыто",H15=""),1,0) -> 0 | AD15: 9400000
A16: С-107 | B16: Сделка | C16: Компания К | D16: Тендерный специалист | E16: Тендеры | F16: Дозапрос | G16: 46318 | H16: 46323.75 | I16: Не требуется | J16: Не требуется | K16: Не требуется | L16: Не требуется | M16: Не требуется | N16: Нет | P16: Не требуется | Q16: Не требуется | V16: =IF(A16="","",IFERROR(VLOOKUP(F16,$A$111:$C$127,2,FALSE),"Не задан этап")) -> Принятый площадкой ответ | W16: =IF(A16="","",IF(V16="Закрыто","",IF(OR(F16="Расчёт",F16="Решение об участии"),IF(COUNTIF(I16:M16,"Готово")+COUNTIF(I16:M16,"Не требуется")<5,IF(OR(I16="",I16="Нет"),"ТЗ; ","")&IF(OR(J16="",J16="Нет"),"КП завода; ","")&IF(OR(K16="",K16="Нет"),"логистика; ","")&IF(OR(L16="",L16="Нет"),"допрасходы; ","")&IF(OR(M16="",M16="Нет"),"цена продажи; ",""),IF(COUNTIF(I16:M16,"Не требуется")=5,"Проверить применимость расчёта",IF(AND(N16="Готово",O16<>""),"","Подтверждение калькуляции"))),IF(F16="Передача в исполнение",IF(AND(P16="Принято",O16<>""),"","Приём заказа смежниками"),IF(F16="Приёмка и оплата",IF(Q16<>"Принято","Подтверждение приёмки; ","")&IF(S16="","Остаток долга не загружен",IF(S16>0,"Оплата клиента","")),IF(AND(N16="Готово",O16<>""),"",V16)))))) -> Принятый площадкой ответ | X16: =IF(AND(A16<>"",V16<>"Закрыто",OR(Продажи!$I$4="Все",D16=Продажи!$I$4),OR(Продажи!$O$4="Все",E16=Продажи!$O$4)),1,0) -> 1 | Y16: =IF(A16="","",IF(AND(ISNUMBER(H16),H16<Продажи!$D$4,W16<>"",V16<>"Закрыто"),1,0)) -> 0 | Z16: =IF(A16="","",IF(V16="Закрыто",0,IF(COUNTIFS(Действия!$B$7:$B$106,A16,Действия!$N$7:$N$106,1,Действия!$D$7:$D$106,"Продажи")=0,1,0))) -> 0 | AA16: =IF(A16="","",IF(OR(S16="",T16=""),"Нет данных",IF(AND(S16>0,T16<INT(Продажи!$D$4)),S16,0))) -> Нет данных | AB16: =IF(A16="","",IFERROR(VLOOKUP(F16,$A$111:$C$127,3,FALSE),"Не классифицировано")) -> Переговоры / подача | AC16: =IF(AND(A16<>"",V16<>"Закрыто",H16=""),1,0) -> 0 | AD16: 41000000
A17: С-108 | B17: Сделка | C17: Компания Л | D17: Менеджер 2 | E17: Прямые | F17: Договор | G17: 46316 | H17: 46320.75 | I17: Не требуется | J17: Не требуется | K17: Не требуется | L17: Не требуется | M17: Не требуется | N17: Нет | P17: Не требуется | Q17: Не требуется | V17: =IF(A17="","",IFERROR(VLOOKUP(F17,$A$111:$C$127,2,FALSE),"Не задан этап")) -> Подписанные договор и спецификация | W17: =IF(A17="","",IF(V17="Закрыто","",IF(OR(F17="Расчёт",F17="Решение об участии"),IF(COUNTIF(I17:M17,"Готово")+COUNTIF(I17:M17,"Не требуется")<5,IF(OR(I17="",I17="Нет"),"ТЗ; ","")&IF(OR(J17="",J17="Нет"),"КП завода; ","")&IF(OR(K17="",K17="Нет"),"логистика; ","")&IF(OR(L17="",L17="Нет"),"допрасходы; ","")&IF(OR(M17="",M17="Нет"),"цена продажи; ",""),IF(COUNTIF(I17:M17,"Не требуется")=5,"Проверить применимость расчёта",IF(AND(N17="Готово",O17<>""),"","Подтверждение калькуляции"))),IF(F17="Передача в исполнение",IF(AND(P17="Принято",O17<>""),"","Приём заказа смежниками"),IF(F17="Приёмка и оплата",IF(Q17<>"Принято","Подтверждение приёмки; ","")&IF(S17="","Остаток долга не загружен",IF(S17>0,"Оплата клиента","")),IF(AND(N17="Готово",O17<>""),"",V17)))))) -> Подписанные договор и спецификация | X17: =IF(AND(A17<>"",V17<>"Закрыто",OR(Продажи!$I$4="Все",D17=Продажи!$I$4),OR(Продажи!$O$4="Все",E17=Продажи!$O$4)),1,0) -> 1 | Y17: =IF(A17="","",IF(AND(ISNUMBER(H17),H17<Продажи!$D$4,W17<>"",V17<>"Закрыто"),1,0)) -> 1 | Z17: =IF(A17="","",IF(V17="Закрыто",0,IF(COUNTIFS(Действия!$B$7:$B$106,A17,Действия!$N$7:$N$106,1,Действия!$D$7:$D$106,"Продажи")=0,1,0))) -> 1 | AA17: =IF(A17="","",IF(OR(S17="",T17=""),"Нет данных",IF(AND(S17>0,T17<INT(Продажи!$D$4)),S17,0))) -> Нет данных | AB17: =IF(A17="","",IFERROR(VLOOKUP(F17,$A$111:$C$127,3,FALSE),"Не классифицировано")) -> Договор / результат | AC17: =IF(AND(A17<>"",V17<>"Закрыто",H17=""),1,0) -> 0 | AD17: 8700000
A18: С-109 | B18: Сделка | C18: Компания М | D18: Тендерный специалист | E18: Тендеры | F18: Подготовка заявки | G18: 46319 | H18: 46323.75 | I18: Не требуется | J18: Не требуется | K18: Не требуется | L18: Не требуется | M18: Не требуется | N18: Готово | O18: Демо: комплект согласован | P18: Не требуется | Q18: Не требуется | V18: =IF(A18="","",IFERROR(VLOOKUP(F18,$A$111:$C$127,2,FALSE),"Не задан этап")) -> Полный комплект тендерной заявки | W18: =IF(A18="","",IF(V18="Закрыто","",IF(OR(F18="Расчёт",F18="Решение об участии"),IF(COUNTIF(I18:M18,"Готово")+COUNTIF(I18:M18,"Не требуется")<5,IF(OR(I18="",I18="Нет"),"ТЗ; ","")&IF(OR(J18="",J18="Нет"),"КП завода; ","")&IF(OR(K18="",K18="Нет"),"логистика; ","")&IF(OR(L18="",L18="Нет"),"допрасходы; ","")&IF(OR(M18="",M18="Нет"),"цена продажи; ",""),IF(COUNTIF(I18:M18,"Не требуется")=5,"Проверить применимость расчёта",IF(AND(N18="Готово",O18<>""),"","Подтверждение калькуляции"))),IF(F18="Передача в исполнение",IF(AND(P18="Принято",O18<>""),"","Приём заказа смежниками"),IF(F18="Приёмка и оплата",IF(Q18<>"Принято","Подтверждение приёмки; ","")&IF(S18="","Остаток долга не загружен",IF(S18>0,"Оплата клиента","")),IF(AND(N18="Готово",O18<>""),"",V18)))))) | X18: =IF(AND(A18<>"",V18<>"Закрыто",OR(Продажи!$I$4="Все",D18=Продажи!$I$4),OR(Продажи!$O$4="Все",E18=Продажи!$O$4)),1,0) -> 1 | Y18: =IF(A18="","",IF(AND(ISNUMBER(H18),H18<Продажи!$D$4,W18<>"",V18<>"Закрыто"),1,0)) -> 0 | Z18: =IF(A18="","",IF(V18="Закрыто",0,IF(COUNTIFS(Действия!$B$7:$B$106,A18,Действия!$N$7:$N$106,1,Действия!$D$7:$D$106,"Продажи")=0,1,0))) -> 0 | AA18: =IF(A18="","",IF(OR(S18="",T18=""),"Нет данных",IF(AND(S18>0,T18<INT(Продажи!$D$4)),S18,0))) -> Нет данных | AB18: =IF(A18="","",IFERROR(VLOOKUP(F18,$A$111:$C$127,3,FALSE),"Не классифицировано")) -> КП / подготовка | AC18: =IF(AND(A18<>"",V18<>"Закрыто",H18=""),1,0) -> 0 | AD18: 15500000
A19: И-201 | B19: Исполнение | C19: Компания Н / опоры | D19: Менеджер 1 | E19: Прямые | F19: Передача в исполнение | G19: 46319 | H19: 46321.5 | I19: Не требуется | J19: Не требуется | K19: Не требуется | L19: Не требуется | M19: Не требуется | N19: Нет | P19: Не принято | Q19: Не требуется | R19: Демо: ЗК-201 | V19: =IF(A19="","",IFERROR(VLOOKUP(F19,$A$111:$C$127,2,FALSE),"Не задан этап")) -> Заказ принят снабжением и логистикой | W19: =IF(A19="","",IF(V19="Закрыто","",IF(OR(F19="Расчёт",F19="Решение об участии"),IF(COUNTIF(I19:M19,"Готово")+COUNTIF(I19:M19,"Не требуется")<5,IF(OR(I19="",I19="Нет"),"ТЗ; ","")&IF(OR(J19="",J19="Нет"),"КП завода; ","")&IF(OR(K19="",K19="Нет"),"логистика; ","")&IF(OR(L19="",L19="Нет"),"допрасходы; ","")&IF(OR(M19="",M19="Нет"),"цена продажи; ",""),IF(COUNTIF(I19:M19,"Не требуется")=5,"Проверить применимость расчёта",IF(AND(N19="Готово",O19<>""),"","Подтверждение калькуляции"))),IF(F19="Передача в исполнение",IF(AND(P19="Принято",O19<>""),"","Приём заказа смежниками"),IF(F19="Приёмка и оплата",IF(Q19<>"Принято","Подтверждение приёмки; ","")&IF(S19="","Остаток долга не загружен",IF(S19>0,"Оплата клиента","")),IF(AND(N19="Готово",O19<>""),"",V19)))))) -> Приём заказа смежниками | X19: =IF(AND(A19<>"",V19<>"Закрыто",OR(Продажи!$I$4="Все",D19=Продажи!$I$4),OR(Продажи!$O$4="Все",E19=Продажи!$O$4)),1,0) -> 1 | Y19: =IF(A19="","",IF(AND(ISNUMBER(H19),H19<Продажи!$D$4,W19<>"",V19<>"Закрыто"),1,0)) -> 0 | Z19: =IF(A19="","",IF(V19="Закрыто",0,IF(COUNTIFS(Действия!$B$7:$B$106,A19,Действия!$N$7:$N$106,1,Действия!$D$7:$D$106,"Продажи")=0,1,0))) -> 1 | AA19: =IF(A19="","",IF(OR(S19="",T19=""),"Нет данных",IF(AND(S19>0,T19<INT(Продажи!$D$4)),S19,0))) -> Нет данных | AB19: =IF(A19="","",IFERROR(VLOOKUP(F19,$A$111:$C$127,3,FALSE),"Не классифицировано")) -> Передача / исполнение | AC19: =IF(AND(A19<>"",V19<>"Закрыто",H19=""),1,0) -> 0
A20: И-202 | B20: Исполнение | C20: Компания О / металлоконструкции | D20: Менеджер 2 | E20: Прямые | F20: Исполнение | G20: 46314 | H20: 46321.625 | I20: Не требуется | J20: Не требуется | K20: Не требуется | L20: Не требуется | M20: Не требуется | N20: Нет | P20: Принято | Q20: Не требуется | R20: Демо: ЗК-202 | V20: =IF(A20="","",IFERROR(VLOOKUP(F20,$A$111:$C$127,2,FALSE),"Не задан этап")) -> Согласованы изменения и сроки клиента | W20: =IF(A20="","",IF(V20="Закрыто","",IF(OR(F20="Расчёт",F20="Решение об участии"),IF(COUNTIF(I20:M20,"Готово")+COUNTIF(I20:M20,"Не требуется")<5,IF(OR(I20="",I20="Нет"),"ТЗ; ","")&IF(OR(J20="",J20="Нет"),"КП завода; ","")&IF(OR(K20="",K20="Нет"),"логистика; ","")&IF(OR(L20="",L20="Нет"),"допрасходы; ","")&IF(OR(M20="",M20="Нет"),"цена продажи; ",""),IF(COUNTIF(I20:M20,"Не требуется")=5,"Проверить применимость расчёта",IF(AND(N20="Готово",O20<>""),"","Подтверждение калькуляции"))),IF(F20="Передача в исполнение",IF(AND(P20="Принято",O20<>""),"","Приём заказа смежниками"),IF(F20="Приёмка и оплата",IF(Q20<>"Принято","Подтверждение приёмки; ","")&IF(S20="","Остаток долга не загружен",IF(S20>0,"Оплата клиента","")),IF(AND(N20="Готово",O20<>""),"",V20)))))) -> Согласованы изменения и сроки клиента | X20: =IF(AND(A20<>"",V20<>"Закрыто",OR(Продажи!$I$4="Все",D20=Продажи!$I$4),OR(Продажи!$O$4="Все",E20=Продажи!$O$4)),1,0) -> 1 | Y20: =IF(A20="","",IF(AND(ISNUMBER(H20),H20<Продажи!$D$4,W20<>"",V20<>"Закрыто"),1,0)) -> 0 | Z20: =IF(A20="","",IF(V20="Закрыто",0,IF(COUNTIFS(Действия!$B$7:$B$106,A20,Действия!$N$7:$N$106,1,Действия!$D$7:$D$106,"Продажи")=0,1,0))) -> 0 | AA20: =IF(A20="","",IF(OR(S20="",T20=""),"Нет данных",IF(AND(S20>0,T20<INT(Продажи!$D$4)),S20,0))) -> Нет данных | AB20: =IF(A20="","",IFERROR(VLOOKUP(F20,$A$111:$C$127,3,FALSE),"Не классифицировано")) -> Передача / исполнение | AC20: =IF(AND(A20<>"",V20<>"Закрыто",H20=""),1,0) -> 0
A21: И-203 | B21: Исполнение | C21: Компания П / покрытие | D21: Тендерный специалист | E21: Тендеры | F21: Приёмка и оплата | G21: 46317 | H21: 46322.708 | I21: Не требуется | J21: Не требуется | K21: Не требуется | L21: Не требуется | M21: Не требуется | N21: Нет | P21: Принято | Q21: Не принято | R21: Демо: ЗК-203 | S21: 1850420.8 | T21: 46318 | V21: =IF(A21="","",IFERROR(VLOOKUP(F21,$A$111:$C$127,2,FALSE),"Не задан этап")) -> Приёмка подтверждена и оплата поступила | W21: =IF(A21="","",IF(V21="Закрыто","",IF(OR(F21="Расчёт",F21="Решение об участии"),IF(COUNTIF(I21:M21,"Готово")+COUNTIF(I21:M21,"Не требуется")<5,IF(OR(I21="",I21="Нет"),"ТЗ; ","")&IF(OR(J21="",J21="Нет"),"КП завода; ","")&IF(OR(K21="",K21="Нет"),"логистика; ","")&IF(OR(L21="",L21="Нет"),"допрасходы; ","")&IF(OR(M21="",M21="Нет"),"цена продажи; ",""),IF(COUNTIF(I21:M21,"Не требуется")=5,"Проверить применимость расчёта",IF(AND(N21="Готово",O21<>""),"","Подтверждение калькуляции"))),IF(F21="Передача в исполнение",IF(AND(P21="Принято",O21<>""),"","Приём заказа смежниками"),IF(F21="Приёмка и оплата",IF(Q21<>"Принято","Подтверждение приёмки; ","")&IF(S21="","Остаток долга не загружен",IF(S21>0,"Оплата клиента","")),IF(AND(N21="Готово",O21<>""),"",V21)))))) -> Подтверждение приёмки; Оплата клиента | X21: =IF(AND(A21<>"",V21<>"Закрыто",OR(Продажи!$I$4="Все",D21=Продажи!$I$4),OR(Продажи!$O$4="Все",E21=Продажи!$O$4)),1,0) -> 1 | Y21: =IF(A21="","",IF(AND(ISNUMBER(H21),H21<Продажи!$D$4,W21<>"",V21<>"Закрыто"),1,0)) -> 0 | Z21: =IF(A21="","",IF(V21="Закрыто",0,IF(COUNTIFS(Действия!$B$7:$B$106,A21,Действия!$N$7:$N$106,1,Действия!$D$7:$D$106,"Продажи")=0,1,0))) -> 0 | AA21: =IF(A21="","",IF(OR(S21="",T21=""),"Нет данных",IF(AND(S21>0,T21<INT(Продажи!$D$4)),S21,0))) -> 1850420.8 | AB21: =IF(A21="","",IFERROR(VLOOKUP(F21,$A$111:$C$127,3,FALSE),"Не классифицировано")) -> Приёмка / оплата | AC21: =IF(AND(A21<>"",V21<>"Закрыто",H21=""),1,0) -> 0
V22: =IF(A22="","",IFERROR(VLOOKUP(F22,$A$111:$C$127,2,FALSE),"Не задан этап")) | W22: =IF(A22="","",IF(V22="Закрыто","",IF(OR(F22="Расчёт",F22="Решение об участии"),IF(COUNTIF(I22:M22,"Готово")+COUNTIF(I22:M22,"Не требуется")<5,IF(OR(I22="",I22="Нет"),"ТЗ; ","")&IF(OR(J22="",J22="Нет"),"КП завода; ","")&IF(OR(K22="",K22="Нет"),"логистика; ","")&IF(OR(L22="",L22="Нет"),"допрасходы; ","")&IF(OR(M22="",M22="Нет"),"цена продажи; ",""),IF(COUNTIF(I22:M22,"Не требуется")=5,"Проверить применимость расчёта",IF(AND(N22="Готово",O22<>""),"","Подтверждение калькуляции"))),IF(F22="Передача в исполнение",IF(AND(P22="Принято",O22<>""),"","Приём заказа смежниками"),IF(F22="Приёмка и оплата",IF(Q22<>"Принято","Подтверждение приёмки; ","")&IF(S22="","Остаток долга не загружен",IF(S22>0,"Оплата клиента","")),IF(AND(N22="Готово",O22<>""),"",V22)))))) | X22: =IF(AND(A22<>"",V22<>"Закрыто",OR(Продажи!$I$4="Все",D22=Продажи!$I$4),OR(Продажи!$O$4="Все",E22=Продажи!$O$4)),1,0) -> 0 | Y22: =IF(A22="","",IF(AND(ISNUMBER(H22),H22<Продажи!$D$4,W22<>"",V22<>"Закрыто"),1,0)) | Z22: =IF(A22="","",IF(V22="Закрыто",0,IF(COUNTIFS(Действия!$B$7:$B$106,A22,Действия!$N$7:$N$106,1,Действия!$D$7:$D$106,"Продажи")=0,1,0))) | AA22: =IF(A22="","",IF(OR(S22="",T22=""),"Нет данных",IF(AND(S22>0,T22<INT(Продажи!$D$4)),S22,0))) | AB22: =IF(A22="","",IFERROR(VLOOKUP(F22,$A$111:$C$127,3,FALSE),"Не классифицировано")) | AC22: =IF(AND(A22<>"",V22<>"Закрыто",H22=""),1,0) -> 0
V23: =IF(A23="","",IFERROR(VLOOKUP(F23,$A$111:$C$127,2,FALSE),"Не задан этап")) | W23: =IF(A23="","",IF(V23="Закрыто","",IF(OR(F23="Расчёт",F23="Решение об участии"),IF(COUNTIF(I23:M23,"Готово")+COUNTIF(I23:M23,"Не требуется")<5,IF(OR(I23="",I23="Нет"),"ТЗ; ","")&IF(OR(J23="",J23="Нет"),"КП завода; ","")&IF(OR(K23="",K23="Нет"),"логистика; ","")&IF(OR(L23="",L23="Нет"),"допрасходы; ","")&IF(OR(M23="",M23="Нет"),"цена продажи; ",""),IF(COUNTIF(I23:M23,"Не требуется")=5,"Проверить применимость расчёта",IF(AND(N23="Готово",O23<>""),"","Подтверждение калькуляции"))),IF(F23="Передача в исполнение",IF(AND(P23="Принято",O23<>""),"","Приём заказа смежниками"),IF(F23="Приёмка и оплата",IF(Q23<>"Принято","Подтверждение приёмки; ","")&IF(S23="","Остаток долга не загружен",IF(S23>0,"Оплата клиента","")),IF(AND(N23="Готово",O23<>""),"",V23)))))) | X23: =IF(AND(A23<>"",V23<>"Закрыто",OR(Продажи!$I$4="Все",D23=Продажи!$I$4),OR(Продажи!$O$4="Все",E23=Продажи!$O$4)),1,0) -> 0 | Y23: =IF(A23="","",IF(AND(ISNUMBER(H23),H23<Продажи!$D$4,W23<>"",V23<>"Закрыто"),1,0)) | Z23: =IF(A23="","",IF(V23="Закрыто",0,IF(COUNTIFS(Действия!$B$7:$B$106,A23,Действия!$N$7:$N$106,1,Действия!$D$7:$D$106,"Продажи")=0,1,0))) | AA23: =IF(A23="","",IF(OR(S23="",T23=""),"Нет данных",IF(AND(S23>0,T23<INT(Продажи!$D$4)),S23,0))) | AB23: =IF(A23="","",IFERROR(VLOOKUP(F23,$A$111:$C$127,3,FALSE),"Не классифицировано")) | AC23: =IF(AND(A23<>"",V23<>"Закрыто",H23=""),1,0) -> 0
V24: =IF(A24="","",IFERROR(VLOOKUP(F24,$A$111:$C$127,2,FALSE),"Не задан этап")) | W24: =IF(A24="","",IF(V24="Закрыто","",IF(OR(F24="Расчёт",F24="Решение об участии"),IF(COUNTIF(I24:M24,"Готово")+COUNTIF(I24:M24,"Не требуется")<5,IF(OR(I24="",I24="Нет"),"ТЗ; ","")&IF(OR(J24="",J24="Нет"),"КП завода; ","")&IF(OR(K24="",K24="Нет"),"логистика; ","")&IF(OR(L24="",L24="Нет"),"допрасходы; ","")&IF(OR(M24="",M24="Нет"),"цена продажи; ",""),IF(COUNTIF(I24:M24,"Не требуется")=5,"Проверить применимость расчёта",IF(AND(N24="Готово",O24<>""),"","Подтверждение калькуляции"))),IF(F24="Передача в исполнение",IF(AND(P24="Принято",O24<>""),"","Приём заказа смежниками"),IF(F24="Приёмка и оплата",IF(Q24<>"Принято","Подтверждение приёмки; ","")&IF(S24="","Остаток долга не загружен",IF(S24>0,"Оплата клиента","")),IF(AND(N24="Готово",O24<>""),"",V24)))))) | X24: =IF(AND(A24<>"",V24<>"Закрыто",OR(Продажи!$I$4="Все",D24=Продажи!$I$4),OR(Продажи!$O$4="Все",E24=Продажи!$O$4)),1,0) -> 0 | Y24: =IF(A24="","",IF(AND(ISNUMBER(H24),H24<Продажи!$D$4,W24<>"",V24<>"Закрыто"),1,0)) | Z24: =IF(A24="","",IF(V24="Закрыто",0,IF(COUNTIFS(Действия!$B$7:$B$106,A24,Действия!$N$7:$N$106,1,Действия!$D$7:$D$106,"Продажи")=0,1,0))) | AA24: =IF(A24="","",IF(OR(S24="",T24=""),"Нет данных",IF(AND(S24>0,T24<INT(Продажи!$D$4)),S24,0))) | AB24: =IF(A24="","",IFERROR(VLOOKUP(F24,$A$111:$C$127,3,FALSE),"Не классифицировано")) | AC24: =IF(AND(A24<>"",V24<>"Закрыто",H24=""),1,0) -> 0
V25: =IF(A25="","",IFERROR(VLOOKUP(F25,$A$111:$C$127,2,FALSE),"Не задан этап")) | W25: =IF(A25="","",IF(V25="Закрыто","",IF(OR(F25="Расчёт",F25="Решение об участии"),IF(COUNTIF(I25:M25,"Готово")+COUNTIF(I25:M25,"Не требуется")<5,IF(OR(I25="",I25="Нет"),"ТЗ; ","")&IF(OR(J25="",J25="Нет"),"КП завода; ","")&IF(OR(K25="",K25="Нет"),"логистика; ","")&IF(OR(L25="",L25="Нет"),"допрасходы; ","")&IF(OR(M25="",M25="Нет"),"цена продажи; ",""),IF(COUNTIF(I25:M25,"Не требуется")=5,"Проверить применимость расчёта",IF(AND(N25="Готово",O25<>""),"","Подтверждение калькуляции"))),IF(F25="Передача в исполнение",IF(AND(P25="Принято",O25<>""),"","Приём заказа смежниками"),IF(F25="Приёмка и оплата",IF(Q25<>"Принято","Подтверждение приёмки; ","")&IF(S25="","Остаток долга не загружен",IF(S25>0,"Оплата клиента","")),IF(AND(N25="Готово",O25<>""),"",V25)))))) | X25: =IF(AND(A25<>"",V25<>"Закрыто",OR(Продажи!$I$4="Все",D25=Продажи!$I$4),OR(Продажи!$O$4="Все",E25=Продажи!$O$4)),1,0) -> 0 | Y25: =IF(A25="","",IF(AND(ISNUMBER(H25),H25<Продажи!$D$4,W25<>"",V25<>"Закрыто"),1,0)) | Z25: =IF(A25="","",IF(V25="Закрыто",0,IF(COUNTIFS(Действия!$B$7:$B$106,A25,Действия!$N$7:$N$106,1,Действия!$D$7:$D$106,"Продажи")=0,1,0))) | AA25: =IF(A25="","",IF(OR(S25="",T25=""),"Нет данных",IF(AND(S25>0,T25<INT(Продажи!$D$4)),S25,0))) | AB25: =IF(A25="","",IFERROR(VLOOKUP(F25,$A$111:$C$127,3,FALSE),"Не классифицировано")) | AC25: =IF(AND(A25<>"",V25<>"Закрыто",H25=""),1,0) -> 0
V26: =IF(A26="","",IFERROR(VLOOKUP(F26,$A$111:$C$127,2,FALSE),"Не задан этап")) | W26: =IF(A26="","",IF(V26="Закрыто","",IF(OR(F26="Расчёт",F26="Решение об участии"),IF(COUNTIF(I26:M26,"Готово")+COUNTIF(I26:M26,"Не требуется")<5,IF(OR(I26="",I26="Нет"),"ТЗ; ","")&IF(OR(J26="",J26="Нет"),"КП завода; ","")&IF(OR(K26="",K26="Нет"),"логистика; ","")&IF(OR(L26="",L26="Нет"),"допрасходы; ","")&IF(OR(M26="",M26="Нет"),"цена продажи; ",""),IF(COUNTIF(I26:M26,"Не требуется")=5,"Проверить применимость расчёта",IF(AND(N26="Готово",O26<>""),"","Подтверждение калькуляции"))),IF(F26="Передача в исполнение",IF(AND(P26="Принято",O26<>""),"","Приём заказа смежниками"),IF(F26="Приёмка и оплата",IF(Q26<>"Принято","Подтверждение приёмки; ","")&IF(S26="","Остаток долга не загружен",IF(S26>0,"Оплата клиента","")),IF(AND(N26="Готово",O26<>""),"",V26)))))) | X26: =IF(AND(A26<>"",V26<>"Закрыто",OR(Продажи!$I$4="Все",D26=Продажи!$I$4),OR(Продажи!$O$4="Все",E26=Продажи!$O$4)),1,0) -> 0 | Y26: =IF(A26="","",IF(AND(ISNUMBER(H26),H26<Продажи!$D$4,W26<>"",V26<>"Закрыто"),1,0)) | Z26: =IF(A26="","",IF(V26="Закрыто",0,IF(COUNTIFS(Действия!$B$7:$B$106,A26,Действия!$N$7:$N$106,1,Действия!$D$7:$D$106,"Продажи")=0,1,0))) | AA26: =IF(A26="","",IF(OR(S26="",T26=""),"Нет данных",IF(AND(S26>0,T26<INT(Продажи!$D$4)),S26,0))) | AB26: =IF(A26="","",IFERROR(VLOOKUP(F26,$A$111:$C$127,3,FALSE),"Не классифицировано")) | AC26: =IF(AND(A26<>"",V26<>"Закрыто",H26=""),1,0) -> 0
V27: =IF(A27="","",IFERROR(VLOOKUP(F27,$A$111:$C$127,2,FALSE),"Не задан этап")) | W27: =IF(A27="","",IF(V27="Закрыто","",IF(OR(F27="Расчёт",F27="Решение об участии"),IF(COUNTIF(I27:M27,"Готово")+COUNTIF(I27:M27,"Не требуется")<5,IF(OR(I27="",I27="Нет"),"ТЗ; ","")&IF(OR(J27="",J27="Нет"),"КП завода; ","")&IF(OR(K27="",K27="Нет"),"логистика; ","")&IF(OR(L27="",L27="Нет"),"допрасходы; ","")&IF(OR(M27="",M27="Нет"),"цена продажи; ",""),IF(COUNTIF(I27:M27,"Не требуется")=5,"Проверить применимость расчёта",IF(AND(N27="Готово",O27<>""),"","Подтверждение калькуляции"))),IF(F27="Передача в исполнение",IF(AND(P27="Принято",O27<>""),"","Приём заказа смежниками"),IF(F27="Приёмка и оплата",IF(Q27<>"Принято","Подтверждение приёмки; ","")&IF(S27="","Остаток долга не загружен",IF(S27>0,"Оплата клиента","")),IF(AND(N27="Готово",O27<>""),"",V27)))))) | X27: =IF(AND(A27<>"",V27<>"Закрыто",OR(Продажи!$I$4="Все",D27=Продажи!$I$4),OR(Продажи!$O$4="Все",E27=Продажи!$O$4)),1,0) -> 0 | Y27: =IF(A27="","",IF(AND(ISNUMBER(H27),H27<Продажи!$D$4,W27<>"",V27<>"Закрыто"),1,0)) | Z27: =IF(A27="","",IF(V27="Закрыто",0,IF(COUNTIFS(Действия!$B$7:$B$106,A27,Действия!$N$7:$N$106,1,Действия!$D$7:$D$106,"Продажи")=0,1,0))) | AA27: =IF(A27="","",IF(OR(S27="",T27=""),"Нет данных",IF(AND(S27>0,T27<INT(Продажи!$D$4)),S27,0))) | AB27: =IF(A27="","",IFERROR(VLOOKUP(F27,$A$111:$C$127,3,FALSE),"Не классифицировано")) | AC27: =IF(AND(A27<>"",V27<>"Закрыто",H27=""),1,0) -> 0
V28: =IF(A28="","",IFERROR(VLOOKUP(F28,$A$111:$C$127,2,FALSE),"Не задан этап")) | W28: =IF(A28="","",IF(V28="Закрыто","",IF(OR(F28="Расчёт",F28="Решение об участии"),IF(COUNTIF(I28:M28,"Готово")+COUNTIF(I28:M28,"Не требуется")<5,IF(OR(I28="",I28="Нет"),"ТЗ; ","")&IF(OR(J28="",J28="Нет"),"КП завода; ","")&IF(OR(K28="",K28="Нет"),"логистика; ","")&IF(OR(L28="",L28="Нет"),"допрасходы; ","")&IF(OR(M28="",M28="Нет"),"цена продажи; ",""),IF(COUNTIF(I28:M28,"Не требуется")=5,"Проверить применимость расчёта",IF(AND(N28="Готово",O28<>""),"","Подтверждение калькуляции"))),IF(F28="Передача в исполнение",IF(AND(P28="Принято",O28<>""),"","Приём заказа смежниками"),IF(F28="Приёмка и оплата",IF(Q28<>"Принято","Подтверждение приёмки; ","")&IF(S28="","Остаток долга не загружен",IF(S28>0,"Оплата клиента","")),IF(AND(N28="Готово",O28<>""),"",V28)))))) | X28: =IF(AND(A28<>"",V28<>"Закрыто",OR(Продажи!$I$4="Все",D28=Продажи!$I$4),OR(Продажи!$O$4="Все",E28=Продажи!$O$4)),1,0) -> 0 | Y28: =IF(A28="","",IF(AND(ISNUMBER(H28),H28<Продажи!$D$4,W28<>"",V28<>"Закрыто"),1,0)) | Z28: =IF(A28="","",IF(V28="Закрыто",0,IF(COUNTIFS(Действия!$B$7:$B$106,A28,Действия!$N$7:$N$106,1,Действия!$D$7:$D$106,"Продажи")=0,1,0))) | AA28: =IF(A28="","",IF(OR(S28="",T28=""),"Нет данных",IF(AND(S28>0,T28<INT(Продажи!$D$4)),S28,0))) | AB28: =IF(A28="","",IFERROR(VLOOKUP(F28,$A$111:$C$127,3,FALSE),"Не классифицировано")) | AC28: =IF(AND(A28<>"",V28<>"Закрыто",H28=""),1,0) -> 0
V29: =IF(A29="","",IFERROR(VLOOKUP(F29,$A$111:$C$127,2,FALSE),"Не задан этап")) | W29: =IF(A29="","",IF(V29="Закрыто","",IF(OR(F29="Расчёт",F29="Решение об участии"),IF(COUNTIF(I29:M29,"Готово")+COUNTIF(I29:M29,"Не требуется")<5,IF(OR(I29="",I29="Нет"),"ТЗ; ","")&IF(OR(J29="",J29="Нет"),"КП завода; ","")&IF(OR(K29="",K29="Нет"),"логистика; ","")&IF(OR(L29="",L29="Нет"),"допрасходы; ","")&IF(OR(M29="",M29="Нет"),"цена продажи; ",""),IF(COUNTIF(I29:M29,"Не требуется")=5,"Проверить применимость расчёта",IF(AND(N29="Готово",O29<>""),"","Подтверждение калькуляции"))),IF(F29="Передача в исполнение",IF(AND(P29="Принято",O29<>""),"","Приём заказа смежниками"),IF(F29="Приёмка и оплата",IF(Q29<>"Принято","Подтверждение приёмки; ","")&IF(S29="","Остаток долга не загружен",IF(S29>0,"Оплата клиента","")),IF(AND(N29="Готово",O29<>""),"",V29)))))) | X29: =IF(AND(A29<>"",V29<>"Закрыто",OR(Продажи!$I$4="Все",D29=Продажи!$I$4),OR(Продажи!$O$4="Все",E29=Продажи!$O$4)),1,0) -> 0 | Y29: =IF(A29="","",IF(AND(ISNUMBER(H29),H29<Продажи!$D$4,W29<>"",V29<>"Закрыто"),1,0)) | Z29: =IF(A29="","",IF(V29="Закрыто",0,IF(COUNTIFS(Действия!$B$7:$B$106,A29,Действия!$N$7:$N$106,1,Действия!$D$7:$D$106,"Продажи")=0,1,0))) | AA29: =IF(A29="","",IF(OR(S29="",T29=""),"Нет данных",IF(AND(S29>0,T29<INT(Продажи!$D$4)),S29,0))) | AB29: =IF(A29="","",IFERROR(VLOOKUP(F29,$A$111:$C$127,3,FALSE),"Не классифицировано")) | AC29: =IF(AND(A29<>"",V29<>"Закрыто",H29=""),1,0) -> 0
V30: =IF(A30="","",IFERROR(VLOOKUP(F30,$A$111:$C$127,2,FALSE),"Не задан этап")) | W30: =IF(A30="","",IF(V30="Закрыто","",IF(OR(F30="Расчёт",F30="Решение об участии"),IF(COUNTIF(I30:M30,"Готово")+COUNTIF(I30:M30,"Не требуется")<5,IF(OR(I30="",I30="Нет"),"ТЗ; ","")&IF(OR(J30="",J30="Нет"),"КП завода; ","")&IF(OR(K30="",K30="Нет"),"логистика; ","")&IF(OR(L30="",L30="Нет"),"допрасходы; ","")&IF(OR(M30="",M30="Нет"),"цена продажи; ",""),IF(COUNTIF(I30:M30,"Не требуется")=5,"Проверить применимость расчёта",IF(AND(N30="Готово",O30<>""),"","Подтверждение калькуляции"))),IF(F30="Передача в исполнение",IF(AND(P30="Принято",O30<>""),"","Приём заказа смежниками"),IF(F30="Приёмка и оплата",IF(Q30<>"Принято","Подтверждение приёмки; ","")&IF(S30="","Остаток долга не загружен",IF(S30>0,"Оплата клиента","")),IF(AND(N30="Готово",O30<>""),"",V30)))))) | X30: =IF(AND(A30<>"",V30<>"Закрыто",OR(Продажи!$I$4="Все",D30=Продажи!$I$4),OR(Продажи!$O$4="Все",E30=Продажи!$O$4)),1,0) -> 0 | Y30: =IF(A30="","",IF(AND(ISNUMBER(H30),H30<Продажи!$D$4,W30<>"",V30<>"Закрыто"),1,0)) | Z30: =IF(A30="","",IF(V30="Закрыто",0,IF(COUNTIFS(Действия!$B$7:$B$106,A30,Действия!$N$7:$N$106,1,Действия!$D$7:$D$106,"Продажи")=0,1,0))) | AA30: =IF(A30="","",IF(OR(S30="",T30=""),"Нет данных",IF(AND(S30>0,T30<INT(Продажи!$D$4)),S30,0))) | AB30: =IF(A30="","",IFERROR(VLOOKUP(F30,$A$111:$C$127,3,FALSE),"Не классифицировано")) | AC30: =IF(AND(A30<>"",V30<>"Закрыто",H30=""),1,0) -> 0
V31: =IF(A31="","",IFERROR(VLOOKUP(F31,$A$111:$C$127,2,FALSE),"Не задан этап")) | W31: =IF(A31="","",IF(V31="Закрыто","",IF(OR(F31="Расчёт",F31="Решение об участии"),IF(COUNTIF(I31:M31,"Готово")+COUNTIF(I31:M31,"Не требуется")<5,IF(OR(I31="",I31="Нет"),"ТЗ; ","")&IF(OR(J31="",J31="Нет"),"КП завода; ","")&IF(OR(K31="",K31="Нет"),"логистика; ","")&IF(OR(L31="",L31="Нет"),"допрасходы; ","")&IF(OR(M31="",M31="Нет"),"цена продажи; ",""),IF(COUNTIF(I31:M31,"Не требуется")=5,"Проверить применимость расчёта",IF(AND(N31="Готово",O31<>""),"","Подтверждение калькуляции"))),IF(F31="Передача в исполнение",IF(AND(P31="Принято",O31<>""),"","Приём заказа смежниками"),IF(F31="Приёмка и оплата",IF(Q31<>"Принято","Подтверждение приёмки; ","")&IF(S31="","Остаток долга не загружен",IF(S31>0,"Оплата клиента","")),IF(AND(N31="Готово",O31<>""),"",V31)))))) | X31: =IF(AND(A31<>"",V31<>"Закрыто",OR(Продажи!$I$4="Все",D31=Продажи!$I$4),OR(Продажи!$O$4="Все",E31=Продажи!$O$4)),1,0) -> 0 | Y31: =IF(A31="","",IF(AND(ISNUMBER(H31),H31<Продажи!$D$4,W31<>"",V31<>"Закрыто"),1,0)) | Z31: =IF(A31="","",IF(V31="Закрыто",0,IF(COUNTIFS(Действия!$B$7:$B$106,A31,Действия!$N$7:$N$106,1,Действия!$D$7:$D$106,"Продажи")=0,1,0))) | AA31: =IF(A31="","",IF(OR(S31="",T31=""),"Нет данных",IF(AND(S31>0,T31<INT(Продажи!$D$4)),S31,0))) | AB31: =IF(A31="","",IFERROR(VLOOKUP(F31,$A$111:$C$127,3,FALSE),"Не классифицировано")) | AC31: =IF(AND(A31<>"",V31<>"Закрыто",H31=""),1,0) -> 0
V32: =IF(A32="","",IFERROR(VLOOKUP(F32,$A$111:$C$127,2,FALSE),"Не задан этап")) | W32: =IF(A32="","",IF(V32="Закрыто","",IF(OR(F32="Расчёт",F32="Решение об участии"),IF(COUNTIF(I32:M32,"Готово")+COUNTIF(I32:M32,"Не требуется")<5,IF(OR(I32="",I32="Нет"),"ТЗ; ","")&IF(OR(J32="",J32="Нет"),"КП завода; ","")&IF(OR(K32="",K32="Нет"),"логистика; ","")&IF(OR(L32="",L32="Нет"),"допрасходы; ","")&IF(OR(M32="",M32="Нет"),"цена продажи; ",""),IF(COUNTIF(I32:M32,"Не требуется")=5,"Проверить применимость расчёта",IF(AND(N32="Готово",O32<>""),"","Подтверждение калькуляции"))),IF(F32="Передача в исполнение",IF(AND(P32="Принято",O32<>""),"","Приём заказа смежниками"),IF(F32="Приёмка и оплата",IF(Q32<>"Принято","Подтверждение приёмки; ","")&IF(S32="","Остаток долга не загружен",IF(S32>0,"Оплата клиента","")),IF(AND(N32="Готово",O32<>""),"",V32)))))) | X32: =IF(AND(A32<>"",V32<>"Закрыто",OR(Продажи!$I$4="Все",D32=Продажи!$I$4),OR(Продажи!$O$4="Все",E32=Продажи!$O$4)),1,0) -> 0 | Y32: =IF(A32="","",IF(AND(ISNUMBER(H32),H32<Продажи!$D$4,W32<>"",V32<>"Закрыто"),1,0)) | Z32: =IF(A32="","",IF(V32="Закрыто",0,IF(COUNTIFS(Действия!$B$7:$B$106,A32,Действия!$N$7:$N$106,1,Действия!$D$7:$D$106,"Продажи")=0,1,0))) | AA32: =IF(A32="","",IF(OR(S32="",T32=""),"Нет данных",IF(AND(S32>0,T32<INT(Продажи!$D$4)),S32,0))) | AB32: =IF(A32="","",IFERROR(VLOOKUP(F32,$A$111:$C$127,3,FALSE),"Не классифицировано")) | AC32: =IF(AND(A32<>"",V32<>"Закрыто",H32=""),1,0) -> 0
V33: =IF(A33="","",IFERROR(VLOOKUP(F33,$A$111:$C$127,2,FALSE),"Не задан этап")) | W33: =IF(A33="","",IF(V33="Закрыто","",IF(OR(F33="Расчёт",F33="Решение об участии"),IF(COUNTIF(I33:M33,"Готово")+COUNTIF(I33:M33,"Не требуется")<5,IF(OR(I33="",I33="Нет"),"ТЗ; ","")&IF(OR(J33="",J33="Нет"),"КП завода; ","")&IF(OR(K33="",K33="Нет"),"логистика; ","")&IF(OR(L33="",L33="Нет"),"допрасходы; ","")&IF(OR(M33="",M33="Нет"),"цена продажи; ",""),IF(COUNTIF(I33:M33,"Не требуется")=5,"Проверить применимость расчёта",IF(AND(N33="Готово",O33<>""),"","Подтверждение калькуляции"))),IF(F33="Передача в исполнение",IF(AND(P33="Принято",O33<>""),"","Приём заказа смежниками"),IF(F33="Приёмка и оплата",IF(Q33<>"Принято","Подтверждение приёмки; ","")&IF(S33="","Остаток долга не загружен",IF(S33>0,"Оплата клиента","")),IF(AND(N33="Готово",O33<>""),"",V33)))))) | X33: =IF(AND(A33<>"",V33<>"Закрыто",OR(Продажи!$I$4="Все",D33=Продажи!$I$4),OR(Продажи!$O$4="Все",E33=Продажи!$O$4)),1,0) -> 0 | Y33: =IF(A33="","",IF(AND(ISNUMBER(H33),H33<Продажи!$D$4,W33<>"",V33<>"Закрыто"),1,0)) | Z33: =IF(A33="","",IF(V33="Закрыто",0,IF(COUNTIFS(Действия!$B$7:$B$106,A33,Действия!$N$7:$N$106,1,Действия!$D$7:$D$106,"Продажи")=0,1,0))) | AA33: =IF(A33="","",IF(OR(S33="",T33=""),"Нет данных",IF(AND(S33>0,T33<INT(Продажи!$D$4)),S33,0))) | AB33: =IF(A33="","",IFERROR(VLOOKUP(F33,$A$111:$C$127,3,FALSE),"Не классифицировано")) | AC33: =IF(AND(A33<>"",V33<>"Закрыто",H33=""),1,0) -> 0
... V106: =IF(A106="","",IFERROR(VLOOKUP(F106,$A$111:$C$127,2,FALSE),"Не задан этап")) | W106: =IF(A106="","",IF(V106="Закрыто","",IF(OR(F106="Расчёт",F106="Решение об участии"),IF(COUNTIF(I106:M106,"Готово")+COUNTIF(I106:M106,"Не требуется")<5,IF(OR(I106="",I106="Нет"),"ТЗ; ","")&IF(OR(J106="",J106="Нет"),"КП завода; ","")&IF(OR(K106="",K106="Нет"),"логистика; ","")&IF(OR(L106="",L106="Нет"),"допрасходы; ","")&IF(OR(M106="",M106="Нет"),"цена продажи; ",""),IF(COUNTIF(I106:M106,"Не требуется")=5,"Проверить применимость расчёта",IF(AND(N106="Готово",O106<>""),"","Подтверждение калькуляции"))),IF(F106="Передача в исполнение",IF(AND(P106="Принято",O106<>""),"","Приём заказа смежниками"),IF(F106="Приёмка и оплата",IF(Q106<>"Принято","Подтверждение приёмки; ","")&IF(S106="","Остаток долга не загружен",IF(S106>0,"Оплата клиента","")),IF(AND(N106="Готово",O106<>""),"",V106)))))) | X106: =IF(AND(A106<>"",V106<>"Закрыто",OR(Продажи!$I$4="Все",D106=Продажи!$I$4),OR(Продажи!$O$4="Все",E106=Продажи!$O$4)),1,0) -> 0 | Y106: =IF(A106="","",IF(AND(ISNUMBER(H106),H106<Продажи!$D$4,W106<>"",V106<>"Закрыто"),1,0)) | Z106: =IF(A106="","",IF(V106="Закрыто",0,IF(COUNTIFS(Действия!$B$7:$B$106,A106,Действия!$N$7:$N$106,1,Действия!$D$7:$D$106,"Продажи")=0,1,0))) | AA106: =IF(A106="","",IF(OR(S106="",T106=""),"Нет данных",IF(AND(S106>0,T106<INT(Продажи!$D$4)),S106,0))) | AB106: =IF(A106="","",IFERROR(VLOOKUP(F106,$A$111:$C$127,3,FALSE),"Не классифицировано")) | AC106: =IF(AND(A106<>"",V106<>"Закрыто",H106=""),1,0) -> 0
A110: Этап | B110: Результат | C110: Группа | D110: Где фиксировать
A111: Лиды | B111: Контакт и подтверждённая потребность | C111: Лиды | D111: Битрикс: карточка контакта, ЛПР, потребность и следующий шаг.
A112: Запрос | B112: Ведомость требований клиента | C112: Запрос / проверка | D112: ТЗ, объёмы, срок, адрес, покрытие, монтаж, документы.
A113: Проверка закупки | B113: Лист оценки закупки | C113: Запрос / проверка | D113: Соответствие ТЗ, сроки, обеспечение и риски участия.
A114: Расчёт | B114: Согласованная калькуляция | C114: Расчёт / решение | D114: Закупка, доставка, дополнительные расходы, маржа, цена продажи.
A115: Решение об участии | B115: Согласованная цена и решение участвовать | C115: Расчёт / решение | D115: Калькуляция, обеспечение, комиссии, риски, решение ответственного.
A116: КП | B116: Ответ клиента на предложение | C116: КП / подготовка | D116: Версия КП, факт отправки, обратная связь и препятствие к заказу.
A117: Подготовка заявки | B117: Полный комплект тендерной заявки | C117: КП / подготовка | D117: Техническая часть, цена, допуски, БГ/обеспечение по условиям закупки.
A118: Переговоры | B118: Согласованные условия и открытые вопросы | C118: Переговоры / подача | D118: Возражения, решения, лица согласования, сроки следующего решения.
A119: Подача | B119: Подтверждение подачи площадкой | C119: Переговоры / подача | D119: Квитанция/статус площадки и фактическое время подачи.
A120: Дозапрос | B120: Принятый площадкой ответ | C120: Переговоры / подача | D120: Комплект уточнений и подтверждение приёма в установленный срок.
A121: Результат | B121: Протокол результата закупки | C121: Договор / результат | D121: Результат, причины отказа или требования для заключения договора.
... A127: Закрыто без результата | B127: Закрыто | C127: Закрыто | D127: Причина закрытия фиксируется в Битриксе.
A129: Метод скрытых артефактов: фиксируем основания решений — требования, выбор поставщика, калькуляцию, возражения и условия запуска. | B129: Метод скрытых артефактов: фиксируем основания решений — требования, выбор поставщика, калькуляцию, возражения и условия запуска. | C129: Метод скрытых артефактов: фиксируем основания решений — требования, выбор поставщика, калькуляцию, возражения и условия запуска. | D129: Метод скрытых артефактов: фиксируем основания решений — требования, выбор поставщика, калькуляцию, возражения и условия запуска. | E129: Метод скрытых артефактов: фиксируем основания решений — требования, выбор поставщика, калькуляцию, возражения и условия запуска. | F129: Метод скрытых артефактов: фиксируем основания решений — требования, выбор поставщика, калькуляцию, возражения и условия запуска. | G129: Метод скрытых артефактов: фиксируем основания решений — требования, выбор поставщика, калькуляцию, возражения и условия запуска. | H129: Метод скрытых артефактов: фиксируем основания решений — требования, выбор поставщика, калькуляцию, возражения и условия запуска. | I129: Метод скрытых артефактов: фиксируем основания решений — требования, выбор поставщика, калькуляцию, возражения и условия запуска. | J129: Метод скрытых артефактов: фиксируем основания решений — требования, выбор поставщика, калькуляцию, возражения и условия запуска. | K129: Метод скрытых артефактов: фиксируем основания решений — требования, выбор поставщика, калькуляцию, возражения и условия запуска. | L129: Метод скрытых артефактов: фиксируем основания решений — требования, выбор поставщика, калькуляцию, возражения и условия запуска. | M129: Метод скрытых артефактов: фиксируем основания решений — требования, выбор поставщика, калькуляцию, возражения и условия запуска. | N129: Метод скрытых артефактов: фиксируем основания решений — требования, выбор поставщика, калькуляцию, возражения и условия запуска. | O129: Метод скрытых артефактов: фиксируем основания решений — требования, выбор поставщика, калькуляцию, возражения и условия запуска. | P129: Метод скрытых артефактов: фиксируем основания решений — требования, выбор поставщика, калькуляцию, возражения и условия запуска. | Q129: Метод скрытых артефактов: фиксируем основания решений — требования, выбор поставщика, калькуляцию, возражения и условия запуска. | R129: Метод скрытых артефактов: фиксируем основания решений — требования, выбор поставщика, калькуляцию, возражения и условия запуска. | S129: Метод скрытых артефактов: фиксируем основания решений — требования, выбор поставщика, калькуляцию, возражения и условия запуска. | T129: Метод скрытых артефактов: фиксируем основания решений — требования, выбор поставщика, калькуляцию, возражения и условия запуска. | U129: Метод скрытых артефактов: фиксируем основания решений — требования, выбор поставщика, калькуляцию, возражения и условия запуска.
A130: Битрикс: ID, сотрудник, канал, стадия, история, задачи, сроки, ссылки на результаты, ожидания и решения ИД. Коды полей проверить в вашей коробке. | B130: Битрикс: ID, сотрудник, канал, стадия, история, задачи, сроки, ссылки на результаты, ожидания и решения ИД. Коды полей проверить в вашей коробке. | C130: Битрикс: ID, сотрудник, канал, стадия, история, задачи, сроки, ссылки на результаты, ожидания и решения ИД. Коды полей проверить в вашей коробке. | D130: Битрикс: ID, сотрудник, канал, стадия, история, задачи, сроки, ссылки на результаты, ожидания и решения ИД. Коды полей проверить в вашей коробке. | E130: Битрикс: ID, сотрудник, канал, стадия, история, задачи, сроки, ссылки на результаты, ожидания и решения ИД. Коды полей проверить в вашей коробке. | F130: Битрикс: ID, сотрудник, канал, стадия, история, задачи, сроки, ссылки на результаты, ожидания и решения ИД. Коды полей проверить в вашей коробке. | G130: Битрикс: ID, сотрудник, канал, стадия, история, задачи, сроки, ссылки на результаты, ожидания и решения ИД. Коды полей проверить в вашей коробке. | H130: Битрикс: ID, сотрудник, канал, стадия, история, задачи, сроки, ссылки на результаты, ожидания и решения ИД. Коды полей проверить в вашей коробке. | I130: Битрикс: ID, сотрудник, канал, стадия, история, задачи, сроки, ссылки на результаты, ожидания и решения ИД. Коды полей проверить в вашей коробке. | J130: Битрикс: ID, сотрудник, канал, стадия, история, задачи, сроки, ссылки на результаты, ожидания и решения ИД. Коды полей проверить в вашей коробке. | K130: Битрикс: ID, сотрудник, канал, стадия, история, задачи, сроки, ссылки на результаты, ожидания и решения ИД. Коды полей проверить в вашей коробке. | L130: Битрикс: ID, сотрудник, канал, стадия, история, задачи, сроки, ссылки на результаты, ожидания и решения ИД. Коды полей проверить в вашей коробке. | M130: Битрикс: ID, сотрудник, канал, стадия, история, задачи, сроки, ссылки на результаты, ожидания и решения ИД. Коды полей проверить в вашей коробке. | N130: Битрикс: ID, сотрудник, канал, стадия, история, задачи, сроки, ссылки на результаты, ожидания и решения ИД. Коды полей проверить в вашей коробке. | O130: Битрикс: ID, сотрудник, канал, стадия, история, задачи, сроки, ссылки на результаты, ожидания и решения ИД. Коды полей проверить в вашей коробке. | P130: Битрикс: ID, сотрудник, канал, стадия, история, задачи, сроки, ссылки на результаты, ожидания и решения ИД. Коды полей проверить в вашей коробке. | Q130: Битрикс: ID, сотрудник, канал, стадия, история, задачи, сроки, ссылки на результаты, ожидания и решения ИД. Коды полей проверить в вашей коробке. | R130: Битрикс: ID, сотрудник, канал, стадия, история, задачи, сроки, ссылки на результаты, ожидания и решения ИД. Коды полей проверить в вашей коробке. | S130: Битрикс: ID, сотрудник, канал, стадия, история, задачи, сроки, ссылки на результаты, ожидания и решения ИД. Коды полей проверить в вашей коробке. | T130: Битрикс: ID, сотрудник, канал, стадия, история, задачи, сроки, ссылки на результаты, ожидания и решения ИД. Коды полей проверить в вашей коробке. | U130: Битрикс: ID, сотрудник, канал, стадия, история, задачи, сроки, ссылки на результаты, ожидания и решения ИД. Коды полей проверить в вашей коробке.
A131: 1С: связанные заказы, суммы и затраты, фактическое исполнение, остаток долга и договорный срок оплаты. Сумма предложения не является выручкой. | B131: 1С: связанные заказы, суммы и затраты, фактическое исполнение, остаток долга и договорный срок оплаты. Сумма предложения не является выручкой. | C131: 1С: связанные заказы, суммы и затраты, фактическое исполнение, остаток долга и договорный срок оплаты. Сумма предложения не является выручкой. | D131: 1С: связанные заказы, суммы и затраты, фактическое исполнение, остаток долга и договорный срок оплаты. Сумма предложения не является выручкой. | E131: 1С: связанные заказы, суммы и затраты, фактическое исполнение, остаток долга и договорный срок оплаты. Сумма предложения не является выручкой. | F131: 1С: связанные заказы, суммы и затраты, фактическое исполнение, остаток долга и договорный срок оплаты. Сумма предложения не является выручкой. | G131: 1С: связанные заказы, суммы и затраты, фактическое исполнение, остаток долга и договорный срок оплаты. Сумма предложения не является выручкой. | H131: 1С: связанные заказы, суммы и затраты, фактическое исполнение, остаток долга и договорный срок оплаты. Сумма предложения не является выручкой. | I131: 1С: связанные заказы, суммы и затраты, фактическое исполнение, остаток долга и договорный срок оплаты. Сумма предложения не является выручкой. | J131: 1С: связанные заказы, суммы и затраты, фактическое исполнение, остаток долга и договорный срок оплаты. Сумма предложения не является выручкой. | K131: 1С: связанные заказы, суммы и затраты, фактическое исполнение, остаток долга и договорный срок оплаты. Сумма предложения не является выручкой. | L131: 1С: связанные заказы, суммы и затраты, фактическое исполнение, остаток долга и договорный срок оплаты. Сумма предложения не является выручкой. | M131: 1С: связанные заказы, суммы и затраты, фактическое исполнение, остаток долга и договорный срок оплаты. Сумма предложения не является выручкой. | N131: 1С: связанные заказы, суммы и затраты, фактическое исполнение, остаток долга и договорный срок оплаты. Сумма предложения не является выручкой. | O131: 1С: связанные заказы, суммы и затраты, фактическое исполнение, остаток долга и договорный срок оплаты. Сумма предложения не является выручкой. | P131: 1С: связанные заказы, суммы и затраты, фактическое исполнение, остаток долга и договорный срок оплаты. Сумма предложения не является выручкой. | Q131: 1С: связанные заказы, суммы и затраты, фактическое исполнение, остаток долга и договорный срок оплаты. Сумма предложения не является выручкой. | R131: 1С: связанные заказы, суммы и затраты, фактическое исполнение, остаток долга и договорный срок оплаты. Сумма предложения не является выручкой. | S131: 1С: связанные заказы, суммы и затраты, фактическое исполнение, остаток долга и договорный срок оплаты. Сумма предложения не является выручкой. | T131: 1С: связанные заказы, суммы и затраты, фактическое исполнение, остаток долга и договорный срок оплаты. Сумма предложения не является выручкой. | U131: 1С: связанные заказы, суммы и затраты, фактическое исполнение, остаток долга и договорный срок оплаты. Сумма предложения не является выручкой.
A132: Готовность: Готово + ID/ссылка в O. Для расчёта дополнительно заполнены I:M. Для передачи — P=Принято. Для приёмки — Q=Принято и долг S=0. | B132: Готовность: Готово + ID/ссылка в O. Для расчёта дополнительно заполнены I:M. Для передачи — P=Принято. Для приёмки — Q=Принято и долг S=0. | C132: Готовность: Готово + ID/ссылка в O. Для расчёта дополнительно заполнены I:M. Для передачи — P=Принято. Для приёмки — Q=Принято и долг S=0. | D132: Готовность: Готово + ID/ссылка в O. Для расчёта дополнительно заполнены I:M. Для передачи — P=Принято. Для приёмки — Q=Принято и долг S=0. | E132: Готовность: Готово + ID/ссылка в O. Для расчёта дополнительно заполнены I:M. Для передачи — P=Принято. Для приёмки — Q=Принято и долг S=0. | F132: Готовность: Готово + ID/ссылка в O. Для расчёта дополнительно заполнены I:M. Для передачи — P=Принято. Для приёмки — Q=Принято и долг S=0. | G132: Готовность: Готово + ID/ссылка в O. Для расчёта дополнительно заполнены I:M. Для передачи — P=Принято. Для приёмки — Q=Принято и долг S=0. | H132: Готовность: Готово + ID/ссылка в O. Для расчёта дополнительно заполнены I:M. Для передачи — P=Принято. Для приёмки — Q=Принято и долг S=0. | I132: Готовность: Готово + ID/ссылка в O. Для расчёта дополнительно заполнены I:M. Для передачи — P=Принято. Для приёмки — Q=Принято и долг S=0. | J132: Готовность: Готово + ID/ссылка в O. Для расчёта дополнительно заполнены I:M. Для передачи — P=Принято. Для приёмки — Q=Принято и долг S=0. | K132: Готовность: Готово + ID/ссылка в O. Для расчёта дополнительно заполнены I:M. Для передачи — P=Принято. Для приёмки — Q=Принято и долг S=0. | L132: Готовность: Готово + ID/ссылка в O. Для расчёта дополнительно заполнены I:M. Для передачи — P=Принято. Для приёмки — Q=Принято и долг S=0. | M132: Готовность: Готово + ID/ссылка в O. Для расчёта дополнительно заполнены I:M. Для передачи — P=Принято. Для приёмки — Q=Принято и долг S=0. | N132: Готовность: Готово + ID/ссылка в O. Для расчёта дополнительно заполнены I:M. Для передачи — P=Принято. Для приёмки — Q=Принято и долг S=0. | O132: Готовность: Готово + ID/ссылка в O. Для расчёта дополнительно заполнены I:M. Для передачи — P=Принято. Для приёмки — Q=Принято и долг S=0. | P132: Готовность: Готово + ID/ссылка в O. Для расчёта дополнительно заполнены I:M. Для передачи — P=Принято. Для приёмки — Q=Принято и долг S=0. | Q132: Готовность: Готово + ID/ссылка в O. Для расчёта дополнительно заполнены I:M. Для передачи — P=Принято. Для приёмки — Q=Принято и долг S=0. | R132: Готовность: Готово + ID/ссылка в O. Для расчёта дополнительно заполнены I:M. Для передачи — P=Принято. Для приёмки — Q=Принято и долг S=0. | S132: Готовность: Готово + ID/ссылка в O. Для расчёта дополнительно заполнены I:M. Для передачи — P=Принято. Для приёмки — Q=Принято и долг S=0. | T132: Готовность: Готово + ID/ссылка в O. Для расчёта дополнительно заполнены I:M. Для передачи — P=Принято. Для приёмки — Q=Принято и долг S=0. | U132: Готовность: Готово + ID/ссылка в O. Для расчёта дополнительно заполнены I:M. Для передачи — P=Принято. Для приёмки — Q=Принято и долг S=0.
A133: Флажки I:M описывают готовность частей расчёта. Не требуется допустимо только при обосновании; для расчёта не допускается Не требуется во всех пяти полях. | B133: Флажки I:M описывают готовность частей расчёта. Не требуется допустимо только при обосновании; для расчёта не допускается Не требуется во всех пяти полях. | C133: Флажки I:M описывают готовность частей расчёта. Не требуется допустимо только при обосновании; для расчёта не допускается Не требуется во всех пяти полях. | D133: Флажки I:M описывают готовность частей расчёта. Не требуется допустимо только при обосновании; для расчёта не допускается Не требуется во всех пяти полях. | E133: Флажки I:M описывают готовность частей расчёта. Не требуется допустимо только при обосновании; для расчёта не допускается Не требуется во всех пяти полях. | F133: Флажки I:M описывают готовность частей расчёта. Не требуется допустимо только при обосновании; для расчёта не допускается Не требуется во всех пяти полях. | G133: Флажки I:M описывают готовность частей расчёта. Не требуется допустимо только при обосновании; для расчёта не допускается Не требуется во всех пяти полях. | H133: Флажки I:M описывают готовность частей расчёта. Не требуется допустимо только при обосновании; для расчёта не допускается Не требуется во всех пяти полях. | I133: Флажки I:M описывают готовность частей расчёта. Не требуется допустимо только при обосновании; для расчёта не допускается Не требуется во всех пяти полях. | J133: Флажки I:M описывают готовность частей расчёта. Не требуется допустимо только при обосновании; для расчёта не допускается Не требуется во всех пяти полях. | K133: Флажки I:M описывают готовность частей расчёта. Не требуется допустимо только при обосновании; для расчёта не допускается Не требуется во всех пяти полях. | L133: Флажки I:M описывают готовность частей расчёта. Не требуется допустимо только при обосновании; для расчёта не допускается Не требуется во всех пяти полях. | M133: Флажки I:M описывают готовность частей расчёта. Не требуется допустимо только при обосновании; для расчёта не допускается Не требуется во всех пяти полях. | N133: Флажки I:M описывают готовность частей расчёта. Не требуется допустимо только при обосновании; для расчёта не допускается Не требуется во всех пяти полях. | O133: Флажки I:M описывают готовность частей расчёта. Не требуется допустимо только при обосновании; для расчёта не допускается Не требуется во всех пяти полях. | P133: Флажки I:M описывают готовность частей расчёта. Не требуется допустимо только при обосновании; для расчёта не допускается Не требуется во всех пяти полях. | Q133: Флажки I:M описывают готовность частей расчёта. Не требуется допустимо только при обосновании; для расчёта не допускается Не требуется во всех пяти полях. | R133: Флажки I:M описывают готовность частей расчёта. Не требуется допустимо только при обосновании; для расчёта не допускается Не требуется во всех пяти полях. | S133: Флажки I:M описывают готовность частей расчёта. Не требуется допустимо только при обосновании; для расчёта не допускается Не требуется во всех пяти полях. | T133: Флажки I:M описывают готовность частей расчёта. Не требуется допустимо только при обосновании; для расчёта не допускается Не требуется во всех пяти полях. | U133: Флажки I:M описывают готовность частей расчёта. Не требуется допустимо только при обосновании; для расчёта не допускается Не требуется во всех пяти полях.
A134: Источник метода: Д. Гуреев, «Цифровое мышление в бизнесе», открытое предисловие МИФ. Структура панели — адаптация под ТТК, а не цитата. | B134: Источник метода: Д. Гуреев, «Цифровое мышление в бизнесе», открытое предисловие МИФ. Структура панели — адаптация под ТТК, а не цитата. | C134: Источник метода: Д. Гуреев, «Цифровое мышление в бизнесе», открытое предисловие МИФ. Структура панели — адаптация под ТТК, а не цитата. | D134: Источник метода: Д. Гуреев, «Цифровое мышление в бизнесе», открытое предисловие МИФ. Структура панели — адаптация под ТТК, а не цитата. | E134: Источник метода: Д. Гуреев, «Цифровое мышление в бизнесе», открытое предисловие МИФ. Структура панели — адаптация под ТТК, а не цитата. | F134: Источник метода: Д. Гуреев, «Цифровое мышление в бизнесе», открытое предисловие МИФ. Структура панели — адаптация под ТТК, а не цитата. | G134: Источник метода: Д. Гуреев, «Цифровое мышление в бизнесе», открытое предисловие МИФ. Структура панели — адаптация под ТТК, а не цитата. | H134: Источник метода: Д. Гуреев, «Цифровое мышление в бизнесе», открытое предисловие МИФ. Структура панели — адаптация под ТТК, а не цитата. | I134: Источник метода: Д. Гуреев, «Цифровое мышление в бизнесе», открытое предисловие МИФ. Структура панели — адаптация под ТТК, а не цитата. | J134: Источник метода: Д. Гуреев, «Цифровое мышление в бизнесе», открытое предисловие МИФ. Структура панели — адаптация под ТТК, а не цитата. | K134: Источник метода: Д. Гуреев, «Цифровое мышление в бизнесе», открытое предисловие МИФ. Структура панели — адаптация под ТТК, а не цитата. | L134: Источник метода: Д. Гуреев, «Цифровое мышление в бизнесе», открытое предисловие МИФ. Структура панели — адаптация под ТТК, а не цитата. | M134: Источник метода: Д. Гуреев, «Цифровое мышление в бизнесе», открытое предисловие МИФ. Структура панели — адаптация под ТТК, а не цитата. | N134: Источник метода: Д. Гуреев, «Цифровое мышление в бизнесе», открытое предисловие МИФ. Структура панели — адаптация под ТТК, а не цитата. | O134: Источник метода: Д. Гуреев, «Цифровое мышление в бизнесе», открытое предисловие МИФ. Структура панели — адаптация под ТТК, а не цитата. | P134: Источник метода: Д. Гуреев, «Цифровое мышление в бизнесе», открытое предисловие МИФ. Структура панели — адаптация под ТТК, а не цитата. | Q134: Источник метода: Д. Гуреев, «Цифровое мышление в бизнесе», открытое предисловие МИФ. Структура панели — адаптация под ТТК, а не цитата. | R134: Источник метода: Д. Гуреев, «Цифровое мышление в бизнесе», открытое предисловие МИФ. Структура панели — адаптация под ТТК, а не цитата. | S134: Источник метода: Д. Гуреев, «Цифровое мышление в бизнесе», открытое предисловие МИФ. Структура панели — адаптация под ТТК, а не цитата. | T134: Источник метода: Д. Гуреев, «Цифровое мышление в бизнесе», открытое предисловие МИФ. Структура панели — адаптация под ТТК, а не цитата. | U134: Источник метода: Д. Гуреев, «Цифровое мышление в бизнесе», открытое предисловие МИФ. Структура панели — адаптация под ТТК, а не цитата.
A135: https://www.mann-ivanov-ferber.ru/assets/media/files-3/cifrovoe-myslenie-v-biznese/cifrovoe-myslenie-v-biznese-mail_stamped.pdf | B135: https://www.mann-ivanov-ferber.ru/assets/media/files-3/cifrovoe-myslenie-v-biznese/cifrovoe-myslenie-v-biznese-mail_stamped.pdf | C135: https://www.mann-ivanov-ferber.ru/assets/media/files-3/cifrovoe-myslenie-v-biznese/cifrovoe-myslenie-v-biznese-mail_stamped.pdf | D135: https://www.mann-ivanov-ferber.ru/assets/media/files-3/cifrovoe-myslenie-v-biznese/cifrovoe-myslenie-v-biznese-mail_stamped.pdf | E135: https://www.mann-ivanov-ferber.ru/assets/media/files-3/cifrovoe-myslenie-v-biznese/cifrovoe-myslenie-v-biznese-mail_stamped.pdf | F135: https://www.mann-ivanov-ferber.ru/assets/media/files-3/cifrovoe-myslenie-v-biznese/cifrovoe-myslenie-v-biznese-mail_stamped.pdf | G135: https://www.mann-ivanov-ferber.ru/assets/media/files-3/cifrovoe-myslenie-v-biznese/cifrovoe-myslenie-v-biznese-mail_stamped.pdf | H135: https://www.mann-ivanov-ferber.ru/assets/media/files-3/cifrovoe-myslenie-v-biznese/cifrovoe-myslenie-v-biznese-mail_stamped.pdf | I135: https://www.mann-ivanov-ferber.ru/assets/media/files-3/cifrovoe-myslenie-v-biznese/cifrovoe-myslenie-v-biznese-mail_stamped.pdf | J135: https://www.mann-ivanov-ferber.ru/assets/media/files-3/cifrovoe-myslenie-v-biznese/cifrovoe-myslenie-v-biznese-mail_stamped.pdf | K135: https://www.mann-ivanov-ferber.ru/assets/media/files-3/cifrovoe-myslenie-v-biznese/cifrovoe-myslenie-v-biznese-mail_stamped.pdf | L135: https://www.mann-ivanov-ferber.ru/assets/media/files-3/cifrovoe-myslenie-v-biznese/cifrovoe-myslenie-v-biznese-mail_stamped.pdf | M135: https://www.mann-ivanov-ferber.ru/assets/media/files-3/cifrovoe-myslenie-v-biznese/cifrovoe-myslenie-v-biznese-mail_stamped.pdf | N135: https://www.mann-ivanov-ferber.ru/assets/media/files-3/cifrovoe-myslenie-v-biznese/cifrovoe-myslenie-v-biznese-mail_stamped.pdf | O135: https://www.mann-ivanov-ferber.ru/assets/media/files-3/cifrovoe-myslenie-v-biznese/cifrovoe-myslenie-v-biznese-mail_stamped.pdf | P135: https://www.mann-ivanov-ferber.ru/assets/media/files-3/cifrovoe-myslenie-v-biznese/cifrovoe-myslenie-v-biznese-mail_stamped.pdf | Q135: https://www.mann-ivanov-ferber.ru/assets/media/files-3/cifrovoe-myslenie-v-biznese/cifrovoe-myslenie-v-biznese-mail_stamped.pdf | R135: https://www.mann-ivanov-ferber.ru/assets/media/files-3/cifrovoe-myslenie-v-biznese/cifrovoe-myslenie-v-biznese-mail_stamped.pdf | S135: https://www.mann-ivanov-ferber.ru/assets/media/files-3/cifrovoe-myslenie-v-biznese/cifrovoe-myslenie-v-biznese-mail_stamped.pdf | T135: https://www.mann-ivanov-ferber.ru/assets/media/files-3/cifrovoe-myslenie-v-biznese/cifrovoe-myslenie-v-biznese-mail_stamped.pdf | U135: https://www.mann-ivanov-ferber.ru/assets/media/files-3/cifrovoe-myslenie-v-biznese/cifrovoe-myslenie-v-biznese-mail_stamped.pdf
A137: Все
A138: Менеджер 1 | C138: Имена сотрудников для списков. При изменении имени обновите соответствующие строки реестра. | D138: Имена сотрудников для списков. При изменении имени обновите соответствующие строки реестра. | E138: Имена сотрудников для списков. При изменении имени обновите соответствующие строки реестра. | F138: Имена сотрудников для списков. При изменении имени обновите соответствующие строки реестра. | G138: Имена сотрудников для списков. При изменении имени обновите соответствующие строки реестра. | H138: Имена сотрудников для списков. При изменении имени обновите соответствующие строки реестра. | I138: Имена сотрудников для списков. При изменении имени обновите соответствующие строки реестра. | J138: Имена сотрудников для списков. При изменении имени обновите соответствующие строки реестра. | K138: Имена сотрудников для списков. При изменении имени обновите соответствующие строки реестра. | L138: Имена сотрудников для списков. При изменении имени обновите соответствующие строки реестра. | M138: Имена сотрудников для списков. При изменении имени обновите соответствующие строки реестра. | N138: Имена сотрудников для списков. При изменении имени обновите соответствующие строки реестра. | O138: Имена сотрудников для списков. При изменении имени обновите соответствующие строки реестра. | P138: Имена сотрудников для списков. При изменении имени обновите соответствующие строки реестра. | Q138: Имена сотрудников для списков. При изменении имени обновите соответствующие строки реестра. | R138: Имена сотрудников для списков. При изменении имени обновите соответствующие строки реестра. | S138: Имена сотрудников для списков. При изменении имени обновите соответствующие строки реестра. | T138: Имена сотрудников для списков. При изменении имени обновите соответствующие строки реестра. | U138: Имена сотрудников для списков. При изменении имени обновите соответствующие строки реестра.
A139: Менеджер 2
A140: Тендерный специалист

Sheet Действия
A2: Действия и ожидания по продажам | B2: Действия и ожидания по продажам | C2: Действия и ожидания по продажам | D2: Действия и ожидания по продажам | E2: Действия и ожидания по продажам | F2: Действия и ожидания по продажам | G2: Действия и ожидания по продажам | H2: Действия и ожидания по продажам | I2: Действия и ожидания по продажам | J2: Действия и ожидания по продажам | K2: Действия и ожидания по продажам
A3: Отдельные строки для действия продавца и запроса другому отделу. Дата и время — Екатеринбург, UTC+5. | B3: Отдельные строки для действия продавца и запроса другому отделу. Дата и время — Екатеринбург, UTC+5. | C3: Отдельные строки для действия продавца и запроса другому отделу. Дата и время — Екатеринбург, UTC+5. | D3: Отдельные строки для действия продавца и запроса другому отделу. Дата и время — Екатеринбург, UTC+5. | E3: Отдельные строки для действия продавца и запроса другому отделу. Дата и время — Екатеринбург, UTC+5. | F3: Отдельные строки для действия продавца и запроса другому отделу. Дата и время — Екатеринбург, UTC+5. | G3: Отдельные строки для действия продавца и запроса другому отделу. Дата и время — Екатеринбург, UTC+5. | H3: Отдельные строки для действия продавца и запроса другому отделу. Дата и время — Екатеринбург, UTC+5. | I3: Отдельные строки для действия продавца и запроса другому отделу. Дата и время — Екатеринбург, UTC+5. | J3: Отдельные строки для действия продавца и запроса другому отделу. Дата и время — Екатеринбург, UTC+5. | K3: Отдельные строки для действия продавца и запроса другому отделу. Дата и время — Екатеринбург, UTC+5.
A4: Приоритет: 1 — жёсткий срок в ближайшие 48 часов/просрочен; 2 — прочая просрочка; 3 — сегодня; 4 — решение ИД или отсутствует срок. | B4: Приоритет: 1 — жёсткий срок в ближайшие 48 часов/просрочен; 2 — прочая просрочка; 3 — сегодня; 4 — решение ИД или отсутствует срок. | C4: Приоритет: 1 — жёсткий срок в ближайшие 48 часов/просрочен; 2 — прочая просрочка; 3 — сегодня; 4 — решение ИД или отсутствует срок. | D4: Приоритет: 1 — жёсткий срок в ближайшие 48 часов/просрочен; 2 — прочая просрочка; 3 — сегодня; 4 — решение ИД или отсутствует срок. | E4: Приоритет: 1 — жёсткий срок в ближайшие 48 часов/просрочен; 2 — прочая просрочка; 3 — сегодня; 4 — решение ИД или отсутствует срок. | F4: Приоритет: 1 — жёсткий срок в ближайшие 48 часов/просрочен; 2 — прочая просрочка; 3 — сегодня; 4 — решение ИД или отсутствует срок. | G4: Приоритет: 1 — жёсткий срок в ближайшие 48 часов/просрочен; 2 — прочая просрочка; 3 — сегодня; 4 — решение ИД или отсутствует срок. | H4: Приоритет: 1 — жёсткий срок в ближайшие 48 часов/просрочен; 2 — прочая просрочка; 3 — сегодня; 4 — решение ИД или отсутствует срок. | I4: Приоритет: 1 — жёсткий срок в ближайшие 48 часов/просрочен; 2 — прочая просрочка; 3 — сегодня; 4 — решение ИД или отсутствует срок. | J4: Приоритет: 1 — жёсткий срок в ближайшие 48 часов/просрочен; 2 — прочая просрочка; 3 — сегодня; 4 — решение ИД или отсутствует срок. | K4: Приоритет: 1 — жёсткий срок в ближайшие 48 часов/просрочен; 2 — прочая просрочка; 3 — сегодня; 4 — решение ИД или отсутствует срок.
A6: ID действия | B6: ID объекта | C6: Что сделать | D6: Кто должен выдать результат | E6: Исполнитель | F6: Срок | G6: Тип действия | H6: Статус | I6: Нужно решение ИД | J6: Вопрос для ИД | K6: Ссылка / подтверждение | L6: Менеджер сделки | M6: Канал | N6: Активно | O6: Просрочено, часов | P6: Критический срок | Q6: Просрочка продаж | R6: Ожидание других | S6: Выбран фильтром | T6: Приоритет | U6: Место в списке | V6: Не готов результат | W6: Клиент / объект | X6: Ранг решения ИД | Y6: Срок для сортировки
A7: Д-01 | B7: Л-001 | C7: Связаться с ЛПР | D7: Продажи | E7: Менеджер 1 | F7: 46321.458 | G7: Контакт | H7: Открыто | I7: Нет | L7: =IF(A7="","",IFERROR(INDEX(Реестр!$D$7:$D$106,MATCH(B7,Реестр!$A$7:$A$106,0)),"Нет связи")) -> Менеджер 1 | M7: =IF(A7="","",IFERROR(INDEX(Реестр!$E$7:$E$106,MATCH(B7,Реестр!$A$7:$A$106,0)),"Нет связи")) -> Прямые | N7: =IF(AND(A7<>"",H7<>"Закрыто",L7<>"Нет связи"),IF(INDEX(Реестр!$V$7:$V$106,MATCH(B7,Реестр!$A$7:$A$106,0))="Закрыто",0,1),0) -> 1 | O7: =IF(N7=0,0,IF(F7="","Нет срока",MAX(0,(Продажи!$D$4-F7)*24))) -> 0 | P7: =IF(AND(N7=1,ISNUMBER(F7),F7<=Продажи!$D$4+2,OR(G7="Подача",G7="Дозапрос",G7="Обеспечение",G7="Обязательство клиенту")),1,0) -> 0 | Q7: =IF(AND(N7=1,D7="Продажи",ISNUMBER(O7),O7>0),1,0) -> 0 | R7: =IF(AND(N7=1,H7="Ожидание",D7<>"Продажи"),1,0) -> 0 | S7: =IF(AND(N7=1,OR(Продажи!$I$4="Все",L7=Продажи!$I$4),OR(Продажи!$O$4="Все",M7=Продажи!$O$4)),1,0) -> 1 | T7: =IF(S7=0,0,IF(P7=1,1,IF(AND(ISNUMBER(O7),O7>0),2,IF(AND(ISNUMBER(F7),INT(F7)=INT(Продажи!$D$4)),3,IF(OR(I7="Да",F7=""),4,0))))) -> 3 | U7: =IF(T7=0,"",COUNTIFS($T$7:$T$106,">0",$T$7:$T$106,"<"&T7)+COUNTIFS($T$7:$T$106,T7,$Y$7:$Y$106,"<"&Y7)+COUNTIFS($T$7:T7,T7,$Y$7:Y7,Y7)) -> 11 | V7: =IF(A7="","",IFERROR(INDEX(Реестр!$W$7:$W$106,MATCH(B7,Реестр!$A$7:$A$106,0)),"Нет связи")) -> Контакт и подтверждённая потребность | W7: =IF(A7="","",IFERROR(INDEX(Реестр!$C$7:$C$106,MATCH(B7,Реестр!$A$7:$A$106,0)),"Нет связи")) -> Компания А | X7: =IF(AND(S7=1,I7="Да"),COUNTIFS($S$7:$S$106,1,$I$7:$I$106,"Да",$Y$7:$Y$106,"<"&Y7)+COUNTIFS($S$7:S7,1,$I$7:I7,"Да",$Y$7:Y7,Y7),"") | Y7: =IF(N7=1,IF(ISNUMBER(F7),F7,2958465),"") -> 46321.458
A8: Д-02 | B8: Л-002 | C8: Уточнить объём и срок потребности | D8: Продажи | E8: Менеджер 2 | F8: 46320.667 | G8: Контакт | H8: Открыто | I8: Нет | L8: =IF(A8="","",IFERROR(INDEX(Реестр!$D$7:$D$106,MATCH(B8,Реестр!$A$7:$A$106,0)),"Нет связи")) -> Менеджер 2 | M8: =IF(A8="","",IFERROR(INDEX(Реестр!$E$7:$E$106,MATCH(B8,Реестр!$A$7:$A$106,0)),"Нет связи")) -> Прямые | N8: =IF(AND(A8<>"",H8<>"Закрыто",L8<>"Нет связи"),IF(INDEX(Реестр!$V$7:$V$106,MATCH(B8,Реестр!$A$7:$A$106,0))="Закрыто",0,1),0) -> 1 | O8: =IF(N8=0,0,IF(F8="","Нет срока",MAX(0,(Продажи!$D$4-F8)*24))) -> 17 | P8: =IF(AND(N8=1,ISNUMBER(F8),F8<=Продажи!$D$4+2,OR(G8="Подача",G8="Дозапрос",G8="Обеспечение",G8="Обязательство клиенту")),1,0) -> 0 | Q8: =IF(AND(N8=1,D8="Продажи",ISNUMBER(O8),O8>0),1,0) -> 1 | R8: =IF(AND(N8=1,H8="Ожидание",D8<>"Продажи"),1,0) -> 0 | S8: =IF(AND(N8=1,OR(Продажи!$I$4="Все",L8=Продажи!$I$4),OR(Продажи!$O$4="Все",M8=Продажи!$O$4)),1,0) -> 1 | T8: =IF(S8=0,0,IF(P8=1,1,IF(AND(ISNUMBER(O8),O8>0),2,IF(AND(ISNUMBER(F8),INT(F8)=INT(Продажи!$D$4)),3,IF(OR(I8="Да",F8=""),4,0))))) -> 2 | U8: =IF(T8=0,"",COUNTIFS($T$7:$T$106,">0",$T$7:$T$106,"<"&T8)+COUNTIFS($T$7:$T$106,T8,$Y$7:$Y$106,"<"&Y8)+COUNTIFS($T$7:T8,T8,$Y$7:Y8,Y8)) -> 8 | V8: =IF(A8="","",IFERROR(INDEX(Реестр!$W$7:$W$106,MATCH(B8,Реестр!$A$7:$A$106,0)),"Нет связи")) -> Контакт и подтверждённая потребность | W8: =IF(A8="","",IFERROR(INDEX(Реестр!$C$7:$C$106,MATCH(B8,Реестр!$A$7:$A$106,0)),"Нет связи")) -> Компания Б | X8: =IF(AND(S8=1,I8="Да"),COUNTIFS($S$7:$S$106,1,$I$7:$I$106,"Да",$Y$7:$Y$106,"<"&Y8)+COUNTIFS($S$7:S8,1,$I$7:I8,"Да",$Y$7:Y8,Y8),"") | Y8: =IF(N8=1,IF(ISNUMBER(F8),F8,2958465),"") -> 46320.667
A9: Д-03 | B9: Л-003 | C9: Передать требования на расчёт | D9: Продажи | E9: Менеджер 1 | F9: 46322.5 | G9: Внутренняя задача | H9: Открыто | I9: Нет | L9: =IF(A9="","",IFERROR(INDEX(Реестр!$D$7:$D$106,MATCH(B9,Реестр!$A$7:$A$106,0)),"Нет связи")) -> Менеджер 1 | M9: =IF(A9="","",IFERROR(INDEX(Реестр!$E$7:$E$106,MATCH(B9,Реестр!$A$7:$A$106,0)),"Нет связи")) -> Прямые | N9: =IF(AND(A9<>"",H9<>"Закрыто",L9<>"Нет связи"),IF(INDEX(Реестр!$V$7:$V$106,MATCH(B9,Реестр!$A$7:$A$106,0))="Закрыто",0,1),0) -> 1 | O9: =IF(N9=0,0,IF(F9="","Нет срока",MAX(0,(Продажи!$D$4-F9)*24))) -> 0 | P9: =IF(AND(N9=1,ISNUMBER(F9),F9<=Продажи!$D$4+2,OR(G9="Подача",G9="Дозапрос",G9="Обеспечение",G9="Обязательство клиенту")),1,0) -> 0 | Q9: =IF(AND(N9=1,D9="Продажи",ISNUMBER(O9),O9>0),1,0) -> 0 | R9: =IF(AND(N9=1,H9="Ожидание",D9<>"Продажи"),1,0) -> 0 | S9: =IF(AND(N9=1,OR(Продажи!$I$4="Все",L9=Продажи!$I$4),OR(Продажи!$O$4="Все",M9=Продажи!$O$4)),1,0) -> 1 | T9: =IF(S9=0,0,IF(P9=1,1,IF(AND(ISNUMBER(O9),O9>0),2,IF(AND(ISNUMBER(F9),INT(F9)=INT(Продажи!$D$4)),3,IF(OR(I9="Да",F9=""),4,0))))) -> 0 | U9: =IF(T9=0,"",COUNTIFS($T$7:$T$106,">0",$T$7:$T$106,"<"&T9)+COUNTIFS($T$7:$T$106,T9,$Y$7:$Y$106,"<"&Y9)+COUNTIFS($T$7:T9,T9,$Y$7:Y9,Y9)) | V9: =IF(A9="","",IFERROR(INDEX(Реестр!$W$7:$W$106,MATCH(B9,Реестр!$A$7:$A$106,0)),"Нет связи")) | W9: =IF(A9="","",IFERROR(INDEX(Реестр!$C$7:$C$106,MATCH(B9,Реестр!$A$7:$A$106,0)),"Нет связи")) -> Компания В | X9: =IF(AND(S9=1,I9="Да"),COUNTIFS($S$7:$S$106,1,$I$7:$I$106,"Да",$Y$7:$Y$106,"<"&Y9)+COUNTIFS($S$7:S9,1,$I$7:I9,"Да",$Y$7:Y9,Y9),"") | Y9: =IF(N9=1,IF(ISNUMBER(F9),F9,2958465),"") -> 46322.5
A10: Д-04 | B10: С-101 | C10: Получить ведомость объёмов | D10: Клиент | E10: Ответственный клиента | F10: 46320.708 | G10: Требования | H10: Ожидание | I10: Нет | L10: =IF(A10="","",IFERROR(INDEX(Реестр!$D$7:$D$106,MATCH(B10,Реестр!$A$7:$A$106,0)),"Нет связи")) -> Менеджер 1 | M10: =IF(A10="","",IFERROR(INDEX(Реестр!$E$7:$E$106,MATCH(B10,Реестр!$A$7:$A$106,0)),"Нет связи")) -> Прямые | N10: =IF(AND(A10<>"",H10<>"Закрыто",L10<>"Нет связи"),IF(INDEX(Реестр!$V$7:$V$106,MATCH(B10,Реестр!$A$7:$A$106,0))="Закрыто",0,1),0) -> 1 | O10: =IF(N10=0,0,IF(F10="","Нет срока",MAX(0,(Продажи!$D$4-F10)*24))) -> 16 | P10: =IF(AND(N10=1,ISNUMBER(F10),F10<=Продажи!$D$4+2,OR(G10="Подача",G10="Дозапрос",G10="Обеспечение",G10="Обязательство клиенту")),1,0) -> 0 | Q10: =IF(AND(N10=1,D10="Продажи",ISNUMBER(O10),O10>0),1,0) -> 0 | R10: =IF(AND(N10=1,H10="Ожидание",D10<>"Продажи"),1,0) -> 1 | S10: =IF(AND(N10=1,OR(Продажи!$I$4="Все",L10=Продажи!$I$4),OR(Продажи!$O$4="Все",M10=Продажи!$O$4)),1,0) -> 1 | T10: =IF(S10=0,0,IF(P10=1,1,IF(AND(ISNUMBER(O10),O10>0),2,IF(AND(ISNUMBER(F10),INT(F10)=INT(Продажи!$D$4)),3,IF(OR(I10="Да",F10=""),4,0))))) -> 2 | U10: =IF(T10=0,"",COUNTIFS($T$7:$T$106,">0",$T$7:$T$106,"<"&T10)+COUNTIFS($T$7:$T$106,T10,$Y$7:$Y$106,"<"&Y10)+COUNTIFS($T$7:T10,T10,$Y$7:Y10,Y10)) -> 9 | V10: =IF(A10="","",IFERROR(INDEX(Реестр!$W$7:$W$106,MATCH(B10,Реестр!$A$7:$A$106,0)),"Нет связи")) -> Ведомость требований клиента | W10: =IF(A10="","",IFERROR(INDEX(Реестр!$C$7:$C$106,MATCH(B10,Реестр!$A$7:$A$106,0)),"Нет связи")) -> Компания Г | X10: =IF(AND(S10=1,I10="Да"),COUNTIFS($S$7:$S$106,1,$I$7:$I$106,"Да",$Y$7:$Y$106,"<"&Y10)+COUNTIFS($S$7:S10,1,$I$7:I10,"Да",$Y$7:Y10,Y10),"") | Y10: =IF(N10=1,IF(ISNUMBER(F10),F10,2958465),"") -> 46320.708
A11: Д-05 | B11: С-101 | C11: Повторно запросить ТЗ у клиента | D11: Продажи | E11: Менеджер 1 | F11: 46321.417 | G11: Контакт | H11: Открыто | I11: Нет | L11: =IF(A11="","",IFERROR(INDEX(Реестр!$D$7:$D$106,MATCH(B11,Реестр!$A$7:$A$106,0)),"Нет связи")) -> Менеджер 1 | M11: =IF(A11="","",IFERROR(INDEX(Реестр!$E$7:$E$106,MATCH(B11,Реестр!$A$7:$A$106,0)),"Нет связи")) -> Прямые | N11: =IF(AND(A11<>"",H11<>"Закрыто",L11<>"Нет связи"),IF(INDEX(Реестр!$V$7:$V$106,MATCH(B11,Реестр!$A$7:$A$106,0))="Закрыто",0,1),0) -> 1 | O11: =IF(N11=0,0,IF(F11="","Нет срока",MAX(0,(Продажи!$D$4-F11)*24))) -> 0 | P11: =IF(AND(N11=1,ISNUMBER(F11),F11<=Продажи!$D$4+2,OR(G11="Подача",G11="Дозапрос",G11="Обеспечение",G11="Обязательство клиенту")),1,0) -> 0 | Q11: =IF(AND(N11=1,D11="Продажи",ISNUMBER(O11),O11>0),1,0) -> 0 | R11: =IF(AND(N11=1,H11="Ожидание",D11<>"Продажи"),1,0) -> 0 | S11: =IF(AND(N11=1,OR(Продажи!$I$4="Все",L11=Продажи!$I$4),OR(Продажи!$O$4="Все",M11=Продажи!$O$4)),1,0) -> 1 | T11: =IF(S11=0,0,IF(P11=1,1,IF(AND(ISNUMBER(O11),O11>0),2,IF(AND(ISNUMBER(F11),INT(F11)=INT(Продажи!$D$4)),3,IF(OR(I11="Да",F11=""),4,0))))) -> 3 | U11: =IF(T11=0,"",COUNTIFS($T$7:$T$106,">0",$T$7:$T$106,"<"&T11)+COUNTIFS($T$7:$T$106,T11,$Y$7:$Y$106,"<"&Y11)+COUNTIFS($T$7:T11,T11,$Y$7:Y11,Y11)) -> 10 | V11: =IF(A11="","",IFERROR(INDEX(Реестр!$W$7:$W$106,MATCH(B11,Реестр!$A$7:$A$106,0)),"Нет связи")) -> Ведомость требований клиента | W11: =IF(A11="","",IFERROR(INDEX(Реестр!$C$7:$C$106,MATCH(B11,Реестр!$A$7:$A$106,0)),"Нет связи")) -> Компания Г | X11: =IF(AND(S11=1,I11="Да"),COUNTIFS($S$7:$S$106,1,$I$7:$I$106,"Да",$Y$7:$Y$106,"<"&Y11)+COUNTIFS($S$7:S11,1,$I$7:I11,"Да",$Y$7:Y11,Y11),"") | Y11: =IF(N11=1,IF(ISNUMBER(F11),F11,2958465),"") -> 46321.417
A12: Д-06 | B12: С-102 | C12: Получить сопоставимое КП завода | D12: Снабжение | E12: Снабженец | F12: 46319.667 | G12: Расчёт | H12: Ожидание | I12: Да | J12: Определить замену поставщика или согласовать перенос расчёта | L12: =IF(A12="","",IFERROR(INDEX(Реестр!$D$7:$D$106,MATCH(B12,Реестр!$A$7:$A$106,0)),"Нет связи")) -> Менеджер 2 | M12: =IF(A12="","",IFERROR(INDEX(Реестр!$E$7:$E$106,MATCH(B12,Реестр!$A$7:$A$106,0)),"Нет связи")) -> Прямые | N12: =IF(AND(A12<>"",H12<>"Закрыто",L12<>"Нет связи"),IF(INDEX(Реестр!$V$7:$V$106,MATCH(B12,Реестр!$A$7:$A$106,0))="Закрыто",0,1),0) -> 1 | O12: =IF(N12=0,0,IF(F12="","Нет срока",MAX(0,(Продажи!$D$4-F12)*24))) -> 41 | P12: =IF(AND(N12=1,ISNUMBER(F12),F12<=Продажи!$D$4+2,OR(G12="Подача",G12="Дозапрос",G12="Обеспечение",G12="Обязательство клиенту")),1,0) -> 0 | Q12: =IF(AND(N12=1,D12="Продажи",ISNUMBER(O12),O12>0),1,0) -> 0 | R12: =IF(AND(N12=1,H12="Ожидание",D12<>"Продажи"),1,0) -> 1 | S12: =IF(AND(N12=1,OR(Продажи!$I$4="Все",L12=Продажи!$I$4),OR(Продажи!$O$4="Все",M12=Продажи!$O$4)),1,0) -> 1 | T12: =IF(S12=0,0,IF(P12=1,1,IF(AND(ISNUMBER(O12),O12>0),2,IF(AND(ISNUMBER(F12),INT(F12)=INT(Продажи!$D$4)),3,IF(OR(I12="Да",F12=""),4,0))))) -> 2 | U12: =IF(T12=0,"",COUNTIFS($T$7:$T$106,">0",$T$7:$T$106,"<"&T12)+COUNTIFS($T$7:$T$106,T12,$Y$7:$Y$106,"<"&Y12)+COUNTIFS($T$7:T12,T12,$Y$7:Y12,Y12)) -> 5 | V12: =IF(A12="","",IFERROR(INDEX(Реестр!$W$7:$W$106,MATCH(B12,Реестр!$A$7:$A$106,0)),"Нет связи")) -> КП завода; цена продажи; | W12: =IF(A12="","",IFERROR(INDEX(Реестр!$C$7:$C$106,MATCH(B12,Реестр!$A$7:$A$106,0)),"Нет связи")) -> Компания Д | X12: =IF(AND(S12=1,I12="Да"),COUNTIFS($S$7:$S$106,1,$I$7:$I$106,"Да",$Y$7:$Y$106,"<"&Y12)+COUNTIFS($S$7:S12,1,$I$7:I12,"Да",$Y$7:Y12,Y12),"") -> 1 | Y12: =IF(N12=1,IF(ISNUMBER(F12),F12,2958465),"") -> 46319.667
A13: Д-07 | B13: С-103 | C13: Подтвердить ставку доставки | D13: Логистика | E13: Логист | F13: 46321.5 | G13: Расчёт | H13: Ожидание | I13: Нет | L13: =IF(A13="","",IFERROR(INDEX(Реестр!$D$7:$D$106,MATCH(B13,Реестр!$A$7:$A$106,0)),"Нет связи")) -> Тендерный специалист | M13: =IF(A13="","",IFERROR(INDEX(Реестр!$E$7:$E$106,MATCH(B13,Реестр!$A$7:$A$106,0)),"Нет связи")) -> Тендеры | N13: =IF(AND(A13<>"",H13<>"Закрыто",L13<>"Нет связи"),IF(INDEX(Реестр!$V$7:$V$106,MATCH(B13,Реестр!$A$7:$A$106,0))="Закрыто",0,1),0) -> 1 | O13: =IF(N13=0,0,IF(F13="","Нет срока",MAX(0,(Продажи!$D$4-F13)*24))) -> 0 | P13: =IF(AND(N13=1,ISNUMBER(F13),F13<=Продажи!$D$4+2,OR(G13="Подача",G13="Дозапрос",G13="Обеспечение",G13="Обязательство клиенту")),1,0) -> 0 | Q13: =IF(AND(N13=1,D13="Продажи",ISNUMBER(O13),O13>0),1,0) -> 0 | R13: =IF(AND(N13=1,H13="Ожидание",D13<>"Продажи"),1,0) -> 1 | S13: =IF(AND(N13=1,OR(Продажи!$I$4="Все",L13=Продажи!$I$4),OR(Продажи!$O$4="Все",M13=Продажи!$O$4)),1,0) -> 1 | T13: =IF(S13=0,0,IF(P13=1,1,IF(AND(ISNUMBER(O13),O13>0),2,IF(AND(ISNUMBER(F13),INT(F13)=INT(Продажи!$D$4)),3,IF(OR(I13="Да",F13=""),4,0))))) -> 3 | U13: =IF(T13=0,"",COUNTIFS($T$7:$T$106,">0",$T$7:$T$106,"<"&T13)+COUNTIFS($T$7:$T$106,T13,$Y$7:$Y$106,"<"&Y13)+COUNTIFS($T$7:T13,T13,$Y$7:Y13,Y13)) -> 12 | V13: =IF(A13="","",IFERROR(INDEX(Реестр!$W$7:$W$106,MATCH(B13,Реестр!$A$7:$A$106,0)),"Нет связи")) -> логистика; цена продажи; | W13: =IF(A13="","",IFERROR(INDEX(Реестр!$C$7:$C$106,MATCH(B13,Реестр!$A$7:$A$106,0)),"Нет связи")) -> Компания Е | X13: =IF(AND(S13=1,I13="Да"),COUNTIFS($S$7:$S$106,1,$I$7:$I$106,"Да",$Y$7:$Y$106,"<"&Y13)+COUNTIFS($S$7:S13,1,$I$7:I13,"Да",$Y$7:Y13,Y13),"") | Y13: =IF(N13=1,IF(ISNUMBER(F13),F13,2958465),"") -> 46321.5
A14: Д-08 | B14: С-103 | C14: Согласовать цену и решение участвовать | D14: Продажи | E14: Тендерный специалист | F14: 46321.583 | G14: Согласование | H14: Открыто | I14: Да | J14: Утвердить цену с учётом доставки и обеспечения | L14: =IF(A14="","",IFERROR(INDEX(Реестр!$D$7:$D$106,MATCH(B14,Реестр!$A$7:$A$106,0)),"Нет связи")) -> Тендерный специалист | M14: =IF(A14="","",IFERROR(INDEX(Реестр!$E$7:$E$106,MATCH(B14,Реестр!$A$7:$A$106,0)),"Нет связи")) -> Тендеры | N14: =IF(AND(A14<>"",H14<>"Закрыто",L14<>"Нет связи"),IF(INDEX(Реестр!$V$7:$V$106,MATCH(B14,Реестр!$A$7:$A$106,0))="Закрыто",0,1),0) -> 1 | O14: =IF(N14=0,0,IF(F14="","Нет срока",MAX(0,(Продажи!$D$4-F14)*24))) -> 0 | P14: =IF(AND(N14=1,ISNUMBER(F14),F14<=Продажи!$D$4+2,OR(G14="Подача",G14="Дозапрос",G14="Обеспечение",G14="Обязательство клиенту")),1,0) -> 0 | Q14: =IF(AND(N14=1,D14="Продажи",ISNUMBER(O14),O14>0),1,0) -> 0 | R14: =IF(AND(N14=1,H14="Ожидание",D14<>"Продажи"),1,0) -> 0 | S14: =IF(AND(N14=1,OR(Продажи!$I$4="Все",L14=Продажи!$I$4),OR(Продажи!$O$4="Все",M14=Продажи!$O$4)),1,0) -> 1 | T14: =IF(S14=0,0,IF(P14=1,1,IF(AND(ISNUMBER(O14),O14>0),2,IF(AND(ISNUMBER(F14),INT(F14)=INT(Продажи!$D$4)),3,IF(OR(I14="Да",F14=""),4,0))))) -> 3 | U14: =IF(T14=0,"",COUNTIFS($T$7:$T$106,">0",$T$7:$T$106,"<"&T14)+COUNTIFS($T$7:$T$106,T14,$Y$7:$Y$106,"<"&Y14)+COUNTIFS($T$7:T14,T14,$Y$7:Y14,Y14)) -> 14 | V14: =IF(A14="","",IFERROR(INDEX(Реестр!$W$7:$W$106,MATCH(B14,Реестр!$A$7:$A$106,0)),"Нет связи")) -> логистика; цена продажи; | W14: =IF(A14="","",IFERROR(INDEX(Реестр!$C$7:$C$106,MATCH(B14,Реестр!$A$7:$A$106,0)),"Нет связи")) -> Компания Е | X14: =IF(AND(S14=1,I14="Да"),COUNTIFS($S$7:$S$106,1,$I$7:$I$106,"Да",$Y$7:$Y$106,"<"&Y14)+COUNTIFS($S$7:S14,1,$I$7:I14,"Да",$Y$7:Y14,Y14),"") -> 4 | Y14: =IF(N14=1,IF(ISNUMBER(F14),F14,2958465),"") -> 46321.583
A15: Д-09 | B15: С-104 | C15: Получить ответ на КП | D15: Продажи | E15: Менеджер 1 | F15: 46321.625 | G15: Контакт | H15: Открыто | I15: Нет | L15: =IF(A15="","",IFERROR(INDEX(Реестр!$D$7:$D$106,MATCH(B15,Реестр!$A$7:$A$106,0)),"Нет связи")) -> Менеджер 1 | M15: =IF(A15="","",IFERROR(INDEX(Реестр!$E$7:$E$106,MATCH(B15,Реестр!$A$7:$A$106,0)),"Нет связи")) -> Прямые | N15: =IF(AND(A15<>"",H15<>"Закрыто",L15<>"Нет связи"),IF(INDEX(Реестр!$V$7:$V$106,MATCH(B15,Реестр!$A$7:$A$106,0))="Закрыто",0,1),0) -> 1 | O15: =IF(N15=0,0,IF(F15="","Нет срока",MAX(0,(Продажи!$D$4-F15)*24))) -> 0 | P15: =IF(AND(N15=1,ISNUMBER(F15),F15<=Продажи!$D$4+2,OR(G15="Подача",G15="Дозапрос",G15="Обеспечение",G15="Обязательство клиенту")),1,0) -> 0 | Q15: =IF(AND(N15=1,D15="Продажи",ISNUMBER(O15),O15>0),1,0) -> 0 | R15: =IF(AND(N15=1,H15="Ожидание",D15<>"Продажи"),1,0) -> 0 | S15: =IF(AND(N15=1,OR(Продажи!$I$4="Все",L15=Продажи!$I$4),OR(Продажи!$O$4="Все",M15=Продажи!$O$4)),1,0) -> 1 | T15: =IF(S15=0,0,IF(P15=1,1,IF(AND(ISNUMBER(O15),O15>0),2,IF(AND(ISNUMBER(F15),INT(F15)=INT(Продажи!$D$4)),3,IF(OR(I15="Да",F15=""),4,0))))) -> 3 | U15: =IF(T15=0,"",COUNTIFS($T$7:$T$106,">0",$T$7:$T$106,"<"&T15)+COUNTIFS($T$7:$T$106,T15,$Y$7:$Y$106,"<"&Y15)+COUNTIFS($T$7:T15,T15,$Y$7:Y15,Y15)) -> 15 | V15: =IF(A15="","",IFERROR(INDEX(Реестр!$W$7:$W$106,MATCH(B15,Реестр!$A$7:$A$106,0)),"Нет связи")) -> Ответ клиента на предложение | W15: =IF(A15="","",IFERROR(INDEX(Реестр!$C$7:$C$106,MATCH(B15,Реестр!$A$7:$A$106,0)),"Нет связи")) -> Компания Ж | X15: =IF(AND(S15=1,I15="Да"),COUNTIFS($S$7:$S$106,1,$I$7:$I$106,"Да",$Y$7:$Y$106,"<"&Y15)+COUNTIFS($S$7:S15,1,$I$7:I15,"Да",$Y$7:Y15,Y15),"") | Y15: =IF(N15=1,IF(ISNUMBER(F15),F15,2958465),"") -> 46321.625
A16: Д-10 | B16: С-106 | C16: Зафиксировать условия оплаты | D16: Продажи | E16: Менеджер 1 | F16: 46322.5 | G16: Согласование | H16: Открыто | I16: Нет | L16: =IF(A16="","",IFERROR(INDEX(Реестр!$D$7:$D$106,MATCH(B16,Реестр!$A$7:$A$106,0)),"Нет связи")) -> Менеджер 1 | M16: =IF(A16="","",IFERROR(INDEX(Реестр!$E$7:$E$106,MATCH(B16,Реестр!$A$7:$A$106,0)),"Нет связи")) -> Прямые | N16: =IF(AND(A16<>"",H16<>"Закрыто",L16<>"Нет связи"),IF(INDEX(Реестр!$V$7:$V$106,MATCH(B16,Реестр!$A$7:$A$106,0))="Закрыто",0,1),0) -> 1 | O16: =IF(N16=0,0,IF(F16="","Нет срока",MAX(0,(Продажи!$D$4-F16)*24))) -> 0 | P16: =IF(AND(N16=1,ISNUMBER(F16),F16<=Продажи!$D$4+2,OR(G16="Подача",G16="Дозапрос",G16="Обеспечение",G16="Обязательство клиенту")),1,0) -> 0 | Q16: =IF(AND(N16=1,D16="Продажи",ISNUMBER(O16),O16>0),1,0) -> 0 | R16: =IF(AND(N16=1,H16="Ожидание",D16<>"Продажи"),1,0) -> 0 | S16: =IF(AND(N16=1,OR(Продажи!$I$4="Все",L16=Продажи!$I$4),OR(Продажи!$O$4="Все",M16=Продажи!$O$4)),1,0) -> 1 | T16: =IF(S16=0,0,IF(P16=1,1,IF(AND(ISNUMBER(O16),O16>0),2,IF(AND(ISNUMBER(F16),INT(F16)=INT(Продажи!$D$4)),3,IF(OR(I16="Да",F16=""),4,0))))) -> 0 | U16: =IF(T16=0,"",COUNTIFS($T$7:$T$106,">0",$T$7:$T$106,"<"&T16)+COUNTIFS($T$7:$T$106,T16,$Y$7:$Y$106,"<"&Y16)+COUNTIFS($T$7:T16,T16,$Y$7:Y16,Y16)) | V16: =IF(A16="","",IFERROR(INDEX(Реестр!$W$7:$W$106,MATCH(B16,Реестр!$A$7:$A$106,0)),"Нет связи")) | W16: =IF(A16="","",IFERROR(INDEX(Реестр!$C$7:$C$106,MATCH(B16,Реестр!$A$7:$A$106,0)),"Нет связи")) -> Компания И | X16: =IF(AND(S16=1,I16="Да"),COUNTIFS($S$7:$S$106,1,$I$7:$I$106,"Да",$Y$7:$Y$106,"<"&Y16)+COUNTIFS($S$7:S16,1,$I$7:I16,"Да",$Y$7:Y16,Y16),"") | Y16: =IF(N16=1,IF(ISNUMBER(F16),F16,2958465),"") -> 46322.5
A17: Д-11 | B17: С-107 | C17: Подать ответ на технический дозапрос | D17: Продажи | E17: Тендерный специалист | F17: 46321.458 | G17: Дозапрос | H17: Открыто | I17: Нет | L17: =IF(A17="","",IFERROR(INDEX(Реестр!$D$7:$D$106,MATCH(B17,Реестр!$A$7:$A$106,0)),"Нет связи")) -> Тендерный специалист | M17: =IF(A17="","",IFERROR(INDEX(Реестр!$E$7:$E$106,MATCH(B17,Реестр!$A$7:$A$106,0)),"Нет связи")) -> Тендеры | N17: =IF(AND(A17<>"",H17<>"Закрыто",L17<>"Нет связи"),IF(INDEX(Реестр!$V$7:$V$106,MATCH(B17,Реестр!$A$7:$A$106,0))="Закрыто",0,1),0) -> 1 | O17: =IF(N17=0,0,IF(F17="","Нет срока",MAX(0,(Продажи!$D$4-F17)*24))) -> 0 | P17: =IF(AND(N17=1,ISNUMBER(F17),F17<=Продажи!$D$4+2,OR(G17="Подача",G17="Дозапрос",G17="Обеспечение",G17="Обязательство клиенту")),1,0) -> 1 | Q17: =IF(AND(N17=1,D17="Продажи",ISNUMBER(O17),O17>0),1,0) -> 0 | R17: =IF(AND(N17=1,H17="Ожидание",D17<>"Продажи"),1,0) -> 0 | S17: =IF(AND(N17=1,OR(Продажи!$I$4="Все",L17=Продажи!$I$4),OR(Продажи!$O$4="Все",M17=Продажи!$O$4)),1,0) -> 1 | T17: =IF(S17=0,0,IF(P17=1,1,IF(AND(ISNUMBER(O17),O17>0),2,IF(AND(ISNUMBER(F17),INT(F17)=INT(Продажи!$D$4)),3,IF(OR(I17="Да",F17=""),4,0))))) -> 1 | U17: =IF(T17=0,"",COUNTIFS($T$7:$T$106,">0",$T$7:$T$106,"<"&T17)+COUNTIFS($T$7:$T$106,T17,$Y$7:$Y$106,"<"&Y17)+COUNTIFS($T$7:T17,T17,$Y$7:Y17,Y17)) -> 1 | V17: =IF(A17="","",IFERROR(INDEX(Реестр!$W$7:$W$106,MATCH(B17,Реестр!$A$7:$A$106,0)),"Нет связи")) -> Принятый площадкой ответ | W17: =IF(A17="","",IFERROR(INDEX(Реестр!$C$7:$C$106,MATCH(B17,Реестр!$A$7:$A$106,0)),"Нет связи")) -> Компания К | X17: =IF(AND(S17=1,I17="Да"),COUNTIFS($S$7:$S$106,1,$I$7:$I$106,"Да",$Y$7:$Y$106,"<"&Y17)+COUNTIFS($S$7:S17,1,$I$7:I17,"Да",$Y$7:Y17,Y17),"") | Y17: =IF(N17=1,IF(ISNUMBER(F17),F17,2958465),"") -> 46321.458
A18: Д-12 | B18: С-108 | C18: Согласовать протокол разногласий | D18: Юрист | E18: Юрист | F18: 46320.625 | G18: Договор | H18: Ожидание | I18: Да | J18: Решить вопрос по ответственности и срокам договора | L18: =IF(A18="","",IFERROR(INDEX(Реестр!$D$7:$D$106,MATCH(B18,Реестр!$A$7:$A$106,0)),"Нет связи")) -> Менеджер 2 | M18: =IF(A18="","",IFERROR(INDEX(Реестр!$E$7:$E$106,MATCH(B18,Реестр!$A$7:$A$106,0)),"Нет связи")) -> Прямые | N18: =IF(AND(A18<>"",H18<>"Закрыто",L18<>"Нет связи"),IF(INDEX(Реестр!$V$7:$V$106,MATCH(B18,Реестр!$A$7:$A$106,0))="Закрыто",0,1),0) -> 1 | O18: =IF(N18=0,0,IF(F18="","Нет срока",MAX(0,(Продажи!$D$4-F18)*24))) -> 18 | P18: =IF(AND(N18=1,ISNUMBER(F18),F18<=Продажи!$D$4+2,OR(G18="Подача",G18="Дозапрос",G18="Обеспечение",G18="Обязательство клиенту")),1,0) -> 0 | Q18: =IF(AND(N18=1,D18="Продажи",ISNUMBER(O18),O18>0),1,0) -> 0 | R18: =IF(AND(N18=1,H18="Ожидание",D18<>"Продажи"),1,0) -> 1 | S18: =IF(AND(N18=1,OR(Продажи!$I$4="Все",L18=Продажи!$I$4),OR(Продажи!$O$4="Все",M18=Продажи!$O$4)),1,0) -> 1 | T18: =IF(S18=0,0,IF(P18=1,1,IF(AND(ISNUMBER(O18),O18>0),2,IF(AND(ISNUMBER(F18),INT(F18)=INT(Продажи!$D$4)),3,IF(OR(I18="Да",F18=""),4,0))))) -> 2 | U18: =IF(T18=0,"",COUNTIFS($T$7:$T$106,">0",$T$7:$T$106,"<"&T18)+COUNTIFS($T$7:$T$106,T18,$Y$7:$Y$106,"<"&Y18)+COUNTIFS($T$7:T18,T18,$Y$7:Y18,Y18)) -> 7 | V18: =IF(A18="","",IFERROR(INDEX(Реестр!$W$7:$W$106,MATCH(B18,Реестр!$A$7:$A$106,0)),"Нет связи")) -> Подписанные договор и спецификация | W18: =IF(A18="","",IFERROR(INDEX(Реестр!$C$7:$C$106,MATCH(B18,Реестр!$A$7:$A$106,0)),"Нет связи")) -> Компания Л | X18: =IF(AND(S18=1,I18="Да"),COUNTIFS($S$7:$S$106,1,$I$7:$I$106,"Да",$Y$7:$Y$106,"<"&Y18)+COUNTIFS($S$7:S18,1,$I$7:I18,"Да",$Y$7:Y18,Y18),"") -> 2 | Y18: =IF(N18=1,IF(ISNUMBER(F18),F18,2958465),"") -> 46320.625
A19: Д-13 | B19: С-109 | C19: Подать тендерную заявку | D19: Продажи | E19: Тендерный специалист | F19: 46322.5 | G19: Подача | H19: Открыто | I19: Нет | L19: =IF(A19="","",IFERROR(INDEX(Реестр!$D$7:$D$106,MATCH(B19,Реестр!$A$7:$A$106,0)),"Нет связи")) -> Тендерный специалист | M19: =IF(A19="","",IFERROR(INDEX(Реестр!$E$7:$E$106,MATCH(B19,Реестр!$A$7:$A$106,0)),"Нет связи")) -> Тендеры | N19: =IF(AND(A19<>"",H19<>"Закрыто",L19<>"Нет связи"),IF(INDEX(Реестр!$V$7:$V$106,MATCH(B19,Реестр!$A$7:$A$106,0))="Закрыто",0,1),0) -> 1 | O19: =IF(N19=0,0,IF(F19="","Нет срока",MAX(0,(Продажи!$D$4-F19)*24))) -> 0 | P19: =IF(AND(N19=1,ISNUMBER(F19),F19<=Продажи!$D$4+2,OR(G19="Подача",G19="Дозапрос",G19="Обеспечение",G19="Обязательство клиенту")),1,0) -> 1 | Q19: =IF(AND(N19=1,D19="Продажи",ISNUMBER(O19),O19>0),1,0) -> 0 | R19: =IF(AND(N19=1,H19="Ожидание",D19<>"Продажи"),1,0) -> 0 | S19: =IF(AND(N19=1,OR(Продажи!$I$4="Все",L19=Продажи!$I$4),OR(Продажи!$O$4="Все",M19=Продажи!$O$4)),1,0) -> 1 | T19: =IF(S19=0,0,IF(P19=1,1,IF(AND(ISNUMBER(O19),O19>0),2,IF(AND(ISNUMBER(F19),INT(F19)=INT(Продажи!$D$4)),3,IF(OR(I19="Да",F19=""),4,0))))) -> 1 | U19: =IF(T19=0,"",COUNTIFS($T$7:$T$106,">0",$T$7:$T$106,"<"&T19)+COUNTIFS($T$7:$T$106,T19,$Y$7:$Y$106,"<"&Y19)+COUNTIFS($T$7:T19,T19,$Y$7:Y19,Y19)) -> 4 | V19: =IF(A19="","",IFERROR(INDEX(Реестр!$W$7:$W$106,MATCH(B19,Реестр!$A$7:$A$106,0)),"Нет связи")) | W19: =IF(A19="","",IFERROR(INDEX(Реестр!$C$7:$C$106,MATCH(B19,Реестр!$A$7:$A$106,0)),"Нет связи")) -> Компания М | X19: =IF(AND(S19=1,I19="Да"),COUNTIFS($S$7:$S$106,1,$I$7:$I$106,"Да",$Y$7:$Y$106,"<"&Y19)+COUNTIFS($S$7:S19,1,$I$7:I19,"Да",$Y$7:Y19,Y19),"") | Y19: =IF(N19=1,IF(ISNUMBER(F19),F19,2958465),"") -> 46322.5
A20: Д-14 | B20: С-109 | C20: Подтвердить обеспечение заявки | D20: Финансы | E20: Финансовый блок | F20: 46321.667 | G20: Обеспечение | H20: Ожидание | I20: Нет | L20: =IF(A20="","",IFERROR(INDEX(Реестр!$D$7:$D$106,MATCH(B20,Реестр!$A$7:$A$106,0)),"Нет связи")) -> Тендерный специалист | M20: =IF(A20="","",IFERROR(INDEX(Реестр!$E$7:$E$106,MATCH(B20,Реестр!$A$7:$A$106,0)),"Нет связи")) -> Тендеры | N20: =IF(AND(A20<>"",H20<>"Закрыто",L20<>"Нет связи"),IF(INDEX(Реестр!$V$7:$V$106,MATCH(B20,Реестр!$A$7:$A$106,0))="Закрыто",0,1),0) -> 1 | O20: =IF(N20=0,0,IF(F20="","Нет срока",MAX(0,(Продажи!$D$4-F20)*24))) -> 0 | P20: =IF(AND(N20=1,ISNUMBER(F20),F20<=Продажи!$D$4+2,OR(G20="Подача",G20="Дозапрос",G20="Обеспечение",G20="Обязательство клиенту")),1,0) -> 1 | Q20: =IF(AND(N20=1,D20="Продажи",ISNUMBER(O20),O20>0),1,0) -> 0 | R20: =IF(AND(N20=1,H20="Ожидание",D20<>"Продажи"),1,0) -> 1 | S20: =IF(AND(N20=1,OR(Продажи!$I$4="Все",L20=Продажи!$I$4),OR(Продажи!$O$4="Все",M20=Продажи!$O$4)),1,0) -> 1 | T20: =IF(S20=0,0,IF(P20=1,1,IF(AND(ISNUMBER(O20),O20>0),2,IF(AND(ISNUMBER(F20),INT(F20)=INT(Продажи!$D$4)),3,IF(OR(I20="Да",F20=""),4,0))))) -> 1 | U20: =IF(T20=0,"",COUNTIFS($T$7:$T$106,">0",$T$7:$T$106,"<"&T20)+COUNTIFS($T$7:$T$106,T20,$Y$7:$Y$106,"<"&Y20)+COUNTIFS($T$7:T20,T20,$Y$7:Y20,Y20)) -> 3 | V20: =IF(A20="","",IFERROR(INDEX(Реестр!$W$7:$W$106,MATCH(B20,Реестр!$A$7:$A$106,0)),"Нет связи")) | W20: =IF(A20="","",IFERROR(INDEX(Реестр!$C$7:$C$106,MATCH(B20,Реестр!$A$7:$A$106,0)),"Нет связи")) -> Компания М | X20: =IF(AND(S20=1,I20="Да"),COUNTIFS($S$7:$S$106,1,$I$7:$I$106,"Да",$Y$7:$Y$106,"<"&Y20)+COUNTIFS($S$7:S20,1,$I$7:I20,"Да",$Y$7:Y20,Y20),"") | Y20: =IF(N20=1,IF(ISNUMBER(F20),F20,2958465),"") -> 46321.667
A21: Д-15 | B21: И-201 | C21: Подтвердить приём комплекта заказа | D21: Снабжение | E21: Снабженец | F21: 46321.5 | G21: Передача заказа | H21: Ожидание | I21: Нет | L21: =IF(A21="","",IFERROR(INDEX(Реестр!$D$7:$D$106,MATCH(B21,Реестр!$A$7:$A$106,0)),"Нет связи")) -> Менеджер 1 | M21: =IF(A21="","",IFERROR(INDEX(Реестр!$E$7:$E$106,MATCH(B21,Реестр!$A$7:$A$106,0)),"Нет связи")) -> Прямые | N21: =IF(AND(A21<>"",H21<>"Закрыто",L21<>"Нет связи"),IF(INDEX(Реестр!$V$7:$V$106,MATCH(B21,Реестр!$A$7:$A$106,0))="Закрыто",0,1),0) -> 1 | O21: =IF(N21=0,0,IF(F21="","Нет срока",MAX(0,(Продажи!$D$4-F21)*24))) -> 0 | P21: =IF(AND(N21=1,ISNUMBER(F21),F21<=Продажи!$D$4+2,OR(G21="Подача",G21="Дозапрос",G21="Обеспечение",G21="Обязательство клиенту")),1,0) -> 0 | Q21: =IF(AND(N21=1,D21="Продажи",ISNUMBER(O21),O21>0),1,0) -> 0 | R21: =IF(AND(N21=1,H21="Ожидание",D21<>"Продажи"),1,0) -> 1 | S21: =IF(AND(N21=1,OR(Продажи!$I$4="Все",L21=Продажи!$I$4),OR(Продажи!$O$4="Все",M21=Продажи!$O$4)),1,0) -> 1 | T21: =IF(S21=0,0,IF(P21=1,1,IF(AND(ISNUMBER(O21),O21>0),2,IF(AND(ISNUMBER(F21),INT(F21)=INT(Продажи!$D$4)),3,IF(OR(I21="Да",F21=""),4,0))))) -> 3 | U21: =IF(T21=0,"",COUNTIFS($T$7:$T$106,">0",$T$7:$T$106,"<"&T21)+COUNTIFS($T$7:$T$106,T21,$Y$7:$Y$106,"<"&Y21)+COUNTIFS($T$7:T21,T21,$Y$7:Y21,Y21)) -> 13 | V21: =IF(A21="","",IFERROR(INDEX(Реестр!$W$7:$W$106,MATCH(B21,Реестр!$A$7:$A$106,0)),"Нет связи")) -> Приём заказа смежниками | W21: =IF(A21="","",IFERROR(INDEX(Реестр!$C$7:$C$106,MATCH(B21,Реестр!$A$7:$A$106,0)),"Нет связи")) -> Компания Н / опоры | X21: =IF(AND(S21=1,I21="Да"),COUNTIFS($S$7:$S$106,1,$I$7:$I$106,"Да",$Y$7:$Y$106,"<"&Y21)+COUNTIFS($S$7:S21,1,$I$7:I21,"Да",$Y$7:Y21,Y21),"") | Y21: =IF(N21=1,IF(ISNUMBER(F21),F21,2958465),"") -> 46321.5
A22: Д-16 | B22: И-202 | C22: Согласовать изменённую дату с клиентом | D22: Продажи | E22: Менеджер 2 | F22: 46321.542 | G22: Обязательство клиенту | H22: Открыто | I22: Да | J22: Определить допустимое решение по переносу поставки | L22: =IF(A22="","",IFERROR(INDEX(Реестр!$D$7:$D$106,MATCH(B22,Реестр!$A$7:$A$106,0)),"Нет связи")) -> Менеджер 2 | M22: =IF(A22="","",IFERROR(INDEX(Реестр!$E$7:$E$106,MATCH(B22,Реестр!$A$7:$A$106,0)),"Нет связи")) -> Прямые | N22: =IF(AND(A22<>"",H22<>"Закрыто",L22<>"Нет связи"),IF(INDEX(Реестр!$V$7:$V$106,MATCH(B22,Реестр!$A$7:$A$106,0))="Закрыто",0,1),0) -> 1 | O22: =IF(N22=0,0,IF(F22="","Нет срока",MAX(0,(Продажи!$D$4-F22)*24))) -> 0 | P22: =IF(AND(N22=1,ISNUMBER(F22),F22<=Продажи!$D$4+2,OR(G22="Подача",G22="Дозапрос",G22="Обеспечение",G22="Обязательство клиенту")),1,0) -> 1 | Q22: =IF(AND(N22=1,D22="Продажи",ISNUMBER(O22),O22>0),1,0) -> 0 | R22: =IF(AND(N22=1,H22="Ожидание",D22<>"Продажи"),1,0) -> 0 | S22: =IF(AND(N22=1,OR(Продажи!$I$4="Все",L22=Продажи!$I$4),OR(Продажи!$O$4="Все",M22=Продажи!$O$4)),1,0) -> 1 | T22: =IF(S22=0,0,IF(P22=1,1,IF(AND(ISNUMBER(O22),O22>0),2,IF(AND(ISNUMBER(F22),INT(F22)=INT(Продажи!$D$4)),3,IF(OR(I22="Да",F22=""),4,0))))) -> 1 | U22: =IF(T22=0,"",COUNTIFS($T$7:$T$106,">0",$T$7:$T$106,"<"&T22)+COUNTIFS($T$7:$T$106,T22,$Y$7:$Y$106,"<"&Y22)+COUNTIFS($T$7:T22,T22,$Y$7:Y22,Y22)) -> 2 | V22: =IF(A22="","",IFERROR(INDEX(Реестр!$W$7:$W$106,MATCH(B22,Реестр!$A$7:$A$106,0)),"Нет связи")) -> Согласованы изменения и сроки клиента | W22: =IF(A22="","",IFERROR(INDEX(Реестр!$C$7:$C$106,MATCH(B22,Реестр!$A$7:$A$106,0)),"Нет связи")) -> Компания О / металлоконструкции | X22: =IF(AND(S22=1,I22="Да"),COUNTIFS($S$7:$S$106,1,$I$7:$I$106,"Да",$Y$7:$Y$106,"<"&Y22)+COUNTIFS($S$7:S22,1,$I$7:I22,"Да",$Y$7:Y22,Y22),"") -> 3 | Y22: =IF(N22=1,IF(ISNUMBER(F22),F22,2958465),"") -> 46321.542
A23: Д-17 | B23: И-203 | C23: Получить подтверждение приёмки | D23: Клиент | E23: Ответственный клиента | F23: 46322.708 | G23: Документы | H23: Ожидание | I23: Нет | L23: =IF(A23="","",IFERROR(INDEX(Реестр!$D$7:$D$106,MATCH(B23,Реестр!$A$7:$A$106,0)),"Нет связи")) -> Тендерный специалист | M23: =IF(A23="","",IFERROR(INDEX(Реестр!$E$7:$E$106,MATCH(B23,Реестр!$A$7:$A$106,0)),"Нет связи")) -> Тендеры | N23: =IF(AND(A23<>"",H23<>"Закрыто",L23<>"Нет связи"),IF(INDEX(Реестр!$V$7:$V$106,MATCH(B23,Реестр!$A$7:$A$106,0))="Закрыто",0,1),0) -> 1 | O23: =IF(N23=0,0,IF(F23="","Нет срока",MAX(0,(Продажи!$D$4-F23)*24))) -> 0 | P23: =IF(AND(N23=1,ISNUMBER(F23),F23<=Продажи!$D$4+2,OR(G23="Подача",G23="Дозапрос",G23="Обеспечение",G23="Обязательство клиенту")),1,0) -> 0 | Q23: =IF(AND(N23=1,D23="Продажи",ISNUMBER(O23),O23>0),1,0) -> 0 | R23: =IF(AND(N23=1,H23="Ожидание",D23<>"Продажи"),1,0) -> 1 | S23: =IF(AND(N23=1,OR(Продажи!$I$4="Все",L23=Продажи!$I$4),OR(Продажи!$O$4="Все",M23=Продажи!$O$4)),1,0) -> 1 | T23: =IF(S23=0,0,IF(P23=1,1,IF(AND(ISNUMBER(O23),O23>0),2,IF(AND(ISNUMBER(F23),INT(F23)=INT(Продажи!$D$4)),3,IF(OR(I23="Да",F23=""),4,0))))) -> 0 | U23: =IF(T23=0,"",COUNTIFS($T$7:$T$106,">0",$T$7:$T$106,"<"&T23)+COUNTIFS($T$7:$T$106,T23,$Y$7:$Y$106,"<"&Y23)+COUNTIFS($T$7:T23,T23,$Y$7:Y23,Y23)) | V23: =IF(A23="","",IFERROR(INDEX(Реестр!$W$7:$W$106,MATCH(B23,Реестр!$A$7:$A$106,0)),"Нет связи")) -> Подтверждение приёмки; Оплата клиента | W23: =IF(A23="","",IFERROR(INDEX(Реестр!$C$7:$C$106,MATCH(B23,Реестр!$A$7:$A$106,0)),"Нет связи")) -> Компания П / покрытие | X23: =IF(AND(S23=1,I23="Да"),COUNTIFS($S$7:$S$106,1,$I$7:$I$106,"Да",$Y$7:$Y$106,"<"&Y23)+COUNTIFS($S$7:S23,1,$I$7:I23,"Да",$Y$7:Y23,Y23),"") | Y23: =IF(N23=1,IF(ISNUMBER(F23),F23,2958465),"") -> 46322.708
A24: Д-18 | B24: И-203 | C24: Согласовать дату погашения долга | D24: Продажи | E24: Тендерный специалист | F24: 46320.583 | G24: Оплата | H24: Открыто | I24: Нет | L24: =IF(A24="","",IFERROR(INDEX(Реестр!$D$7:$D$106,MATCH(B24,Реестр!$A$7:$A$106,0)),"Нет связи")) -> Тендерный специалист | M24: =IF(A24="","",IFERROR(INDEX(Реестр!$E$7:$E$106,MATCH(B24,Реестр!$A$7:$A$106,0)),"Нет связи")) -> Тендеры | N24: =IF(AND(A24<>"",H24<>"Закрыто",L24<>"Нет связи"),IF(INDEX(Реестр!$V$7:$V$106,MATCH(B24,Реестр!$A$7:$A$106,0))="Закрыто",0,1),0) -> 1 | O24: =IF(N24=0,0,IF(F24="","Нет срока",MAX(0,(Продажи!$D$4-F24)*24))) -> 19 | P24: =IF(AND(N24=1,ISNUMBER(F24),F24<=Продажи!$D$4+2,OR(G24="Подача",G24="Дозапрос",G24="Обеспечение",G24="Обязательство клиенту")),1,0) -> 0 | Q24: =IF(AND(N24=1,D24="Продажи",ISNUMBER(O24),O24>0),1,0) -> 1 | R24: =IF(AND(N24=1,H24="Ожидание",D24<>"Продажи"),1,0) -> 0 | S24: =IF(AND(N24=1,OR(Продажи!$I$4="Все",L24=Продажи!$I$4),OR(Продажи!$O$4="Все",M24=Продажи!$O$4)),1,0) -> 1 | T24: =IF(S24=0,0,IF(P24=1,1,IF(AND(ISNUMBER(O24),O24>0),2,IF(AND(ISNUMBER(F24),INT(F24)=INT(Продажи!$D$4)),3,IF(OR(I24="Да",F24=""),4,0))))) -> 2 | U24: =IF(T24=0,"",COUNTIFS($T$7:$T$106,">0",$T$7:$T$106,"<"&T24)+COUNTIFS($T$7:$T$106,T24,$Y$7:$Y$106,"<"&Y24)+COUNTIFS($T$7:T24,T24,$Y$7:Y24,Y24)) -> 6 | V24: =IF(A24="","",IFERROR(INDEX(Реестр!$W$7:$W$106,MATCH(B24,Реестр!$A$7:$A$106,0)),"Нет связи")) -> Подтверждение приёмки; Оплата клиента | W24: =IF(A24="","",IFERROR(INDEX(Реестр!$C$7:$C$106,MATCH(B24,Реестр!$A$7:$A$106,0)),"Нет связи")) -> Компания П / покрытие | X24: =IF(AND(S24=1,I24="Да"),COUNTIFS($S$7:$S$106,1,$I$7:$I$106,"Да",$Y$7:$Y$106,"<"&Y24)+COUNTIFS($S$7:S24,1,$I$7:I24,"Да",$Y$7:Y24,Y24),"") | Y24: =IF(N24=1,IF(ISNUMBER(F24),F24,2958465),"") -> 46320.583
L25: =IF(A25="","",IFERROR(INDEX(Реестр!$D$7:$D$106,MATCH(B25,Реестр!$A$7:$A$106,0)),"Нет связи")) | M25: =IF(A25="","",IFERROR(INDEX(Реестр!$E$7:$E$106,MATCH(B25,Реестр!$A$7:$A$106,0)),"Нет связи")) | N25: =IF(AND(A25<>"",H25<>"Закрыто",L25<>"Нет связи"),IF(INDEX(Реестр!$V$7:$V$106,MATCH(B25,Реестр!$A$7:$A$106,0))="Закрыто",0,1),0) -> 0 | O25: =IF(N25=0,0,IF(F25="","Нет срока",MAX(0,(Продажи!$D$4-F25)*24))) -> 0 | P25: =IF(AND(N25=1,ISNUMBER(F25),F25<=Продажи!$D$4+2,OR(G25="Подача",G25="Дозапрос",G25="Обеспечение",G25="Обязательство клиенту")),1,0) -> 0 | Q25: =IF(AND(N25=1,D25="Продажи",ISNUMBER(O25),O25>0),1,0) -> 0 | R25: =IF(AND(N25=1,H25="Ожидание",D25<>"Продажи"),1,0) -> 0 | S25: =IF(AND(N25=1,OR(Продажи!$I$4="Все",L25=Продажи!$I$4),OR(Продажи!$O$4="Все",M25=Продажи!$O$4)),1,0) -> 0 | T25: =IF(S25=0,0,IF(P25=1,1,IF(AND(ISNUMBER(O25),O25>0),2,IF(AND(ISNUMBER(F25),INT(F25)=INT(Продажи!$D$4)),3,IF(OR(I25="Да",F25=""),4,0))))) -> 0 | U25: =IF(T25=0,"",COUNTIFS($T$7:$T$106,">0",$T$7:$T$106,"<"&T25)+COUNTIFS($T$7:$T$106,T25,$Y$7:$Y$106,"<"&Y25)+COUNTIFS($T$7:T25,T25,$Y$7:Y25,Y25)) | V25: =IF(A25="","",IFERROR(INDEX(Реестр!$W$7:$W$106,MATCH(B25,Реестр!$A$7:$A$106,0)),"Нет связи")) | W25: =IF(A25="","",IFERROR(INDEX(Реестр!$C$7:$C$106,MATCH(B25,Реестр!$A$7:$A$106,0)),"Нет связи")) | X25: =IF(AND(S25=1,I25="Да"),COUNTIFS($S$7:$S$106,1,$I$7:$I$106,"Да",$Y$7:$Y$106,"<"&Y25)+COUNTIFS($S$7:S25,1,$I$7:I25,"Да",$Y$7:Y25,Y25),"") | Y25: =IF(N25=1,IF(ISNUMBER(F25),F25,2958465),"")
L26: =IF(A26="","",IFERROR(INDEX(Реестр!$D$7:$D$106,MATCH(B26,Реестр!$A$7:$A$106,0)),"Нет связи")) | M26: =IF(A26="","",IFERROR(INDEX(Реестр!$E$7:$E$106,MATCH(B26,Реестр!$A$7:$A$106,0)),"Нет связи")) | N26: =IF(AND(A26<>"",H26<>"Закрыто",L26<>"Нет связи"),IF(INDEX(Реестр!$V$7:$V$106,MATCH(B26,Реестр!$A$7:$A$106,0))="Закрыто",0,1),0) -> 0 | O26: =IF(N26=0,0,IF(F26="","Нет срока",MAX(0,(Продажи!$D$4-F26)*24))) -> 0 | P26: =IF(AND(N26=1,ISNUMBER(F26),F26<=Продажи!$D$4+2,OR(G26="Подача",G26="Дозапрос",G26="Обеспечение",G26="Обязательство клиенту")),1,0) -> 0 | Q26: =IF(AND(N26=1,D26="Продажи",ISNUMBER(O26),O26>0),1,0) -> 0 | R26: =IF(AND(N26=1,H26="Ожидание",D26<>"Продажи"),1,0) -> 0 | S26: =IF(AND(N26=1,OR(Продажи!$I$4="Все",L26=Продажи!$I$4),OR(Продажи!$O$4="Все",M26=Продажи!$O$4)),1,0) -> 0 | T26: =IF(S26=0,0,IF(P26=1,1,IF(AND(ISNUMBER(O26),O26>0),2,IF(AND(ISNUMBER(F26),INT(F26)=INT(Продажи!$D$4)),3,IF(OR(I26="Да",F26=""),4,0))))) -> 0 | U26: =IF(T26=0,"",COUNTIFS($T$7:$T$106,">0",$T$7:$T$106,"<"&T26)+COUNTIFS($T$7:$T$106,T26,$Y$7:$Y$106,"<"&Y26)+COUNTIFS($T$7:T26,T26,$Y$7:Y26,Y26)) | V26: =IF(A26="","",IFERROR(INDEX(Реестр!$W$7:$W$106,MATCH(B26,Реестр!$A$7:$A$106,0)),"Нет связи")) | W26: =IF(A26="","",IFERROR(INDEX(Реестр!$C$7:$C$106,MATCH(B26,Реестр!$A$7:$A$106,0)),"Нет связи")) | X26: =IF(AND(S26=1,I26="Да"),COUNTIFS($S$7:$S$106,1,$I$7:$I$106,"Да",$Y$7:$Y$106,"<"&Y26)+COUNTIFS($S$7:S26,1,$I$7:I26,"Да",$Y$7:Y26,Y26),"") | Y26: =IF(N26=1,IF(ISNUMBER(F26),F26,2958465),"")
L27: =IF(A27="","",IFERROR(INDEX(Реестр!$D$7:$D$106,MATCH(B27,Реестр!$A$7:$A$106,0)),"Нет связи")) | M27: =IF(A27="","",IFERROR(INDEX(Реестр!$E$7:$E$106,MATCH(B27,Реестр!$A$7:$A$106,0)),"Нет связи")) | N27: =IF(AND(A27<>"",H27<>"Закрыто",L27<>"Нет связи"),IF(INDEX(Реестр!$V$7:$V$106,MATCH(B27,Реестр!$A$7:$A$106,0))="Закрыто",0,1),0) -> 0 | O27: =IF(N27=0,0,IF(F27="","Нет срока",MAX(0,(Продажи!$D$4-F27)*24))) -> 0 | P27: =IF(AND(N27=1,ISNUMBER(F27),F27<=Продажи!$D$4+2,OR(G27="Подача",G27="Дозапрос",G27="Обеспечение",G27="Обязательство клиенту")),1,0) -> 0 | Q27: =IF(AND(N27=1,D27="Продажи",ISNUMBER(O27),O27>0),1,0) -> 0 | R27: =IF(AND(N27=1,H27="Ожидание",D27<>"Продажи"),1,0) -> 0 | S27: =IF(AND(N27=1,OR(Продажи!$I$4="Все",L27=Продажи!$I$4),OR(Продажи!$O$4="Все",M27=Продажи!$O$4)),1,0) -> 0 | T27: =IF(S27=0,0,IF(P27=1,1,IF(AND(ISNUMBER(O27),O27>0),2,IF(AND(ISNUMBER(F27),INT(F27)=INT(Продажи!$D$4)),3,IF(OR(I27="Да",F27=""),4,0))))) -> 0 | U27: =IF(T27=0,"",COUNTIFS($T$7:$T$106,">0",$T$7:$T$106,"<"&T27)+COUNTIFS($T$7:$T$106,T27,$Y$7:$Y$106,"<"&Y27)+COUNTIFS($T$7:T27,T27,$Y$7:Y27,Y27)) | V27: =IF(A27="","",IFERROR(INDEX(Реестр!$W$7:$W$106,MATCH(B27,Реестр!$A$7:$A$106,0)),"Нет связи")) | W27: =IF(A27="","",IFERROR(INDEX(Реестр!$C$7:$C$106,MATCH(B27,Реестр!$A$7:$A$106,0)),"Нет связи")) | X27: =IF(AND(S27=1,I27="Да"),COUNTIFS($S$7:$S$106,1,$I$7:$I$106,"Да",$Y$7:$Y$106,"<"&Y27)+COUNTIFS($S$7:S27,1,$I$7:I27,"Да",$Y$7:Y27,Y27),"") | Y27: =IF(N27=1,IF(ISNUMBER(F27),F27,2958465),"")
L28: =IF(A28="","",IFERROR(INDEX(Реестр!$D$7:$D$106,MATCH(B28,Реестр!$A$7:$A$106,0)),"Нет связи")) | M28: =IF(A28="","",IFERROR(INDEX(Реестр!$E$7:$E$106,MATCH(B28,Реестр!$A$7:$A$106,0)),"Нет связи")) | N28: =IF(AND(A28<>"",H28<>"Закрыто",L28<>"Нет связи"),IF(INDEX(Реестр!$V$7:$V$106,MATCH(B28,Реестр!$A$7:$A$106,0))="Закрыто",0,1),0) -> 0 | O28: =IF(N28=0,0,IF(F28="","Нет срока",MAX(0,(Продажи!$D$4-F28)*24))) -> 0 | P28: =IF(AND(N28=1,ISNUMBER(F28),F28<=Продажи!$D$4+2,OR(G28="Подача",G28="Дозапрос",G28="Обеспечение",G28="Обязательство клиенту")),1,0) -> 0 | Q28: =IF(AND(N28=1,D28="Продажи",ISNUMBER(O28),O28>0),1,0) -> 0 | R28: =IF(AND(N28=1,H28="Ожидание",D28<>"Продажи"),1,0) -> 0 | S28: =IF(AND(N28=1,OR(Продажи!$I$4="Все",L28=Продажи!$I$4),OR(Продажи!$O$4="Все",M28=Продажи!$O$4)),1,0) -> 0 | T28: =IF(S28=0,0,IF(P28=1,1,IF(AND(ISNUMBER(O28),O28>0),2,IF(AND(ISNUMBER(F28),INT(F28)=INT(Продажи!$D$4)),3,IF(OR(I28="Да",F28=""),4,0))))) -> 0 | U28: =IF(T28=0,"",COUNTIFS($T$7:$T$106,">0",$T$7:$T$106,"<"&T28)+COUNTIFS($T$7:$T$106,T28,$Y$7:$Y$106,"<"&Y28)+COUNTIFS($T$7:T28,T28,$Y$7:Y28,Y28)) | V28: =IF(A28="","",IFERROR(INDEX(Реестр!$W$7:$W$106,MATCH(B28,Реестр!$A$7:$A$106,0)),"Нет связи")) | W28: =IF(A28="","",IFERROR(INDEX(Реестр!$C$7:$C$106,MATCH(B28,Реестр!$A$7:$A$106,0)),"Нет связи")) | X28: =IF(AND(S28=1,I28="Да"),COUNTIFS($S$7:$S$106,1,$I$7:$I$106,"Да",$Y$7:$Y$106,"<"&Y28)+COUNTIFS($S$7:S28,1,$I$7:I28,"Да",$Y$7:Y28,Y28),"") | Y28: =IF(N28=1,IF(ISNUMBER(F28),F28,2958465),"")
L29: =IF(A29="","",IFERROR(INDEX(Реестр!$D$7:$D$106,MATCH(B29,Реестр!$A$7:$A$106,0)),"Нет связи")) | M29: =IF(A29="","",IFERROR(INDEX(Реестр!$E$7:$E$106,MATCH(B29,Реестр!$A$7:$A$106,0)),"Нет связи")) | N29: =IF(AND(A29<>"",H29<>"Закрыто",L29<>"Нет связи"),IF(INDEX(Реестр!$V$7:$V$106,MATCH(B29,Реестр!$A$7:$A$106,0))="Закрыто",0,1),0) -> 0 | O29: =IF(N29=0,0,IF(F29="","Нет срока",MAX(0,(Продажи!$D$4-F29)*24))) -> 0 | P29: =IF(AND(N29=1,ISNUMBER(F29),F29<=Продажи!$D$4+2,OR(G29="Подача",G29="Дозапрос",G29="Обеспечение",G29="Обязательство клиенту")),1,0) -> 0 | Q29: =IF(AND(N29=1,D29="Продажи",ISNUMBER(O29),O29>0),1,0) -> 0 | R29: =IF(AND(N29=1,H29="Ожидание",D29<>"Продажи"),1,0) -> 0 | S29: =IF(AND(N29=1,OR(Продажи!$I$4="Все",L29=Продажи!$I$4),OR(Продажи!$O$4="Все",M29=Продажи!$O$4)),1,0) -> 0 | T29: =IF(S29=0,0,IF(P29=1,1,IF(AND(ISNUMBER(O29),O29>0),2,IF(AND(ISNUMBER(F29),INT(F29)=INT(Продажи!$D$4)),3,IF(OR(I29="Да",F29=""),4,0))))) -> 0 | U29: =IF(T29=0,"",COUNTIFS($T$7:$T$106,">0",$T$7:$T$106,"<"&T29)+COUNTIFS($T$7:$T$106,T29,$Y$7:$Y$106,"<"&Y29)+COUNTIFS($T$7:T29,T29,$Y$7:Y29,Y29)) | V29: =IF(A29="","",IFERROR(INDEX(Реестр!$W$7:$W$106,MATCH(B29,Реестр!$A$7:$A$106,0)),"Нет связи")) | W29: =IF(A29="","",IFERROR(INDEX(Реестр!$C$7:$C$106,MATCH(B29,Реестр!$A$7:$A$106,0)),"Нет связи")) | X29: =IF(AND(S29=1,I29="Да"),COUNTIFS($S$7:$S$106,1,$I$7:$I$106,"Да",$Y$7:$Y$106,"<"&Y29)+COUNTIFS($S$7:S29,1,$I$7:I29,"Да",$Y$7:Y29,Y29),"") | Y29: =IF(N29=1,IF(ISNUMBER(F29),F29,2958465),"")
L30: =IF(A30="","",IFERROR(INDEX(Реестр!$D$7:$D$106,MATCH(B30,Реестр!$A$7:$A$106,0)),"Нет связи")) | M30: =IF(A30="","",IFERROR(INDEX(Реестр!$E$7:$E$106,MATCH(B30,Реестр!$A$7:$A$106,0)),"Нет связи")) | N30: =IF(AND(A30<>"",H30<>"Закрыто",L30<>"Нет связи"),IF(INDEX(Реестр!$V$7:$V$106,MATCH(B30,Реестр!$A$7:$A$106,0))="Закрыто",0,1),0) -> 0 | O30: =IF(N30=0,0,IF(F30="","Нет срока",MAX(0,(Продажи!$D$4-F30)*24))) -> 0 | P30: =IF(AND(N30=1,ISNUMBER(F30),F30<=Продажи!$D$4+2,OR(G30="Подача",G30="Дозапрос",G30="Обеспечение",G30="Обязательство клиенту")),1,0) -> 0 | Q30: =IF(AND(N30=1,D30="Продажи",ISNUMBER(O30),O30>0),1,0) -> 0 | R30: =IF(AND(N30=1,H30="Ожидание",D30<>"Продажи"),1,0) -> 0 | S30: =IF(AND(N30=1,OR(Продажи!$I$4="Все",L30=Продажи!$I$4),OR(Продажи!$O$4="Все",M30=Продажи!$O$4)),1,0) -> 0 | T30: =IF(S30=0,0,IF(P30=1,1,IF(AND(ISNUMBER(O30),O30>0),2,IF(AND(ISNUMBER(F30),INT(F30)=INT(Продажи!$D$4)),3,IF(OR(I30="Да",F30=""),4,0))))) -> 0 | U30: =IF(T30=0,"",COUNTIFS($T$7:$T$106,">0",$T$7:$T$106,"<"&T30)+COUNTIFS($T$7:$T$106,T30,$Y$7:$Y$106,"<"&Y30)+COUNTIFS($T$7:T30,T30,$Y$7:Y30,Y30)) | V30: =IF(A30="","",IFERROR(INDEX(Реестр!$W$7:$W$106,MATCH(B30,Реестр!$A$7:$A$106,0)),"Нет связи")) | W30: =IF(A30="","",IFERROR(INDEX(Реестр!$C$7:$C$106,MATCH(B30,Реестр!$A$7:$A$106,0)),"Нет связи")) | X30: =IF(AND(S30=1,I30="Да"),COUNTIFS($S$7:$S$106,1,$I$7:$I$106,"Да",$Y$7:$Y$106,"<"&Y30)+COUNTIFS($S$7:S30,1,$I$7:I30,"Да",$Y$7:Y30,Y30),"") | Y30: =IF(N30=1,IF(ISNUMBER(F30),F30,2958465),"")
L31: =IF(A31="","",IFERROR(INDEX(Реестр!$D$7:$D$106,MATCH(B31,Реестр!$A$7:$A$106,0)),"Нет связи")) | M31: =IF(A31="","",IFERROR(INDEX(Реестр!$E$7:$E$106,MATCH(B31,Реестр!$A$7:$A$106,0)),"Нет связи")) | N31: =IF(AND(A31<>"",H31<>"Закрыто",L31<>"Нет связи"),IF(INDEX(Реестр!$V$7:$V$106,MATCH(B31,Реестр!$A$7:$A$106,0))="Закрыто",0,1),0) -> 0 | O31: =IF(N31=0,0,IF(F31="","Нет срока",MAX(0,(Продажи!$D$4-F31)*24))) -> 0 | P31: =IF(AND(N31=1,ISNUMBER(F31),F31<=Продажи!$D$4+2,OR(G31="Подача",G31="Дозапрос",G31="Обеспечение",G31="Обязательство клиенту")),1,0) -> 0 | Q31: =IF(AND(N31=1,D31="Продажи",ISNUMBER(O31),O31>0),1,0) -> 0 | R31: =IF(AND(N31=1,H31="Ожидание",D31<>"Продажи"),1,0) -> 0 | S31: =IF(AND(N31=1,OR(Продажи!$I$4="Все",L31=Продажи!$I$4),OR(Продажи!$O$4="Все",M31=Продажи!$O$4)),1,0) -> 0 | T31: =IF(S31=0,0,IF(P31=1,1,IF(AND(ISNUMBER(O31),O31>0),2,IF(AND(ISNUMBER(F31),INT(F31)=INT(Продажи!$D$4)),3,IF(OR(I31="Да",F31=""),4,0))))) -> 0 | U31: =IF(T31=0,"",COUNTIFS($T$7:$T$106,">0",$T$7:$T$106,"<"&T31)+COUNTIFS($T$7:$T$106,T31,$Y$7:$Y$106,"<"&Y31)+COUNTIFS($T$7:T31,T31,$Y$7:Y31,Y31)) | V31: =IF(A31="","",IFERROR(INDEX(Реестр!$W$7:$W$106,MATCH(B31,Реестр!$A$7:$A$106,0)),"Нет связи")) | W31: =IF(A31="","",IFERROR(INDEX(Реестр!$C$7:$C$106,MATCH(B31,Реестр!$A$7:$A$106,0)),"Нет связи")) | X31: =IF(AND(S31=1,I31="Да"),COUNTIFS($S$7:$S$106,1,$I$7:$I$106,"Да",$Y$7:$Y$106,"<"&Y31)+COUNTIFS($S$7:S31,1,$I$7:I31,"Да",$Y$7:Y31,Y31),"") | Y31: =IF(N31=1,IF(ISNUMBER(F31),F31,2958465),"")
L32: =IF(A32="","",IFERROR(INDEX(Реестр!$D$7:$D$106,MATCH(B32,Реестр!$A$7:$A$106,0)),"Нет связи")) | M32: =IF(A32="","",IFERROR(INDEX(Реестр!$E$7:$E$106,MATCH(B32,Реестр!$A$7:$A$106,0)),"Нет связи")) | N32: =IF(AND(A32<>"",H32<>"Закрыто",L32<>"Нет связи"),IF(INDEX(Реестр!$V$7:$V$106,MATCH(B32,Реестр!$A$7:$A$106,0))="Закрыто",0,1),0) -> 0 | O32: =IF(N32=0,0,IF(F32="","Нет срока",MAX(0,(Продажи!$D$4-F32)*24))) -> 0 | P32: =IF(AND(N32=1,ISNUMBER(F32),F32<=Продажи!$D$4+2,OR(G32="Подача",G32="Дозапрос",G32="Обеспечение",G32="Обязательство клиенту")),1,0) -> 0 | Q32: =IF(AND(N32=1,D32="Продажи",ISNUMBER(O32),O32>0),1,0) -> 0 | R32: =IF(AND(N32=1,H32="Ожидание",D32<>"Продажи"),1,0) -> 0 | S32: =IF(AND(N32=1,OR(Продажи!$I$4="Все",L32=Продажи!$I$4),OR(Продажи!$O$4="Все",M32=Продажи!$O$4)),1,0) -> 0 | T32: =IF(S32=0,0,IF(P32=1,1,IF(AND(ISNUMBER(O32),O32>0),2,IF(AND(ISNUMBER(F32),INT(F32)=INT(Продажи!$D$4)),3,IF(OR(I32="Да",F32=""),4,0))))) -> 0 | U32: =IF(T32=0,"",COUNTIFS($T$7:$T$106,">0",$T$7:$T$106,"<"&T32)+COUNTIFS($T$7:$T$106,T32,$Y$7:$Y$106,"<"&Y32)+COUNTIFS($T$7:T32,T32,$Y$7:Y32,Y32)) | V32: =IF(A32="","",IFERROR(INDEX(Реестр!$W$7:$W$106,MATCH(B32,Реестр!$A$7:$A$106,0)),"Нет связи")) | W32: =IF(A32="","",IFERROR(INDEX(Реестр!$C$7:$C$106,MATCH(B32,Реестр!$A$7:$A$106,0)),"Нет связи")) | X32: =IF(AND(S32=1,I32="Да"),COUNTIFS($S$7:$S$106,1,$I$7:$I$106,"Да",$Y$7:$Y$106,"<"&Y32)+COUNTIFS($S$7:S32,1,$I$7:I32,"Да",$Y$7:Y32,Y32),"") | Y32: =IF(N32=1,IF(ISNUMBER(F32),F32,2958465),"")
L33: =IF(A33="","",IFERROR(INDEX(Реестр!$D$7:$D$106,MATCH(B33,Реестр!$A$7:$A$106,0)),"Нет связи")) | M33: =IF(A33="","",IFERROR(INDEX(Реестр!$E$7:$E$106,MATCH(B33,Реестр!$A$7:$A$106,0)),"Нет связи")) | N33: =IF(AND(A33<>"",H33<>"Закрыто",L33<>"Нет связи"),IF(INDEX(Реестр!$V$7:$V$106,MATCH(B33,Реестр!$A$7:$A$106,0))="Закрыто",0,1),0) -> 0 | O33: =IF(N33=0,0,IF(F33="","Нет срока",MAX(0,(Продажи!$D$4-F33)*24))) -> 0 | P33: =IF(AND(N33=1,ISNUMBER(F33),F33<=Продажи!$D$4+2,OR(G33="Подача",G33="Дозапрос",G33="Обеспечение",G33="Обязательство клиенту")),1,0) -> 0 | Q33: =IF(AND(N33=1,D33="Продажи",ISNUMBER(O33),O33>0),1,0) -> 0 | R33: =IF(AND(N33=1,H33="Ожидание",D33<>"Продажи"),1,0) -> 0 | S33: =IF(AND(N33=1,OR(Продажи!$I$4="Все",L33=Продажи!$I$4),OR(Продажи!$O$4="Все",M33=Продажи!$O$4)),1,0) -> 0 | T33: =IF(S33=0,0,IF(P33=1,1,IF(AND(ISNUMBER(O33),O33>0),2,IF(AND(ISNUMBER(F33),INT(F33)=INT(Продажи!$D$4)),3,IF(OR(I33="Да",F33=""),4,0))))) -> 0 | U33: =IF(T33=0,"",COUNTIFS($T$7:$T$106,">0",$T$7:$T$106,"<"&T33)+COUNTIFS($T$7:$T$106,T33,$Y$7:$Y$106,"<"&Y33)+COUNTIFS($T$7:T33,T33,$Y$7:Y33,Y33)) | V33: =IF(A33="","",IFERROR(INDEX(Реестр!$W$7:$W$106,MATCH(B33,Реестр!$A$7:$A$106,0)),"Нет связи")) | W33: =IF(A33="","",IFERROR(INDEX(Реестр!$C$7:$C$106,MATCH(B33,Реестр!$A$7:$A$106,0)),"Нет связи")) | X33: =IF(AND(S33=1,I33="Да"),COUNTIFS($S$7:$S$106,1,$I$7:$I$106,"Да",$Y$7:$Y$106,"<"&Y33)+COUNTIFS($S$7:S33,1,$I$7:I33,"Да",$Y$7:Y33,Y33),"") | Y33: =IF(N33=1,IF(ISNUMBER(F33),F33,2958465),"")
L34: =IF(A34="","",IFERROR(INDEX(Реестр!$D$7:$D$106,MATCH(B34,Реестр!$A$7:$A$106,0)),"Нет связи")) | M34: =IF(A34="","",IFERROR(INDEX(Реестр!$E$7:$E$106,MATCH(B34,Реестр!$A$7:$A$106,0)),"Нет связи")) | N34: =IF(AND(A34<>"",H34<>"Закрыто",L34<>"Нет связи"),IF(INDEX(Реестр!$V$7:$V$106,MATCH(B34,Реестр!$A$7:$A$106,0))="Закрыто",0,1),0) -> 0 | O34: =IF(N34=0,0,IF(F34="","Нет срока",MAX(0,(Продажи!$D$4-F34)*24))) -> 0 | P34: =IF(AND(N34=1,ISNUMBER(F34),F34<=Продажи!$D$4+2,OR(G34="Подача",G34="Дозапрос",G34="Обеспечение",G34="Обязательство клиенту")),1,0) -> 0 | Q34: =IF(AND(N34=1,D34="Продажи",ISNUMBER(O34),O34>0),1,0) -> 0 | R34: =IF(AND(N34=1,H34="Ожидание",D34<>"Продажи"),1,0) -> 0 | S34: =IF(AND(N34=1,OR(Продажи!$I$4="Все",L34=Продажи!$I$4),OR(Продажи!$O$4="Все",M34=Продажи!$O$4)),1,0) -> 0 | T34: =IF(S34=0,0,IF(P34=1,1,IF(AND(ISNUMBER(O34),O34>0),2,IF(AND(ISNUMBER(F34),INT(F34)=INT(Продажи!$D$4)),3,IF(OR(I34="Да",F34=""),4,0))))) -> 0 | U34: =IF(T34=0,"",COUNTIFS($T$7:$T$106,">0",$T$7:$T$106,"<"&T34)+COUNTIFS($T$7:$T$106,T34,$Y$7:$Y$106,"<"&Y34)+COUNTIFS($T$7:T34,T34,$Y$7:Y34,Y34)) | V34: =IF(A34="","",IFERROR(INDEX(Реестр!$W$7:$W$106,MATCH(B34,Реестр!$A$7:$A$106,0)),"Нет связи")) | W34: =IF(A34="","",IFERROR(INDEX(Реестр!$C$7:$C$106,MATCH(B34,Реестр!$A$7:$A$106,0)),"Нет связи")) | X34: =IF(AND(S34=1,I34="Да"),COUNTIFS($S$7:$S$106,1,$I$7:$I$106,"Да",$Y$7:$Y$106,"<"&Y34)+COUNTIFS($S$7:S34,1,$I$7:I34,"Да",$Y$7:Y34,Y34),"") | Y34: =IF(N34=1,IF(ISNUMBER(F34),F34,2958465),"")
L35: =IF(A35="","",IFERROR(INDEX(Реестр!$D$7:$D$106,MATCH(B35,Реестр!$A$7:$A$106,0)),"Нет связи")) | M35: =IF(A35="","",IFERROR(INDEX(Реестр!$E$7:$E$106,MATCH(B35,Реестр!$A$7:$A$106,0)),"Нет связи")) | N35: =IF(AND(A35<>"",H35<>"Закрыто",L35<>"Нет связи"),IF(INDEX(Реестр!$V$7:$V$106,MATCH(B35,Реестр!$A$7:$A$106,0))="Закрыто",0,1),0) -> 0 | O35: =IF(N35=0,0,IF(F35="","Нет срока",MAX(0,(Продажи!$D$4-F35)*24))) -> 0 | P35: =IF(AND(N35=1,ISNUMBER(F35),F35<=Продажи!$D$4+2,OR(G35="Подача",G35="Дозапрос",G35="Обеспечение",G35="Обязательство клиенту")),1,0) -> 0 | Q35: =IF(AND(N35=1,D35="Продажи",ISNUMBER(O35),O35>0),1,0) -> 0 | R35: =IF(AND(N35=1,H35="Ожидание",D35<>"Продажи"),1,0) -> 0 | S35: =IF(AND(N35=1,OR(Продажи!$I$4="Все",L35=Продажи!$I$4),OR(Продажи!$O$4="Все",M35=Продажи!$O$4)),1,0) -> 0 | T35: =IF(S35=0,0,IF(P35=1,1,IF(AND(ISNUMBER(O35),O35>0),2,IF(AND(ISNUMBER(F35),INT(F35)=INT(Продажи!$D$4)),3,IF(OR(I35="Да",F35=""),4,0))))) -> 0 | U35: =IF(T35=0,"",COUNTIFS($T$7:$T$106,">0",$T$7:$T$106,"<"&T35)+COUNTIFS($T$7:$T$106,T35,$Y$7:$Y$106,"<"&Y35)+COUNTIFS($T$7:T35,T35,$Y$7:Y35,Y35)) | V35: =IF(A35="","",IFERROR(INDEX(Реестр!$W$7:$W$106,MATCH(B35,Реестр!$A$7:$A$106,0)),"Нет связи")) | W35: =IF(A35="","",IFERROR(INDEX(Реестр!$C$7:$C$106,MATCH(B35,Реестр!$A$7:$A$106,0)),"Нет связи")) | X35: =IF(AND(S35=1,I35="Да"),COUNTIFS($S$7:$S$106,1,$I$7:$I$106,"Да",$Y$7:$Y$106,"<"&Y35)+COUNTIFS($S$7:S35,1,$I$7:I35,"Да",$Y$7:Y35,Y35),"") | Y35: =IF(N35=1,IF(ISNUMBER(F35),F35,2958465),"")
L36: =IF(A36="","",IFERROR(INDEX(Реестр!$D$7:$D$106,MATCH(B36,Реестр!$A$7:$A$106,0)),"Нет связи")) | M36: =IF(A36="","",IFERROR(INDEX(Реестр!$E$7:$E$106,MATCH(B36,Реестр!$A$7:$A$106,0)),"Нет связи")) | N36: =IF(AND(A36<>"",H36<>"Закрыто",L36<>"Нет связи"),IF(INDEX(Реестр!$V$7:$V$106,MATCH(B36,Реестр!$A$7:$A$106,0))="Закрыто",0,1),0) -> 0 | O36: =IF(N36=0,0,IF(F36="","Нет срока",MAX(0,(Продажи!$D$4-F36)*24))) -> 0 | P36: =IF(AND(N36=1,ISNUMBER(F36),F36<=Продажи!$D$4+2,OR(G36="Подача",G36="Дозапрос",G36="Обеспечение",G36="Обязательство клиенту")),1,0) -> 0 | Q36: =IF(AND(N36=1,D36="Продажи",ISNUMBER(O36),O36>0),1,0) -> 0 | R36: =IF(AND(N36=1,H36="Ожидание",D36<>"Продажи"),1,0) -> 0 | S36: =IF(AND(N36=1,OR(Продажи!$I$4="Все",L36=Продажи!$I$4),OR(Продажи!$O$4="Все",M36=Продажи!$O$4)),1,0) -> 0 | T36: =IF(S36=0,0,IF(P36=1,1,IF(AND(ISNUMBER(O36),O36>0),2,IF(AND(ISNUMBER(F36),INT(F36)=INT(Продажи!$D$4)),3,IF(OR(I36="Да",F36=""),4,0))))) -> 0 | U36: =IF(T36=0,"",COUNTIFS($T$7:$T$106,">0",$T$7:$T$106,"<"&T36)+COUNTIFS($T$7:$T$106,T36,$Y$7:$Y$106,"<"&Y36)+COUNTIFS($T$7:T36,T36,$Y$7:Y36,Y36)) | V36: =IF(A36="","",IFERROR(INDEX(Реестр!$W$7:$W$106,MATCH(B36,Реестр!$A$7:$A$106,0)),"Нет связи")) | W36: =IF(A36="","",IFERROR(INDEX(Реестр!$C$7:$C$106,MATCH(B36,Реестр!$A$7:$A$106,0)),"Нет связи")) | X36: =IF(AND(S36=1,I36="Да"),COUNTIFS($S$7:$S$106,1,$I$7:$I$106,"Да",$Y$7:$Y$106,"<"&Y36)+COUNTIFS($S$7:S36,1,$I$7:I36,"Да",$Y$7:Y36,Y36),"") | Y36: =IF(N36=1,IF(ISNUMBER(F36),F36,2958465),"")
... L106: =IF(A106="","",IFERROR(INDEX(Реестр!$D$7:$D$106,MATCH(B106,Реестр!$A$7:$A$106,0)),"Нет связи")) | M106: =IF(A106="","",IFERROR(INDEX(Реестр!$E$7:$E$106,MATCH(B106,Реестр!$A$7:$A$106,0)),"Нет связи")) | N106: =IF(AND(A106<>"",H106<>"Закрыто",L106<>"Нет связи"),IF(INDEX(Реестр!$V$7:$V$106,MATCH(B106,Реестр!$A$7:$A$106,0))="Закрыто",0,1),0) -> 0 | O106: =IF(N106=0,0,IF(F106="","Нет срока",MAX(0,(Продажи!$D$4-F106)*24))) -> 0 | P106: =IF(AND(N106=1,ISNUMBER(F106),F106<=Продажи!$D$4+2,OR(G106="Подача",G106="Дозапрос",G106="Обеспечение",G106="Обязательство клиенту")),1,0) -> 0 | Q106: =IF(AND(N106=1,D106="Продажи",ISNUMBER(O106),O106>0),1,0) -> 0 | R106: =IF(AND(N106=1,H106="Ожидание",D106<>"Продажи"),1,0) -> 0 | S106: =IF(AND(N106=1,OR(Продажи!$I$4="Все",L106=Продажи!$I$4),OR(Продажи!$O$4="Все",M106=Продажи!$O$4)),1,0) -> 0 | T106: =IF(S106=0,0,IF(P106=1,1,IF(AND(ISNUMBER(O106),O106>0),2,IF(AND(ISNUMBER(F106),INT(F106)=INT(Продажи!$D$4)),3,IF(OR(I106="Да",F106=""),4,0))))) -> 0 | U106: =IF(T106=0,"",COUNTIFS($T$7:$T$106,">0",$T$7:$T$106,"<"&T106)+COUNTIFS($T$7:$T$106,T106,$Y$7:$Y$106,"<"&Y106)+COUNTIFS($T$7:T106,T106,$Y$7:Y106,Y106)) | V106: =IF(A106="","",IFERROR(INDEX(Реестр!$W$7:$W$106,MATCH(B106,Реестр!$A$7:$A$106,0)),"Нет связи")) | W106: =IF(A106="","",IFERROR(INDEX(Реестр!$C$7:$C$106,MATCH(B106,Реестр!$A$7:$A$106,0)),"Нет связи")) | X106: =IF(AND(S106=1,I106="Да"),COUNTIFS($S$7:$S$106,1,$I$7:$I$106,"Да",$Y$7:$Y$106,"<"&Y106)+COUNTIFS($S$7:S106,1,$I$7:I106,"Да",$Y$7:Y106,Y106),"") | Y106: =IF(N106=1,IF(ISNUMBER(F106),F106,2958465),"")

Sheet Визуальное оформление
